Workbook

Sheet 說明
A1: 美股觀察表 · 架構範本 v2
B3: 資料由 GitHub Actions 自動更新。Raw 分頁為管線寫入區，請勿手改。
A5: v2 改了什麼
B6: Raw_Q 從 32 欄砍到 14 欄。只留下你指定的指標，以及計算這些指標所必需的原始欄位。
B7: 刪掉的是：營益率、FCF、杜邦拆解、ROIC、淨負債、有效稅率、adj_gap、PE 百分位、2年CAGR、
B8: 近4季平均加速度、EPS加速度、年度加速度 —— 這些都是我加的，不是你要的。
B9: 新增：殖利率（需要 Raw_Q 的 dps 欄）。
A11: Raw_Q 的 14 欄，每一欄都有用途
B12: ticker / period / fy / fq / period_end → 鍵值與期別對齊
B13: is_est / est_source → 區分實際與預估，避免預估污染歷史
B14: eps_basis → EPS 口徑標記：street=市場口徑；gaap=四層來源
B15: 全部失敗時的降級，PE/PEG 會失真，須注意
B16: revenue → 營收成長率、毛利率分母
B17: gross_profit → 毛利率分子
B18: eps_diluted_adj → EPS、PE、PEG、EPS成長率
B19: shares_diluted → 反推 ROE 淨利、ROE_Forward 的每股淨值
B20: total_equity → ROE 分母
B21: dps → 殖利率
B22: price_at_end → 歷史 PE、PEG_T、歷史殖利率
A24: 抓不到的東西（誠實說明）
B25: Adjusted 淨利：沒有任何 API 提供。它不是損益表項目，只存在於公司財報的 non-GAAP 對帳附註。
B26: 本表用「逐季 adjusted EPS × 稀釋股數」反推，逐季相乘再加總比用單一股數準，但仍是近似值。
B27: Adjusted EPS 本身拿得到，但不是從損益表，是從「歷史財報實際值」那類端點的 actual EPS。
B28: fy / fq：多數來源不直接提供公司自己的財年標號，要從 period_end 推算。
B29: 歷史的 Forward PE（每一年當時的前瞻本益比）：拿不到，歷史分析師共識一般不留存。
A31: 年 與 季 分在哪裡
B32: 年度層 → 「年度檢視」：每一列＝一個完整財年，由 Raw_Q 的季度資料 rollup 而來。
B33: 季度層 → 「季度檢視」：每一列＝一個財季，另有年 × 季矩陣做季節可比的閱讀。
B34: 橫向層 → 「Dashboard」：每一列＝一檔股票，用來跨標的比較與篩選。
B35: 三層共用同一份 Raw_Q，年度值永遠等於該年四季加總，不會有兩套打架的資料。
A37: 加速度只做在季度層
B38: 季度成長率(QoQ) ＝ 本季營收 ÷ 上一季營收 − 1。
B39: 加速度(pp) ＝ 本季QoQ − 上一季QoQ。字面上就是「這季成長率有沒有比上季快」。
B40: 但這一欄會被季節性主宰：旺季 QoQ 天生高、淡季天生低，每年在同一季重複同樣的震盪。
B41: 同期加速度(pp) ＝ 本季QoQ − 去年同一財季的QoQ。一樣在比季度成長率，但基準換成
B42: 去年同一季，季節性自動抵消。實務上這一欄才有訊號，建議以它為主、加速度當參考。
B43: 年度層刻意不放加速度：一年才一個點，訊號遲鈍到失去意義。
A45: 口徑
B46: EPS / PE / PEG / EPS成長 → Adjusted，與分析師預估和市場定價同口徑。
B47: ROE → 分子用 adjusted EPS 反推的淨利，分母用 GAAP 股東權益（你選的口徑）。
B48: 注意：這代表 ROE 數字會與各大財經網站（多用 GAAP 淨利）不同，這是刻意的。
A50: 顏色慣例
B51: 藍字＝你手動輸入 ｜ 黑字＝公式 ｜ 綠字＝跨分頁連結 ｜ 黃底＝資料管線寫入區，請勿手改
A53: 新增一檔股票
B54: ① Tickers 第 2~21 列往下打一列 → ② 重跑資料管線 → ③ Excel 按「資料 → 全部重新整理」

Sheet Dashboard
A1: 基本 | E1: 估值 | I1: 殖利率 | K1: 成長 | S1: 毛利率 | W1: ROE | Z1: 預估
A2: Ticker | B2: 公司 | C2: 等級 | D2: 股價 | E2: PE_TTM | F2: PE Forward | G2: PEG_T | H2: PEG_F | I2: 殖利率 | J2: 配息YoY | K2: 營收QoQ | L2: 上季QoQ | M2: 加速度(pp) | N2: 動能判讀 | O2: 同期加速度(pp) | P2: 營收YoY | Q2: EPS_YoY | R2: EPS_TTM_YoY | S2: 毛利率 | T2: 5年平均 | U2: vs5年(bps) | V2: ΔGM_YoY(bps) | W2: ROE_TTM | X2: ROE_5年平均 | Y2: ROE Forward | Z2: 當季EPS預估 | AA2: 預估期別 | AB2: 來源 | AC2: 下次財報
A3: =IF(Calc!$A$2="","",Calc!A$2) -> AAPL | B3: =IF(Calc!$A$2="","",Calc!B$2) -> Apple Inc. | C3: =IF(Calc!$A$2="","",Calc!C$2) -> 0 | D3: =IF(Calc!$A$2="","",Calc!D$2) -> 329.35999 | E3: =IF(Calc!$A$2="","",Calc!J$2) -> 37.770641 | F3: =IF(Calc!$A$2="","",Calc!L$2) -> 34.507766 | G3: =IF(Calc!$A$2="","",Calc!N$2) -> 1.1685846 | H3: =IF(Calc!$A$2="","",Calc!O$2) -> 3.9973204 | I3: =IF(Calc!$A$2="","",Calc!Q$2) -> 0.0031880011 | J3: =IF(Calc!$A$2="","",Calc!R$2) -> 0.03960396 | K3: =IF(Calc!$A$2="","",Calc!T$2) -> -0.015892574 | L3: =IF(Calc!$A$2="","",Calc!U$2) -> -0.22657837 | M3: =IF(Calc!$A$2="","",Calc!V$2) -> 21.068579 | N3: =IF(Calc!$A$2="","",Calc!W$2) -> 衰退但收斂 | O3: =IF(Calc!$A$2="","",Calc!X$2) -> -0.20186874 | P3: =IF(Calc!$A$2="","",Calc!S$2) -> 0.16356502 | Q3: =IF(Calc!$A$2="","",Calc!Y$2) -> 0.2866242 | R3: =IF(Calc!$A$2="","",Calc!I$2) -> 0.323217 | S3: =IF(Calc!$A$2="","",Calc!Z$2) -> 0.48652916 | T3: =IF(Calc!$A$2="","",Calc!AA$2) -> 0.45744556 | U3: =IF(Calc!$A$2="","",Calc!AB$2) -> 290.83593 | V3: =IF(Calc!$A$2="","",Calc!AC$2) -> 356.55013 | W3: =IF(Calc!$A$2="","",Calc!AF$2) -> 1.486954 | X3: =IF(Calc!$A$2="","",Calc!AG$2) -> 1.4327803 | Y3: =IF(Calc!$A$2="","",Calc!AH$2) -> 1.2063557 | Z3: =IF(Calc!$A$2="","",Calc!AI$2) -> 1.97656 | AA3: =IF(Calc!$A$2="","",Calc!AJ$2) -> FY2026Q4E | AB3: =IF(Calc!$A$2="","",Calc!AK$2) -> consensus | AC3: =IF(Calc!$A$2="","",Calc!AM$2) -> 46324
A4: =IF(Calc!$A$3="","",Calc!A$3) -> MSFT | B4: =IF(Calc!$A$3="","",Calc!B$3) -> Microsoft Corporation | C4: =IF(Calc!$A$3="","",Calc!C$3) -> 0 | D4: =IF(Calc!$A$3="","",Calc!D$3) -> 500.84 | E4: =IF(Calc!$A$3="","",Calc!J$3) -> 28.983796 | F4: =IF(Calc!$A$3="","",Calc!L$3) -> 24.350072 | G4: =IF(Calc!$A$3="","",Calc!N$3) -> 1.0860961 | H4: =IF(Calc!$A$3="","",Calc!O$3) -> 1.2552977 | I4: =IF(Calc!$A$3="","",Calc!Q$3) -> 0.0071080585 | J4: =IF(Calc!$A$3="","",Calc!R$3) -> 0.098765432 | K4: =IF(Calc!$A$3="","",Calc!T$3) -> 0.085913182 | L4: =IF(Calc!$A$3="","",Calc!U$3) -> 0.01984669 | M4: =IF(Calc!$A$3="","",Calc!V$3) -> 6.6066492 | N4: =IF(Calc!$A$3="","",Calc!W$3) -> 成長且加速 | O4: =IF(Calc!$A$3="","",Calc!X$3) -> -0.50724601 | P4: =IF(Calc!$A$3="","",Calc!S$3) -> 0.17747021 | Q4: =IF(Calc!$A$3="","",Calc!Y$3) -> 0.29863014 | R4: =IF(Calc!$A$3="","",Calc!I$3) -> 0.26686217 | S4: =IF(Calc!$A$3="","",Calc!Z$3) -> 0.67944093 | T4: =IF(Calc!$A$3="","",Calc!AA$3) -> 0.68725559 | U4: =IF(Calc!$A$3="","",Calc!AB$3) -> -78.146559 | V4: =IF(Calc!$A$3="","",Calc!AC$3) -> -138.79259 | W4: =IF(Calc!$A$3="","",Calc!AF$3) -> 0.32776313 | X4: =IF(Calc!$A$3="","",Calc!AG$3) -> 0.31321768 | Y4: =IF(Calc!$A$3="","",Calc!AH$3) -> 0.33245009 | Z4: =IF(Calc!$A$3="","",Calc!AI$3) -> 4.72092 | AA4: =IF(Calc!$A$3="","",Calc!AJ$3) -> FY2027Q1E | AB4: =IF(Calc!$A$3="","",Calc!AK$3) -> consensus | AC4: =IF(Calc!$A$3="","",Calc!AM$3) -> 46323
A5: =IF(Calc!$A$4="","",Calc!A$4) -> NVDA | B5: =IF(Calc!$A$4="","",Calc!B$4) -> NVIDIA Corporation | C5: =IF(Calc!$A$4="","",Calc!C$4) -> 0 | D5: =IF(Calc!$A$4="","",Calc!D$4) -> 212.27 | E5: =IF(Calc!$A$4="","",Calc!J$4) -> 30.281028 | F5: =IF(Calc!$A$4="","",Calc!L$4) -> 16.044669 | G5: =IF(Calc!$A$4="","",Calc!N$4) -> 0.3124651 | H5: =IF(Calc!$A$4="","",Calc!O$4) -> 0.23672348 | I5: =IF(Calc!$A$4="","",Calc!Q$4) -> 0.0013190747 | J5: =IF(Calc!$A$4="","",Calc!R$4) -> 6 | K5: =IF(Calc!$A$4="","",Calc!T$4) -> 2.7121853 | L5: =IF(Calc!$A$4="","",Calc!U$4) -> 0.19798318 | M5: =IF(Calc!$A$4="","",Calc!V$4) -> 251.42021 | N5: =IF(Calc!$A$4="","",Calc!W$4) -> 成長且加速 | O5: =IF(Calc!$A$4="","",Calc!X$4) -> 265.13392 | P5: =IF(Calc!$A$4="","",Calc!S$4) -> 5.4816122 | Q5: =IF(Calc!$A$4="","",Calc!Y$4) -> 1.1142857 | R5: =IF(Calc!$A$4="","",Calc!I$4) -> 0.96910112 | S5: =IF(Calc!$A$4="","",Calc!Z$4) -> 0.7461773 | T5: =IF(Calc!$A$4="","",Calc!AA$4) -> 0.72932076 | U5: =IF(Calc!$A$4="","",Calc!AB$4) -> 168.56542 | V5: =IF(Calc!$A$4="","",Calc!AC$4) -> 225.07118 | W5: =IF(Calc!$A$4="","",Calc!AF$4) -> 1.0402526 | X5: =IF(Calc!$A$4="","",Calc!AG$4) -> 0.6367055 | Y5: =IF(Calc!$A$4="","",Calc!AH$4) -> 0.99161671 | Z5: =IF(Calc!$A$4="","",Calc!AI$4) -> 2.34 | AA5: =IF(Calc!$A$4="","",Calc!AJ$4) -> FY2027Q3E | AB5: =IF(Calc!$A$4="","",Calc!AK$4) -> consensus | AC5: =IF(Calc!$A$4="","",Calc!AM$4) -> 46343
A6: =IF(Calc!$A$5="","",Calc!A$5) -> AAOI | B6: =IF(Calc!$A$5="","",Calc!B$5) -> Applied Optoelectronics, Inc. | C6: =IF(Calc!$A$5="","",Calc!C$5) -> 觀察 | D6: =IF(Calc!$A$5="","",Calc!D$5) -> 96.349998 | E6: =IF(Calc!$A$5="","",Calc!J$5) -> N/M | F6: =IF(Calc!$A$5="","",Calc!L$5) -> 27.909229 | G6: =IF(Calc!$A$5="","",Calc!N$5) -> N/M | H6: =IF(Calc!$A$5="","",Calc!O$5) -> 0.04838928 | I6: =IF(Calc!$A$5="","",Calc!Q$5) -> 不配息 | J6: =IF(Calc!$A$5="","",Calc!R$5) | K6: =IF(Calc!$A$5="","",Calc!T$5) -> 0.26979569 | L6: =IF(Calc!$A$5="","",Calc!U$5) -> 0.12563862 | M6: =IF(Calc!$A$5="","",Calc!V$5) -> 14.415707 | N6: =IF(Calc!$A$5="","",Calc!W$5) -> 成長且加速 | O6: =IF(Calc!$A$5="","",Calc!X$5) -> 23.882202 | P6: =IF(Calc!$A$5="","",Calc!S$5) -> 0.86418914 | Q6: =IF(Calc!$A$5="","",Calc!Y$5) -> -1.375 | R6: =IF(Calc!$A$5="","",Calc!I$5) -> -0.73170732 | S6: =IF(Calc!$A$5="","",Calc!Z$5) -> 0.28915885 | T6: =IF(Calc!$A$5="","",Calc!AA$5) -> 0.25346476 | U6: =IF(Calc!$A$5="","",Calc!AB$5) -> 356.94087 | V6: =IF(Calc!$A$5="","",Calc!AC$5) -> -254.52329 | W6: =IF(Calc!$A$5="","",Calc!AF$5) -> -0.0065240998 | X6: =IF(Calc!$A$5="","",Calc!AG$5) -> -0.12618364 | Y6: =IF(Calc!$A$5="","",Calc!AH$5) -> 0.033252643 | Z6: =IF(Calc!$A$5="","",Calc!AI$5) -> 0.14333 | AA6: =IF(Calc!$A$5="","",Calc!AJ$5) -> FY2026Q3E | AB6: =IF(Calc!$A$5="","",Calc!AK$5) -> consensus | AC6: =IF(Calc!$A$5="","",Calc!AM$5) -> 46331
A7: =IF(Calc!$A$6="","",Calc!A$6) -> MRVL | B7: =IF(Calc!$A$6="","",Calc!B$6) -> Marvell Technology, Inc. | C7: =IF(Calc!$A$6="","",Calc!C$6) -> 池子 | D7: =IF(Calc!$A$6="","",Calc!D$6) -> 224.32001 | E7: =IF(Calc!$A$6="","",Calc!J$6) -> 67.97576 | F7: =IF(Calc!$A$6="","",Calc!L$6) -> 38.692999 | G7: =IF(Calc!$A$6="","",Calc!N$6) -> 1.6092221 | H7: =IF(Calc!$A$6="","",Calc!O$6) -> 0.63972433 | I7: =IF(Calc!$A$6="","",Calc!Q$6) -> 0.0010699001 | J7: =IF(Calc!$A$6="","",Calc!R$6) -> 0 | K7: =IF(Calc!$A$6="","",Calc!T$6) -> 0.13297212 | L7: =IF(Calc!$A$6="","",Calc!U$6) -> 0.089737234 | M7: =IF(Calc!$A$6="","",Calc!V$6) -> 4.323489 | N7: =IF(Calc!$A$6="","",Calc!W$6) -> 成長且加速 | O7: =IF(Calc!$A$6="","",Calc!X$6) -> 7.4511721 | P7: =IF(Calc!$A$6="","",Calc!S$6) -> 0.36548527 | Q7: =IF(Calc!$A$6="","",Calc!Y$6) -> 0.40298507 | R7: =IF(Calc!$A$6="","",Calc!I$6) -> 0.42241379 | S7: =IF(Calc!$A$6="","",Calc!Z$6) -> 0.52211041 | T7: =IF(Calc!$A$6="","",Calc!AA$6) -> 0.47838083 | U7: =IF(Calc!$A$6="","",Calc!AB$6) -> 437.29583 | V7: =IF(Calc!$A$6="","",Calc!AC$6) -> 276.13108 | W7: =IF(Calc!$A$6="","",Calc!AF$6) -> 0.18288815 | X7: =IF(Calc!$A$6="","",Calc!AG$6) -> 0.098821299 | Y7: =IF(Calc!$A$6="","",Calc!AH$6) -> 0.20941497 | Z7: =IF(Calc!$A$6="","",Calc!AI$6) -> 1.1004 | AA7: =IF(Calc!$A$6="","",Calc!AJ$6) -> FY2027Q3E | AB7: =IF(Calc!$A$6="","",Calc!AK$6) -> consensus | AC7: =IF(Calc!$A$6="","",Calc!AM$6) -> 46357
A8: =IF(Calc!$A$7="","",Calc!A$7) -> MU | B8: =IF(Calc!$A$7="","",Calc!B$7) -> Micron Technology, Inc. | C8: =IF(Calc!$A$7="","",Calc!C$7) -> 池子 | D8: =IF(Calc!$A$7="","",Calc!D$7) -> 932.77002 | E8: =IF(Calc!$A$7="","",Calc!J$7) -> 20.673094 | F8: =IF(Calc!$A$7="","",Calc!L$7) -> 5.9767637 | G8: =IF(Calc!$A$7="","",Calc!N$7) -> 0.034419526 | H8: =IF(Calc!$A$7="","",Calc!O$7) -> 0.053121205 | I8: =IF(Calc!$A$7="","",Calc!Q$7) -> 0.00053067743 | J8: =IF(Calc!$A$7="","",Calc!R$7) -> 0.076086957 | K8: =IF(Calc!$A$7="","",Calc!T$7) -> 0.73746857 | L8: =IF(Calc!$A$7="","",Calc!U$7) -> 0.74888221 | M8: =IF(Calc!$A$7="","",Calc!V$7) -> -1.1413644 | N8: =IF(Calc!$A$7="","",Calc!W$7) -> 成長但減速 | O8: =IF(Calc!$A$7="","",Calc!X$7) -> 58.249526 | P8: =IF(Calc!$A$7="","",Calc!S$7) -> 3.4571551 | Q8: =IF(Calc!$A$7="","",Calc!Y$7) -> 12.146597 | R8: =IF(Calc!$A$7="","",Calc!I$7) -> 6.0062112 | S8: =IF(Calc!$A$7="","",Calc!Z$7) -> 0.72569068 | T8: =IF(Calc!$A$7="","",Calc!AA$7) -> 0.49656668 | U8: =IF(Calc!$A$7="","",Calc!AB$7) -> 2291.24 | V8: =IF(Calc!$A$7="","",Calc!AC$7) -> 4684.5571 | W8: =IF(Calc!$A$7="","",Calc!AF$7) -> 0.68065279 | X8: =IF(Calc!$A$7="","",Calc!AG$7) -> 0.17985176 | Y8: =IF(Calc!$A$7="","",Calc!AH$7) -> 0.83482975 | Z8: =IF(Calc!$A$7="","",Calc!AI$7) -> 31.28341 | AA8: =IF(Calc!$A$7="","",Calc!AJ$7) -> FY2026Q4E | AB8: =IF(Calc!$A$7="","",Calc!AK$7) -> consensus | AC8: =IF(Calc!$A$7="","",Calc!AM$7) -> 46295
A9: =IF(Calc!$A$8="","",Calc!A$8) -> TER | B9: =IF(Calc!$A$8="","",Calc!B$8) -> Teradyne, Inc. | C9: =IF(Calc!$A$8="","",Calc!C$8) -> 池子 | D9: =IF(Calc!$A$8="","",Calc!D$8) -> 328.125 | E9: =IF(Calc!$A$8="","",Calc!J$8) -> 42.724609 | F9: =IF(Calc!$A$8="","",Calc!L$8) -> 30.098632 | G9: =IF(Calc!$A$8="","",Calc!N$8) -> 0.3003038 | H9: =IF(Calc!$A$8="","",Calc!O$8) -> 1.0683958 | I9: =IF(Calc!$A$8="","",Calc!Q$8) -> 0.0015238095 | J9: =IF(Calc!$A$8="","",Calc!R$8) -> 0.041666667 | K9: =IF(Calc!$A$8="","",Calc!T$8) -> 0.036254361 | L9: =IF(Calc!$A$8="","",Calc!U$8) -> 0.18383661 | M9: =IF(Calc!$A$8="","",Calc!V$8) -> -14.758225 | N9: =IF(Calc!$A$8="","",Calc!W$8) -> 成長但減速 | O9: =IF(Calc!$A$8="","",Calc!X$8) -> 8.566954 | P9: =IF(Calc!$A$8="","",Calc!S$8) -> 1.0389631 | Q9: =IF(Calc!$A$8="","",Calc!Y$8) -> 3.3333333 | R9: =IF(Calc!$A$8="","",Calc!I$8) -> 1.4227129 | S9: =IF(Calc!$A$8="","",Calc!Z$8) -> 0.59241591 | T9: =IF(Calc!$A$8="","",Calc!AA$8) -> 0.5883855 | U9: =IF(Calc!$A$8="","",Calc!AB$8) -> 40.304133 | V9: =IF(Calc!$A$8="","",Calc!AC$8) -> 256.28721 | W9: =IF(Calc!$A$8="","",Calc!AF$8) -> 0.38634513 | X9: =IF(Calc!$A$8="","",Calc!AG$8) -> 0.19783528 | Y9: =IF(Calc!$A$8="","",Calc!AH$8) -> 0.41709782 | Z9: =IF(Calc!$A$8="","",Calc!AI$8) -> 2.05052 | AA9: =IF(Calc!$A$8="","",Calc!AJ$8) -> FY2026Q3E | AB9: =IF(Calc!$A$8="","",Calc!AK$8) -> consensus | AC9: =IF(Calc!$A$8="","",Calc!AM$8) -> 46316
A10: =IF(Calc!$A$9="","",Calc!A$9) -> DELL | B10: =IF(Calc!$A$9="","",Calc!B$9) -> Dell Technologies Inc. | C10: =IF(Calc!$A$9="","",Calc!C$9) -> 池子 | D10: =IF(Calc!$A$9="","",Calc!D$9) -> 555.69012 | E10: =IF(Calc!$A$9="","",Calc!J$9) -> 40.680097 | F10: =IF(Calc!$A$9="","",Calc!L$9) -> 22.117062 | G10: =IF(Calc!$A$9="","",Calc!N$9) -> 0.62416401 | H10: =IF(Calc!$A$9="","",Calc!O$9) -> N/M | I10: =IF(Calc!$A$9="","",Calc!Q$9) -> 0.0039680388 | J10: =IF(Calc!$A$9="","",Calc!R$9) -> 0.18548387 | K10: =IF(Calc!$A$9="","",Calc!T$9) -> 0.31346056 | L10: =IF(Calc!$A$9="","",Calc!U$9) -> 0.23603036 | M10: =IF(Calc!$A$9="","",Calc!V$9) -> 7.7430194 | N10: =IF(Calc!$A$9="","",Calc!W$9) -> 成長且加速 | O10: =IF(Calc!$A$9="","",Calc!X$9) -> 33.143922 | P10: =IF(Calc!$A$9="","",Calc!S$9) -> 0.8753529 | Q10: =IF(Calc!$A$9="","",Calc!Y$9) -> 2.1354839 | R10: =IF(Calc!$A$9="","",Calc!I$9) -> 0.65175333 | S10: =IF(Calc!$A$9="","",Calc!Z$9) -> 0.19068372 | T10: =IF(Calc!$A$9="","",Calc!AA$9) -> 0.20559039 | U10: =IF(Calc!$A$9="","",Calc!AB$9) -> -149.06667 | V10: =IF(Calc!$A$9="","",Calc!AC$9) -> -336.80426 | W10: =IF(Calc!$A$9="","",Calc!AF$9) -> N/M | X10: =IF(Calc!$A$9="","",Calc!AG$9) | Y10: =IF(Calc!$A$9="","",Calc!AH$9) -> N/M | Z10: =IF(Calc!$A$9="","",Calc!AI$9) -> 4.91986 | AA10: =IF(Calc!$A$9="","",Calc!AJ$9) -> FY2027Q2E | AB10: =IF(Calc!$A$9="","",Calc!AK$9) -> consensus | AC10: =IF(Calc!$A$9="","",Calc!AM$9) -> 46353
A11: =IF(Calc!$A$10="","",Calc!A$10) -> DIOD | B11: =IF(Calc!$A$10="","",Calc!B$10) -> Diodes Incorporated | C11: =IF(Calc!$A$10="","",Calc!C$10) -> 池子 | D11: =IF(Calc!$A$10="","",Calc!D$10) -> 87.529999 | E11: =IF(Calc!$A$10="","",Calc!J$10) -> 47.570652 | F11: =IF(Calc!$A$10="","",Calc!L$10) -> 17.228689 | G11: =IF(Calc!$A$10="","",Calc!N$10) -> 0.91365854 | H11: =IF(Calc!$A$10="","",Calc!O$10) -> 0.21166675 | I11: =IF(Calc!$A$10="","",Calc!Q$10) -> 不配息 | J11: =IF(Calc!$A$10="","",Calc!R$10) | K11: =IF(Calc!$A$10="","",Calc!T$10) -> 0.098804588 | L11: =IF(Calc!$A$10="","",Calc!U$10) -> 0.035469306 | M11: =IF(Calc!$A$10="","",Calc!V$10) -> 6.3335282 | N11: =IF(Calc!$A$10="","",Calc!W$10) -> 成長且加速 | O11: =IF(Calc!$A$10="","",Calc!X$10) -> -0.38682971 | P11: =IF(Calc!$A$10="","",Calc!S$10) -> 0.21658766 | Q11: =IF(Calc!$A$10="","",Calc!Y$10) -> 1.1875 | R11: =IF(Calc!$A$10="","",Calc!I$10) -> 0.52066116 | S11: =IF(Calc!$A$10="","",Calc!Z$10) -> 0.31734388 | T11: =IF(Calc!$A$10="","",Calc!AA$10) -> 0.36715426 | U11: =IF(Calc!$A$10="","",Calc!AB$10) -> -498.10387 | V11: =IF(Calc!$A$10="","",Calc!AC$10) -> 163.04763 | W11: =IF(Calc!$A$10="","",Calc!AF$10) -> 0.044528376 | X11: =IF(Calc!$A$10="","",Calc!AG$10) -> 0.097373429 | Y11: =IF(Calc!$A$10="","",Calc!AH$10) -> 0.076724004 | Z11: =IF(Calc!$A$10="","",Calc!AI$10) -> 1.055 | AA11: =IF(Calc!$A$10="","",Calc!AJ$10) -> FY2026Q3E | AB11: =IF(Calc!$A$10="","",Calc!AK$10) -> consensus | AC11: =IF(Calc!$A$10="","",Calc!AM$10) -> 46331
A12: =IF(Calc!$A$11="","",Calc!A$11) -> CRWD | B12: =IF(Calc!$A$11="","",Calc!B$11) -> CrowdStrike Holdings, Inc. | C12: =IF(Calc!$A$11="","",Calc!C$11) -> 池子 | D12: =IF(Calc!$A$11="","",Calc!D$11) -> 238.23 | E12: =IF(Calc!$A$11="","",Calc!J$11) -> 214.62162 | F12: =IF(Calc!$A$11="","",Calc!L$11) -> 161.6599 | G12: =IF(Calc!$A$11="","",Calc!N$11) -> 9.1980693 | H12: =IF(Calc!$A$11="","",Calc!O$11) -> 5.8046819 | I12: =IF(Calc!$A$11="","",Calc!Q$11) -> 不配息 | J12: =IF(Calc!$A$11="","",Calc!R$11) | K12: =IF(Calc!$A$11="","",Calc!T$11) -> 2.8943649 | L12: =IF(Calc!$A$11="","",Calc!U$11) -> 0.061479651 | M12: =IF(Calc!$A$11="","",Calc!V$11) -> 283.28853 | N12: =IF(Calc!$A$11="","",Calc!W$11) -> 成長且加速 | O12: =IF(Calc!$A$11="","",Calc!X$11) -> 283.49885 | P12: =IF(Calc!$A$11="","",Calc!S$11) -> 3.6162246 | Q12: =IF(Calc!$A$11="","",Calc!Y$11) -> 0.34782609 | R12: =IF(Calc!$A$11="","",Calc!I$11) -> 0.23333333 | S12: =IF(Calc!$A$11="","",Calc!Z$11) -> 0.75319547 | T12: =IF(Calc!$A$11="","",Calc!AA$11) -> 0.74780075 | U12: =IF(Calc!$A$11="","",Calc!AB$11) -> 53.947188 | V12: =IF(Calc!$A$11="","",Calc!AC$11) -> 173.37196 | W12: =IF(Calc!$A$11="","",Calc!AF$11) -> 0.25655295 | X12: =IF(Calc!$A$11="","",Calc!AG$11) -> 0.1266593 | Y12: =IF(Calc!$A$11="","",Calc!AH$11) -> 0.25186078 | Z12: =IF(Calc!$A$11="","",Calc!AI$11) -> 0.31116 | AA12: =IF(Calc!$A$11="","",Calc!AJ$11) -> FY2027Q3E | AB12: =IF(Calc!$A$11="","",Calc!AK$11) -> consensus | AC12: =IF(Calc!$A$11="","",Calc!AM$11) -> 46357
A13: =IF(Calc!$A$12="","",Calc!A$12) -> NET | B13: =IF(Calc!$A$12="","",Calc!B$12) -> Cloudflare, Inc. | C13: =IF(Calc!$A$12="","",Calc!C$12) -> 核心 | D13: =IF(Calc!$A$12="","",Calc!D$12) -> 327.565 | E13: =IF(Calc!$A$12="","",Calc!J$12) -> 300.51835 | F13: =IF(Calc!$A$12="","",Calc!L$12) -> 210.64263 | G13: =IF(Calc!$A$12="","",Calc!N$12) -> 6.9210287 | H13: =IF(Calc!$A$12="","",Calc!O$12) -> 6.4428141 | I13: =IF(Calc!$A$12="","",Calc!Q$12) -> 不配息 | J13: =IF(Calc!$A$12="","",Calc!R$12) | K13: =IF(Calc!$A$12="","",Calc!T$12) -> 0.088011817 | L13: =IF(Calc!$A$12="","",Calc!U$12) -> 0.041086595 | M13: =IF(Calc!$A$12="","",Calc!V$12) -> 4.6925222 | N13: =IF(Calc!$A$12="","",Calc!W$12) -> 成長且加速 | O13: =IF(Calc!$A$12="","",Calc!X$12) -> 1.8652807 | P13: =IF(Calc!$A$12="","",Calc!S$12) -> 0.3586556 | Q13: =IF(Calc!$A$12="","",Calc!Y$12) -> 0.38095238 | R13: =IF(Calc!$A$12="","",Calc!I$12) -> 0.43421053 | S13: =IF(Calc!$A$12="","",Calc!Z$12) -> 0.72576512 | T13: =IF(Calc!$A$12="","",Calc!AA$12) -> 0.75272195 | U13: =IF(Calc!$A$12="","",Calc!AB$12) -> -269.56831 | V13: =IF(Calc!$A$12="","",Calc!AC$12) -> -311.98809 | W13: =IF(Calc!$A$12="","",Calc!AF$12) -> 0.26822772 | X13: =IF(Calc!$A$12="","",Calc!AG$12) -> 0.18858849 | Y13: =IF(Calc!$A$12="","",Calc!AH$12) -> 0.27628087 | Z13: =IF(Calc!$A$12="","",Calc!AI$12) -> 0.34308 | AA13: =IF(Calc!$A$12="","",Calc!AJ$12) -> FY2026Q3E | AB13: =IF(Calc!$A$12="","",Calc!AK$12) -> consensus | AC13: =IF(Calc!$A$12="","",Calc!AM$12) -> 46324
A14: =IF(Calc!$A$13="","",Calc!A$13) -> CEG | B14: =IF(Calc!$A$13="","",Calc!B$13) -> Constellation Energy Corporation | C14: =IF(Calc!$A$13="","",Calc!C$13) -> 池子 | D14: =IF(Calc!$A$13="","",Calc!D$13) -> 261.25 | E14: =IF(Calc!$A$13="","",Calc!J$13) -> 24.57667 | F14: =IF(Calc!$A$13="","",Calc!L$13) -> 20.122671 | G14: =IF(Calc!$A$13="","",Calc!N$13) -> 1.6203047 | H14: =IF(Calc!$A$13="","",Calc!O$13) -> 1.9923677 | I14: =IF(Calc!$A$13="","",Calc!Q$13) -> 0.0062392344 | J14: =IF(Calc!$A$13="","",Calc!R$13) -> 0.099865047 | K14: =IF(Calc!$A$13="","",Calc!T$13) -> -0.3253012 | L14: =IF(Calc!$A$13="","",Calc!U$13) -> 0.83108331 | M14: =IF(Calc!$A$13="","",Calc!V$13) -> -115.63845 | N14: =IF(Calc!$A$13="","",Calc!W$13) -> 衰退且惡化 | O14: =IF(Calc!$A$13="","",Calc!X$13) -> -22.409319 | P14: =IF(Calc!$A$13="","",Calc!S$13) -> 0.2299623 | Q14: =IF(Calc!$A$13="","",Calc!Y$13) -> 0.33507853 | R14: =IF(Calc!$A$13="","",Calc!I$13) -> 0.15167931 | S14: =IF(Calc!$A$13="","",Calc!Z$13) -> 0.21426287 | T14: =IF(Calc!$A$13="","",Calc!AA$13) -> 0.17324422 | U14: =IF(Calc!$A$13="","",Calc!AB$13) -> 410.18656 | V14: =IF(Calc!$A$13="","",Calc!AC$13) -> -579.5696 | W14: =IF(Calc!$A$13="","",Calc!AF$13) -> 0.15672148 | X14: =IF(Calc!$A$13="","",Calc!AG$13) -> 0.1437463 | Y14: =IF(Calc!$A$13="","",Calc!AH$13) -> 0.13642297 | Z14: =IF(Calc!$A$13="","",Calc!AI$13) -> 3.74379 | AA14: =IF(Calc!$A$13="","",Calc!AJ$13) -> FY2026Q3E | AB14: =IF(Calc!$A$13="","",Calc!AK$13) -> consensus | AC14: =IF(Calc!$A$13="","",Calc!AM$13) -> 46335
A15: =IF(Calc!$A$14="","",Calc!A$14) -> AMZN | B15: =IF(Calc!$A$14="","",Calc!B$14) -> Amazon.com, Inc. | C15: =IF(Calc!$A$14="","",Calc!C$14) -> 池子 | D15: =IF(Calc!$A$14="","",Calc!D$14) -> 248.92999 | E15: =IF(Calc!$A$14="","",Calc!J$14) -> 20.026548 | F15: =IF(Calc!$A$14="","",Calc!L$14) -> 22.233959 | G15: =IF(Calc!$A$14="","",Calc!N$14) -> 0.22380606 | H15: =IF(Calc!$A$14="","",Calc!O$14) -> N/M | I15: =IF(Calc!$A$14="","",Calc!Q$14) -> 不配息 | J15: =IF(Calc!$A$14="","",Calc!R$14) | K15: =IF(Calc!$A$14="","",Calc!T$14) -> 3.2732717 | L15: =IF(Calc!$A$14="","",Calc!U$14) -> -0.14933969 | M15: =IF(Calc!$A$14="","",Calc!V$14) -> 342.26114 | N15: =IF(Calc!$A$14="","",Calc!W$14) -> 成長且加速 | O15: =IF(Calc!$A$14="","",Calc!X$14) -> 319.59592 | P15: =IF(Calc!$A$14="","",Calc!S$14) -> 3.6253473 | Q15: =IF(Calc!$A$14="","",Calc!Y$14) -> 2.422619 | R15: =IF(Calc!$A$14="","",Calc!I$14) -> 0.89481707 | S15: =IF(Calc!$A$14="","",Calc!Z$14) -> 0.50548953 | T15: =IF(Calc!$A$14="","",Calc!AA$14) -> 0.48168494 | U15: =IF(Calc!$A$14="","",Calc!AB$14) -> 238.04584 | V15: =IF(Calc!$A$14="","",Calc!AC$14) -> -104.42846 | W15: =IF(Calc!$A$14="","",Calc!AF$14) -> 0.30551916 | X15: =IF(Calc!$A$14="","",Calc!AG$14) -> 0.16680834 | Y15: =IF(Calc!$A$14="","",Calc!AH$14) -> 0.25485629 | Z15: =IF(Calc!$A$14="","",Calc!AI$14) -> 1.95485 | AA15: =IF(Calc!$A$14="","",Calc!AJ$14) -> FY2026Q3E | AB15: =IF(Calc!$A$14="","",Calc!AK$14) -> consensus | AC15: =IF(Calc!$A$14="","",Calc!AM$14) -> 46324
A16: =IF(Calc!$A$15="","",Calc!A$15) -> GOOG | B16: =IF(Calc!$A$15="","",Calc!B$15) -> Alphabet Inc. | C16: =IF(Calc!$A$15="","",Calc!C$15) -> 池子 | D16: =IF(Calc!$A$15="","",Calc!D$15) -> 340.73999 | E16: =IF(Calc!$A$15="","",Calc!J$15) -> 17.114013 | F16: =IF(Calc!$A$15="","",Calc!L$15) -> 20.598814 | G16: =IF(Calc!$A$15="","",Calc!N$15) -> 0.1527572 | H16: =IF(Calc!$A$15="","",Calc!O$15) -> N/M | I16: =IF(Calc!$A$15="","",Calc!Q$15) -> 0.0024945707 | J16: =IF(Calc!$A$15="","",Calc!R$15) -> 0.049382716 | K16: =IF(Calc!$A$15="","",Calc!T$15) -> 0.090085171 | L16: =IF(Calc!$A$15="","",Calc!U$15) -> -0.034551828 | M16: =IF(Calc!$A$15="","",Calc!V$15) -> 12.4637 | N16: =IF(Calc!$A$15="","",Calc!W$15) -> 成長且加速 | O16: =IF(Calc!$A$15="","",Calc!X$15) -> 2.1441423 | P16: =IF(Calc!$A$15="","",Calc!S$15) -> 0.24233625 | Q16: =IF(Calc!$A$15="","",Calc!Y$15) -> 2.9437229 | R16: =IF(Calc!$A$15="","",Calc!I$15) -> 1.1203408 | S16: =IF(Calc!$A$15="","",Calc!Z$15) -> 0.60896411 | T16: =IF(Calc!$A$15="","",Calc!AA$15) -> 0.52588576 | U16: =IF(Calc!$A$15="","",Calc!AB$15) -> 830.78349 | V16: =IF(Calc!$A$15="","",Calc!AC$15) -> 213.40987 | W16: =IF(Calc!$A$15="","",Calc!AF$15) -> 0.48670064 | X16: =IF(Calc!$A$15="","",Calc!AG$15) -> 0.19374921 | Y16: =IF(Calc!$A$15="","",Calc!AH$15) -> 0.39598319 | Z16: =IF(Calc!$A$15="","",Calc!AI$15) -> 3.00444 | AA16: =IF(Calc!$A$15="","",Calc!AJ$15) -> FY2026Q3E | AB16: =IF(Calc!$A$15="","",Calc!AK$15) -> consensus | AC16: =IF(Calc!$A$15="","",Calc!AM$15) -> 46323
A17: =IF(Calc!$A$16="","",Calc!A$16) -> OKTA | B17: =IF(Calc!$A$16="","",Calc!B$16) -> Okta, Inc. | C17: =IF(Calc!$A$16="","",Calc!C$16) -> 池子 | D17: =IF(Calc!$A$16="","",Calc!D$16) -> 187.755 | E17: =IF(Calc!$A$16="","",Calc!J$16) -> 51.020382 | F17: =IF(Calc!$A$16="","",Calc!L$16) -> 44.612904 | G17: =IF(Calc!$A$16="","",Calc!N$16) -> 3.5714267 | H17: =IF(Calc!$A$16="","",Calc!O$16) -> 3.8996119 | I17: =IF(Calc!$A$16="","",Calc!Q$16) -> 不配息 | J17: =IF(Calc!$A$16="","",Calc!R$16) | K17: =IF(Calc!$A$16="","",Calc!T$16) -> 0.052287582 | L17: =IF(Calc!$A$16="","",Calc!U$16) -> 0.0052562418 | M17: =IF(Calc!$A$16="","",Calc!V$16) -> 4.703134 | N17: =IF(Calc!$A$16="","",Calc!W$16) -> 成長且加速 | O17: =IF(Calc!$A$16="","",Calc!X$16) -> -0.58519532 | P17: =IF(Calc!$A$16="","",Calc!S$16) -> 0.10576923 | Q17: =IF(Calc!$A$16="","",Calc!Y$16) -> 0.15384615 | R17: =IF(Calc!$A$16="","",Calc!I$16) -> 0.14285714 | S17: =IF(Calc!$A$16="","",Calc!Z$16) -> 0.78132118 | T17: =IF(Calc!$A$16="","",Calc!AA$16) -> 0.75164009 | U17: =IF(Calc!$A$16="","",Calc!AB$16) -> 296.81091 | V17: =IF(Calc!$A$16="","",Calc!AC$16) -> 270.42523 | W17: =IF(Calc!$A$16="","",Calc!AF$16) -> 0.095891182 | X17: =IF(Calc!$A$16="","",Calc!AG$16) -> 0.051171527 | Y17: =IF(Calc!$A$16="","",Calc!AH$16) -> 0.10075073 | Z17: =IF(Calc!$A$16="","",Calc!AI$16) -> 0.93474 | AA17: =IF(Calc!$A$16="","",Calc!AJ$16) -> FY2027Q3E | AB17: =IF(Calc!$A$16="","",Calc!AK$16) -> consensus | AC17: =IF(Calc!$A$16="","",Calc!AM$16) -> 46357
A18: =IF(Calc!$A$17="","",Calc!A$17) -> PLTR | B18: =IF(Calc!$A$17="","",Calc!B$17) -> Palantir Technologies Inc. | C18: =IF(Calc!$A$17="","",Calc!C$17) -> 池子 | D18: =IF(Calc!$A$17="","",Calc!D$17) -> 171.81 | E18: =IF(Calc!$A$17="","",Calc!J$17) -> 143.175 | F18: =IF(Calc!$A$17="","",Calc!L$17) -> 81.303137 | G18: =IF(Calc!$A$17="","",Calc!N$17) -> 1.1325783 | H18: =IF(Calc!$A$17="","",Calc!O$17) -> 1.826131 | I18: =IF(Calc!$A$17="","",Calc!Q$17) -> 不配息 | J18: =IF(Calc!$A$17="","",Calc!R$17) | K18: =IF(Calc!$A$17="","",Calc!T$17) -> 0.18552257 | L18: =IF(Calc!$A$17="","",Calc!U$17) -> 0.16049238 | M18: =IF(Calc!$A$17="","",Calc!V$17) -> 2.5030195 | N18: =IF(Calc!$A$17="","",Calc!W$17) -> 成長且加速 | O18: =IF(Calc!$A$17="","",Calc!X$17) -> 4.993246 | P18: =IF(Calc!$A$17="","",Calc!S$17) -> 0.92833495 | Q18: =IF(Calc!$A$17="","",Calc!Y$17) -> 1.5625 | R18: =IF(Calc!$A$17="","",Calc!I$17) -> 1.2641509 | S18: =IF(Calc!$A$17="","",Calc!Z$17) -> 0.84796134 | T18: =IF(Calc!$A$17="","",Calc!AA$17) -> 0.81835015 | U18: =IF(Calc!$A$17="","",Calc!AB$17) -> 296.11195 | V18: =IF(Calc!$A$17="","",Calc!AC$17) -> 388.38942 | W18: =IF(Calc!$A$17="","",Calc!AF$17) -> 0.39279884 | X18: =IF(Calc!$A$17="","",Calc!AG$17) -> 0.20112594 | Y18: =IF(Calc!$A$17="","",Calc!AH$17) -> 0.4224201 | Z18: =IF(Calc!$A$17="","",Calc!AI$17) -> 0.41452 | AA18: =IF(Calc!$A$17="","",Calc!AJ$17) -> FY2026Q3E | AB18: =IF(Calc!$A$17="","",Calc!AK$17) -> consensus | AC18: =IF(Calc!$A$17="","",Calc!AM$17) -> 46328
A19: =IF(Calc!$A$18="","",Calc!A$18) -> SMTC | B19: =IF(Calc!$A$18="","",Calc!B$18) -> Semtech Corporation | C19: =IF(Calc!$A$18="","",Calc!C$18) -> 池子 | D19: =IF(Calc!$A$18="","",Calc!D$18) -> 151.03999 | E19: =IF(Calc!$A$18="","",Calc!J$18) -> 70.579436 | F19: =IF(Calc!$A$18="","",Calc!L$18) -> 30.557512 | G19: =IF(Calc!$A$18="","",Calc!N$18) -> 1.483191 | H19: =IF(Calc!$A$18="","",Calc!O$18) -> 0.44958063 | I19: =IF(Calc!$A$18="","",Calc!Q$18) -> 不配息 | J19: =IF(Calc!$A$18="","",Calc!R$18) | K19: =IF(Calc!$A$18="","",Calc!T$18) -> 0.17474177 | L19: =IF(Calc!$A$18="","",Calc!U$18) -> 0.060735179 | M19: =IF(Calc!$A$18="","",Calc!V$18) -> 11.400659 | N19: =IF(Calc!$A$18="","",Calc!W$18) -> 成長且加速 | O19: =IF(Calc!$A$18="","",Calc!X$18) -> 14.873603 | P19: =IF(Calc!$A$18="","",Calc!S$18) -> 0.32719565 | Q19: =IF(Calc!$A$18="","",Calc!Y$18) -> 0.73170732 | R19: =IF(Calc!$A$18="","",Calc!I$18) -> 0.47586207 | S19: =IF(Calc!$A$18="","",Calc!Z$18) -> 0.52118053 | T19: =IF(Calc!$A$18="","",Calc!AA$18) -> 0.52869047 | U19: =IF(Calc!$A$18="","",Calc!AB$18) -> -75.099376 | V19: =IF(Calc!$A$18="","",Calc!AC$18) -> 169.08212 | W19: =IF(Calc!$A$18="","",Calc!AF$18) -> 0.31401698 | X19: =IF(Calc!$A$18="","",Calc!AG$18) -> 0.20199964 | Y19: =IF(Calc!$A$18="","",Calc!AH$18) -> 0.4676385 | Z19: =IF(Calc!$A$18="","",Calc!AI$18) -> 1.0557 | AA19: =IF(Calc!$A$18="","",Calc!AJ$18) -> FY2027Q3E | AB19: =IF(Calc!$A$18="","",Calc!AK$18) -> consensus | AC19: =IF(Calc!$A$18="","",Calc!AM$18) -> 46349
A20: =IF(Calc!$A$19="","",Calc!A$19) -> QCOM | B20: =IF(Calc!$A$19="","",Calc!B$19) -> QUALCOMM Incorporated | C20: =IF(Calc!$A$19="","",Calc!C$19) -> 池子 | D20: =IF(Calc!$A$19="","",Calc!D$19) -> 187.16251 | E20: =IF(Calc!$A$19="","",Calc!J$19) -> 16.475573 | F20: =IF(Calc!$A$19="","",Calc!L$19) -> 18.321378 | G20: =IF(Calc!$A$19="","",Calc!N$19) -> N/M | H20: =IF(Calc!$A$19="","",Calc!O$19) -> N/M | I20: =IF(Calc!$A$19="","",Calc!Q$19) -> 0.019181192 | J20: =IF(Calc!$A$19="","",Calc!R$19) -> 0.043604651 | K20: =IF(Calc!$A$19="","",Calc!T$19) -> -0.061515237 | L20: =IF(Calc!$A$19="","",Calc!U$19) -> -0.13491675 | M20: =IF(Calc!$A$19="","",Calc!V$19) -> 7.3401511 | N20: =IF(Calc!$A$19="","",Calc!W$19) -> 衰退但收斂 | O20: =IF(Calc!$A$19="","",Calc!X$19) -> -0.55902897 | P20: =IF(Calc!$A$19="","",Calc!S$19) -> -0.040328027 | Q20: =IF(Calc!$A$19="","",Calc!Y$19) -> -0.20216606 | R20: =IF(Calc!$A$19="","",Calc!I$19) -> -0.030716724 | S20: =IF(Calc!$A$19="","",Calc!Z$19) -> 0.54226327 | T20: =IF(Calc!$A$19="","",Calc!AA$19) -> 0.50886811 | U20: =IF(Calc!$A$19="","",Calc!AB$19) -> 333.95163 | V20: =IF(Calc!$A$19="","",Calc!AC$19) -> -251.08163 | W20: =IF(Calc!$A$19="","",Calc!AF$19) -> 0.44521443 | X20: =IF(Calc!$A$19="","",Calc!AG$19) -> 0.46903097 | Y20: =IF(Calc!$A$19="","",Calc!AH$19) -> 0.40522204 | Z20: =IF(Calc!$A$19="","",Calc!AI$19) -> 2.1566 | AA20: =IF(Calc!$A$19="","",Calc!AJ$19) -> FY2026Q4E | AB20: =IF(Calc!$A$19="","",Calc!AK$19) -> consensus | AC20: =IF(Calc!$A$19="","",Calc!AM$19) -> 46324
A21: =IF(Calc!$A$20="","",Calc!A$20) -> AVGO | B21: =IF(Calc!$A$20="","",Calc!B$20) -> Broadcom Inc. | C21: =IF(Calc!$A$20="","",Calc!C$20) -> 池子 | D21: =IF(Calc!$A$20="","",Calc!D$20) -> 341.70001 | E21: =IF(Calc!$A$20="","",Calc!J$20) -> 53.059008 | F21: =IF(Calc!$A$20="","",Calc!L$20) -> 18.560373 | G21: =IF(Calc!$A$20="","",Calc!N$20) -> N/M | H21: =IF(Calc!$A$20="","",Calc!O$20) -> 0.28004597 | I21: =IF(Calc!$A$20="","",Calc!Q$20) -> 0.0074334209 | J21: =IF(Calc!$A$20="","",Calc!R$20) -> 0.10434783 | K21: =IF(Calc!$A$20="","",Calc!T$20) -> 0.33370893 | L21: =IF(Calc!$A$20="","",Calc!U$20) -> 0.14893066 | M21: =IF(Calc!$A$20="","",Calc!V$20) -> 18.477827 | N21: =IF(Calc!$A$20="","",Calc!W$20) -> 成長且加速 | O21: =IF(Calc!$A$20="","",Calc!X$20) -> 27.052578 | P21: =IF(Calc!$A$20="","",Calc!S$20) -> 0.85500251 | Q21: =IF(Calc!$A$20="","",Calc!Y$20) -> -1 | R21: =IF(Calc!$A$20="","",Calc!I$20) -> 0.023847377 | S21: =IF(Calc!$A$20="","",Calc!Z$20) -> 0.68770201 | T21: =IF(Calc!$A$20="","",Calc!AA$20) -> 0.67022082 | U21: =IF(Calc!$A$20="","",Calc!AB$20) -> 174.81195 | V21: =IF(Calc!$A$20="","",Calc!AC$20) -> 203.4092 | W21: =IF(Calc!$A$20="","",Calc!AF$20) -> 0.36366925 | X21: =IF(Calc!$A$20="","",Calc!AG$20) -> 0.25385739 | Y21: =IF(Calc!$A$20="","",Calc!AH$20) -> 0.57148144 | Z21: =IF(Calc!$A$20="","",Calc!AI$20) -> 3.82578 | AA21: =IF(Calc!$A$20="","",Calc!AJ$20) -> FY2026Q4E | AB21: =IF(Calc!$A$20="","",Calc!AK$20) -> consensus | AC21: =IF(Calc!$A$20="","",Calc!AM$20) -> 46365
A22: =IF(Calc!$A$21="","",Calc!A$21) -> FTNT | B22: =IF(Calc!$A$21="","",Calc!B$21) -> Fortinet, Inc. | C22: =IF(Calc!$A$21="","",Calc!C$21) -> 池子 | D22: =IF(Calc!$A$21="","",Calc!D$21) -> 170.17999 | E22: =IF(Calc!$A$21="","",Calc!J$21) -> 52.042811 | F22: =IF(Calc!$A$21="","",Calc!L$21) -> 46.223117 | G22: =IF(Calc!$A$21="","",Calc!N$21) -> 1.9822188 | H22: =IF(Calc!$A$21="","",Calc!O$21) -> 4.866595 | I22: =IF(Calc!$A$21="","",Calc!Q$21) -> 不配息 | J22: =IF(Calc!$A$21="","",Calc!R$21) | K22: =IF(Calc!$A$21="","",Calc!T$21) -> 0.10721237 | L22: =IF(Calc!$A$21="","",Calc!U$21) -> -0.029081365 | M22: =IF(Calc!$A$21="","",Calc!V$21) -> 13.629374 | N22: =IF(Calc!$A$21="","",Calc!W$21) -> 成長且加速 | O22: =IF(Calc!$A$21="","",Calc!X$21) -> 4.8564582 | P22: =IF(Calc!$A$21="","",Calc!S$21) -> 0.25638037 | Q22: =IF(Calc!$A$21="","",Calc!Y$21) -> 0.40625 | R22: =IF(Calc!$A$21="","",Calc!I$21) -> 0.26254826 | S22: =IF(Calc!$A$21="","",Calc!Z$21) -> 0.8020432 | T22: =IF(Calc!$A$21="","",Calc!AA$21) -> 0.7866652 | U22: =IF(Calc!$A$21="","",Calc!AB$21) -> 153.78001 | V22: =IF(Calc!$A$21="","",Calc!AC$21) -> -44.268871 | W22: =IF(Calc!$A$21="","",Calc!AF$21) -> 1.3535506 | X22: =IF(Calc!$A$21="","",Calc!AG$21) -> 2.2266055 | Y22: =IF(Calc!$A$21="","",Calc!AH$21) -> 1.6457444 | Z22: =IF(Calc!$A$21="","",Calc!AI$21) -> 0.85724 | AA22: =IF(Calc!$A$21="","",Calc!AJ$21) -> FY2026Q3E | AB22: =IF(Calc!$A$21="","",Calc!AK$21) -> consensus | AC22: =IF(Calc!$A$21="","",Calc!AM$21) -> 46330
A23: =IF(Calc!$A$22="","",Calc!A$22) | B23: =IF(Calc!$A$22="","",Calc!B$22) | C23: =IF(Calc!$A$22="","",Calc!C$22) | D23: =IF(Calc!$A$22="","",Calc!D$22) | E23: =IF(Calc!$A$22="","",Calc!J$22) | F23: =IF(Calc!$A$22="","",Calc!L$22) | G23: =IF(Calc!$A$22="","",Calc!N$22) | H23: =IF(Calc!$A$22="","",Calc!O$22) | I23: =IF(Calc!$A$22="","",Calc!Q$22) | J23: =IF(Calc!$A$22="","",Calc!R$22) | K23: =IF(Calc!$A$22="","",Calc!T$22) | L23: =IF(Calc!$A$22="","",Calc!U$22) | M23: =IF(Calc!$A$22="","",Calc!V$22) | N23: =IF(Calc!$A$22="","",Calc!W$22) | O23: =IF(Calc!$A$22="","",Calc!X$22) | P23: =IF(Calc!$A$22="","",Calc!S$22) | Q23: =IF(Calc!$A$22="","",Calc!Y$22) | R23: =IF(Calc!$A$22="","",Calc!I$22) | S23: =IF(Calc!$A$22="","",Calc!Z$22) | T23: =IF(Calc!$A$22="","",Calc!AA$22) | U23: =IF(Calc!$A$22="","",Calc!AB$22) | V23: =IF(Calc!$A$22="","",Calc!AC$22) | W23: =IF(Calc!$A$22="","",Calc!AF$22) | X23: =IF(Calc!$A$22="","",Calc!AG$22) | Y23: =IF(Calc!$A$22="","",Calc!AH$22) | Z23: =IF(Calc!$A$22="","",Calc!AI$22) | AA23: =IF(Calc!$A$22="","",Calc!AJ$22) | AB23: =IF(Calc!$A$22="","",Calc!AK$22) | AC23: =IF(Calc!$A$22="","",Calc!AM$22)
A24: =IF(Calc!$A$23="","",Calc!A$23) | B24: =IF(Calc!$A$23="","",Calc!B$23) | C24: =IF(Calc!$A$23="","",Calc!C$23) | D24: =IF(Calc!$A$23="","",Calc!D$23) | E24: =IF(Calc!$A$23="","",Calc!J$23) | F24: =IF(Calc!$A$23="","",Calc!L$23) | G24: =IF(Calc!$A$23="","",Calc!N$23) | H24: =IF(Calc!$A$23="","",Calc!O$23) | I24: =IF(Calc!$A$23="","",Calc!Q$23) | J24: =IF(Calc!$A$23="","",Calc!R$23) | K24: =IF(Calc!$A$23="","",Calc!T$23) | L24: =IF(Calc!$A$23="","",Calc!U$23) | M24: =IF(Calc!$A$23="","",Calc!V$23) | N24: =IF(Calc!$A$23="","",Calc!W$23) | O24: =IF(Calc!$A$23="","",Calc!X$23) | P24: =IF(Calc!$A$23="","",Calc!S$23) | Q24: =IF(Calc!$A$23="","",Calc!Y$23) | R24: =IF(Calc!$A$23="","",Calc!I$23) | S24: =IF(Calc!$A$23="","",Calc!Z$23) | T24: =IF(Calc!$A$23="","",Calc!AA$23) | U24: =IF(Calc!$A$23="","",Calc!AB$23) | V24: =IF(Calc!$A$23="","",Calc!AC$23) | W24: =IF(Calc!$A$23="","",Calc!AF$23) | X24: =IF(Calc!$A$23="","",Calc!AG$23) | Y24: =IF(Calc!$A$23="","",Calc!AH$23) | Z24: =IF(Calc!$A$23="","",Calc!AI$23) | AA24: =IF(Calc!$A$23="","",Calc!AJ$23) | AB24: =IF(Calc!$A$23="","",Calc!AK$23) | AC24: =IF(Calc!$A$23="","",Calc!AM$23)
A25: =IF(Calc!$A$24="","",Calc!A$24) -> ↑ 藍字＝手動輸入。新增股票就在第 2~21 列往下打一列，其餘分頁全自動延伸。 | B25: =IF(Calc!$A$24="","",Calc!B$24) | C25: =IF(Calc!$A$24="","",Calc!C$24) | D25: =IF(Calc!$A$24="","",Calc!D$24) | E25: =IF(Calc!$A$24="","",Calc!J$24) -> N/M | F25: =IF(Calc!$A$24="","",Calc!L$24) -> N/M | G25: =IF(Calc!$A$24="","",Calc!N$24) -> N/M | H25: =IF(Calc!$A$24="","",Calc!O$24) -> N/M | I25: =IF(Calc!$A$24="","",Calc!Q$24) -> 不配息 | J25: =IF(Calc!$A$24="","",Calc!R$24) | K25: =IF(Calc!$A$24="","",Calc!T$24) | L25: =IF(Calc!$A$24="","",Calc!U$24) | M25: =IF(Calc!$A$24="","",Calc!V$24) | N25: =IF(Calc!$A$24="","",Calc!W$24) | O25: =IF(Calc!$A$24="","",Calc!X$24) | P25: =IF(Calc!$A$24="","",Calc!S$24) | Q25: =IF(Calc!$A$24="","",Calc!Y$24) | R25: =IF(Calc!$A$24="","",Calc!I$24) | S25: =IF(Calc!$A$24="","",Calc!Z$24) | T25: =IF(Calc!$A$24="","",Calc!AA$24) | U25: =IF(Calc!$A$24="","",Calc!AB$24) | V25: =IF(Calc!$A$24="","",Calc!AC$24) | W25: =IF(Calc!$A$24="","",Calc!AF$24) -> N/M | X25: =IF(Calc!$A$24="","",Calc!AG$24) | Y25: =IF(Calc!$A$24="","",Calc!AH$24) -> N/M | Z25: =IF(Calc!$A$24="","",Calc!AI$24) -> 0 | AA25: =IF(Calc!$A$24="","",Calc!AJ$24) | AB25: =IF(Calc!$A$24="","",Calc!AK$24) | AC25: =IF(Calc!$A$24="","",Calc!AM$24)
A26: =IF(Calc!$A$25="","",Calc!A$25) | B26: =IF(Calc!$A$25="","",Calc!B$25) | C26: =IF(Calc!$A$25="","",Calc!C$25) | D26: =IF(Calc!$A$25="","",Calc!D$25) | E26: =IF(Calc!$A$25="","",Calc!J$25) | F26: =IF(Calc!$A$25="","",Calc!L$25) | G26: =IF(Calc!$A$25="","",Calc!N$25) | H26: =IF(Calc!$A$25="","",Calc!O$25) | I26: =IF(Calc!$A$25="","",Calc!Q$25) | J26: =IF(Calc!$A$25="","",Calc!R$25) | K26: =IF(Calc!$A$25="","",Calc!T$25) | L26: =IF(Calc!$A$25="","",Calc!U$25) | M26: =IF(Calc!$A$25="","",Calc!V$25) | N26: =IF(Calc!$A$25="","",Calc!W$25) | O26: =IF(Calc!$A$25="","",Calc!X$25) | P26: =IF(Calc!$A$25="","",Calc!S$25) | Q26: =IF(Calc!$A$25="","",Calc!Y$25) | R26: =IF(Calc!$A$25="","",Calc!I$25) | S26: =IF(Calc!$A$25="","",Calc!Z$25) | T26: =IF(Calc!$A$25="","",Calc!AA$25) | U26: =IF(Calc!$A$25="","",Calc!AB$25) | V26: =IF(Calc!$A$25="","",Calc!AC$25) | W26: =IF(Calc!$A$25="","",Calc!AF$25) | X26: =IF(Calc!$A$25="","",Calc!AG$25) | Y26: =IF(Calc!$A$25="","",Calc!AH$25) | Z26: =IF(Calc!$A$25="","",Calc!AI$25) | AA26: =IF(Calc!$A$25="","",Calc!AJ$25) | AB26: =IF(Calc!$A$25="","",Calc!AK$25) | AC26: =IF(Calc!$A$25="","",Calc!AM$25)
A27: =IF(Calc!$A$26="","",Calc!A$26) | B27: =IF(Calc!$A$26="","",Calc!B$26) | C27: =IF(Calc!$A$26="","",Calc!C$26) | D27: =IF(Calc!$A$26="","",Calc!D$26) | E27: =IF(Calc!$A$26="","",Calc!J$26) | F27: =IF(Calc!$A$26="","",Calc!L$26) | G27: =IF(Calc!$A$26="","",Calc!N$26) | H27: =IF(Calc!$A$26="","",Calc!O$26) | I27: =IF(Calc!$A$26="","",Calc!Q$26) | J27: =IF(Calc!$A$26="","",Calc!R$26) | K27: =IF(Calc!$A$26="","",Calc!T$26) | L27: =IF(Calc!$A$26="","",Calc!U$26) | M27: =IF(Calc!$A$26="","",Calc!V$26) | N27: =IF(Calc!$A$26="","",Calc!W$26) | O27: =IF(Calc!$A$26="","",Calc!X$26) | P27: =IF(Calc!$A$26="","",Calc!S$26) | Q27: =IF(Calc!$A$26="","",Calc!Y$26) | R27: =IF(Calc!$A$26="","",Calc!I$26) | S27: =IF(Calc!$A$26="","",Calc!Z$26) | T27: =IF(Calc!$A$26="","",Calc!AA$26) | U27: =IF(Calc!$A$26="","",Calc!AB$26) | V27: =IF(Calc!$A$26="","",Calc!AC$26) | W27: =IF(Calc!$A$26="","",Calc!AF$26) | X27: =IF(Calc!$A$26="","",Calc!AG$26) | Y27: =IF(Calc!$A$26="","",Calc!AH$26) | Z27: =IF(Calc!$A$26="","",Calc!AI$26) | AA27: =IF(Calc!$A$26="","",Calc!AJ$26) | AB27: =IF(Calc!$A$26="","",Calc!AK$26) | AC27: =IF(Calc!$A$26="","",Calc!AM$26)
A29: 加速度(pp) ＝ 最新季 QoQ − 上一季 QoQ。QoQ ＝ 本季營收 ÷ 上一季營收 − 1（季度成長率）。正值代表這一季的成長速度比上一季快。
A30: ROE 顯示 N/M 代表股東權益為負（大量庫藏股或累積虧損），此時 ROE 沒有比較意義。殖利率顯示「不配息」代表該檔近四季沒有配息紀錄。
A31: 資料來源：yfinance / yahooquery / Alpha Vantage / SEC EDGAR

Sheet Stock_Card
A1: 個股卡 | Z1: =IF(INDEX(Calc!$AL$2:$AL$100,MATCH($B$2,Calc!$A$2:$A$100,0))<Config!$B$7,"⚠ 分析師家數不足，共識預估可信度低 ","")&IF(NOT(ISNUMBER(INDEX(Calc!$AF$2:$AF$100,MATCH($B$2,Calc!$A$2:$A$100,0)))),"⚠ 股東權益為負，ROE 無比較意義 ","")&IF(INDEX(Calc!$P$2:$P$100,MATCH($B$2,Calc!$A$2:$A$100,0))=0,"ℹ 此檔近四季未配息 ","")
A2: 選擇股票 → | B2: AAPL | D2: =IF($B$2="","",IFERROR(INDEX(Calc!$B$2:$B$100,MATCH($B$2,Calc!$A$2:$A$100,0)),"")) -> Apple Inc. | G2: =IF($B$2="","",IFERROR(INDEX(Calc!$C$2:$C$100,MATCH($B$2,Calc!$A$2:$A$100,0)),"")) -> 0
C3: ← 這個下拉同時驅動「年度檢視」與「季度檢視」兩頁
A4: 股價 | B4: =IF($B$2="","",IFERROR(INDEX(Calc!$D$2:$D$100,MATCH($B$2,Calc!$A$2:$A$100,0)),"")) -> 329.35999 | D4: 分析師家數 | E4: =IF($B$2="","",IFERROR(INDEX(Calc!$AL$2:$AL$100,MATCH($B$2,Calc!$A$2:$A$100,0)),"")) -> 27 | G4: 下次財報日 | H4: =IF($B$2="","",IFERROR(INDEX(Calc!$AM$2:$AM$100,MATCH($B$2,Calc!$A$2:$A$100,0)),"")) -> 46324 | I4: 資料日期 | J4: =IF($B$2="","",IFERROR(INDEX(Calc!$AN$2:$AN$100,MATCH($B$2,Calc!$A$2:$A$100,0)),"")) -> 46280
A6: 估值 · 殖利率 | D6: 成長 | G6: 毛利率 · ROE
A7: PE_TTM | B7: =IF($B$2="","",IFERROR(INDEX(Calc!$J$2:$J$100,MATCH($B$2,Calc!$A$2:$A$100,0)),"")) -> 37.770641 | D7: 營收QoQ 最新季 | E7: =IF($B$2="","",IFERROR(INDEX(Calc!$T$2:$T$100,MATCH($B$2,Calc!$A$2:$A$100,0)),"")) -> -0.015892574 | G7: 毛利率_TTM | H7: =IF($B$2="","",IFERROR(INDEX(Calc!$Z$2:$Z$100,MATCH($B$2,Calc!$A$2:$A$100,0)),"")) -> 0.48652916
A8: PE Forward | B8: =IF($B$2="","",IFERROR(INDEX(Calc!$L$2:$L$100,MATCH($B$2,Calc!$A$2:$A$100,0)),"")) -> 34.507766 | D8: 上一季 QoQ | E8: =IF($B$2="","",IFERROR(INDEX(Calc!$U$2:$U$100,MATCH($B$2,Calc!$A$2:$A$100,0)),"")) -> -0.22657837 | G8: 5 年平均 | H8: =IF($B$2="","",IFERROR(INDEX(Calc!$AA$2:$AA$100,MATCH($B$2,Calc!$A$2:$A$100,0)),"")) -> 0.45744556
A9: PEG_T | B9: =IF($B$2="","",IFERROR(INDEX(Calc!$N$2:$N$100,MATCH($B$2,Calc!$A$2:$A$100,0)),"")) -> 1.1685846 | D9: 加速度 (pp) | E9: =IF($B$2="","",IFERROR(INDEX(Calc!$V$2:$V$100,MATCH($B$2,Calc!$A$2:$A$100,0)),"")) -> 21.068579 | G9: 差距 (bps) | H9: =IF($B$2="","",IFERROR(INDEX(Calc!$AB$2:$AB$100,MATCH($B$2,Calc!$A$2:$A$100,0)),"")) -> 290.83593
A10: PEG_F | B10: =IF($B$2="","",IFERROR(INDEX(Calc!$O$2:$O$100,MATCH($B$2,Calc!$A$2:$A$100,0)),"")) -> 3.9973204 | D10: 動能判讀 | E10: =IF($B$2="","",IFERROR(INDEX(Calc!$W$2:$W$100,MATCH($B$2,Calc!$A$2:$A$100,0)),"")) -> 衰退但收斂 | G10: ΔGM_YoY (bps) | H10: =IF($B$2="","",IFERROR(INDEX(Calc!$AC$2:$AC$100,MATCH($B$2,Calc!$A$2:$A$100,0)),"")) -> 356.55013
A11: EPS_TTM (Adj) | B11: =IF($B$2="","",IFERROR(INDEX(Calc!$F$2:$F$100,MATCH($B$2,Calc!$A$2:$A$100,0)),"")) -> 8.72 | D11: 同期加速度 (pp) | E11: =IF($B$2="","",IFERROR(INDEX(Calc!$X$2:$X$100,MATCH($B$2,Calc!$A$2:$A$100,0)),"")) -> -0.20186874 | G11: ROE_TTM | H11: =IF($B$2="","",IFERROR(INDEX(Calc!$AF$2:$AF$100,MATCH($B$2,Calc!$A$2:$A$100,0)),"")) -> 1.486954
A12: EPS Forward | B12: =IF($B$2="","",IFERROR(INDEX(Calc!$H$2:$H$100,MATCH($B$2,Calc!$A$2:$A$100,0)),"")) -> 9.5445177 | D12: 營收YoY 最新季 | E12: =IF($B$2="","",IFERROR(INDEX(Calc!$S$2:$S$100,MATCH($B$2,Calc!$A$2:$A$100,0)),"")) -> 0.16356502 | G12: 5 年平均 | H12: =IF($B$2="","",IFERROR(INDEX(Calc!$AG$2:$AG$100,MATCH($B$2,Calc!$A$2:$A$100,0)),"")) -> 1.4327803
A13: 殖利率 | B13: =IF($B$2="","",IFERROR(INDEX(Calc!$Q$2:$Q$100,MATCH($B$2,Calc!$A$2:$A$100,0)),"")) -> 0.0031880011 | D13: EPS_YoY 最新季 | E13: =IF($B$2="","",IFERROR(INDEX(Calc!$Y$2:$Y$100,MATCH($B$2,Calc!$A$2:$A$100,0)),"")) -> 0.2866242 | G13: ROE Forward | H13: =IF($B$2="","",IFERROR(INDEX(Calc!$AH$2:$AH$100,MATCH($B$2,Calc!$A$2:$A$100,0)),"")) -> 1.2063557
A14: 每股配息 TTM | B14: =IF($B$2="","",IFERROR(INDEX(Calc!$P$2:$P$100,MATCH($B$2,Calc!$A$2:$A$100,0)),"")) -> 1.05 | D14: EPS成長_F (F1→F2) | E14: =IF($B$2="","",IFERROR(INDEX(Calc!$M$2:$M$100,MATCH($B$2,Calc!$A$2:$A$100,0)),"")) -> 0.086327246 | G14: 每股淨值 | H14: =IF($B$2="","",IFERROR(INDEX(Calc!$AD$2:$AD$100,MATCH($B$2,Calc!$A$2:$A$100,0)),"")) -> 7.3069907
D15: 當季EPS預估 | E15: =IF($B$2="","",IFERROR(INDEX(Calc!$AI$2:$AI$100,MATCH($B$2,Calc!$A$2:$A$100,0)),"")) -> 1.97656
A16: 旗標 | B16: =IF($B$2="","",IF(LEN($Z$1)=0,"✓ 目前沒有觸發任何旗標",$Z$1)) -> ✓ 目前沒有觸發任何旗標

Sheet 年度檢視
A1: 年度檢視 · 近六財年逐年指標 | Z1: =IF(Stock_Card!$B$2="","",IFERROR(SUMIFS(Raw_Q!$C$2:$C$600,Raw_Q!$A$2:$A$600,Stock_Card!$B$2,Raw_Q!$P$2:$P$600,0),"")) -> 2026
A2: 股票 | B2: =Stock_Card!$B$2 -> AAPL | C2: ← 在 Stock_Card 換股票，這一頁與「季度檢視」同步。每一列＝一個完整財年，全部由 Raw_Q 的季度資料 rollup 而來。
A4: 財年 | B4: 實際季數 | C4: 營收($M) | D4: 營收YoY | E4: 毛利率 | F4: 毛利率變化(bps) | G4: EPS(Adj) | H4: EPS YoY | I4: ROE | J4: 每股配息 | K4: 年末股價 | L4: 殖利率 | M4: PE | N4: PEG_T
A5: =IF(Stock_Card!$B$2="","",IFERROR($Z$1-5,"")) -> 2021 | B5: =IF(Stock_Card!$B$2="","",COUNTIFS(Raw_Q!$A$2:$A$600,Stock_Card!$B$2,Raw_Q!$C$2:$C$600,$A5,Raw_Q!$F$2:$F$600,"N")) -> 4 | C5: =IF($B5>=4,SUMIFS(Raw_Q!$I$2:$I$600,Raw_Q!$A$2:$A$600,Stock_Card!$B$2,Raw_Q!$C$2:$C$600,$A5,Raw_Q!$F$2:$F$600,"N"),"") -> 365817 | D5: =IFERROR(IF(AND(ISNUMBER(C5),ISNUMBER(C4)),C5/C4-1,""),"") | E5: =IF($B5>=4,IFERROR(SUMIFS(Raw_Q!$J$2:$J$600,Raw_Q!$A$2:$A$600,Stock_Card!$B$2,Raw_Q!$C$2:$C$600,$A5,Raw_Q!$F$2:$F$600,"N")/C5,""),"") -> 0.4177936 | F5: =IFERROR(IF(AND(ISNUMBER(E5),ISNUMBER(E4)),(E5-E4)*10000,""),"") | G5: =IF($B5>=4,SUMIFS(Raw_Q!$K$2:$K$600,Raw_Q!$A$2:$A$600,Stock_Card!$B$2,Raw_Q!$C$2:$C$600,$A5,Raw_Q!$F$2:$F$600,"N"),"") -> 5.62 | H5: =IFERROR(IF(AND(ISNUMBER(G5),ISNUMBER(G4)),G5/G4-1,""),"") | I5: =IF($B5>=4,IFERROR(IF(MIN(SUMIFS(Raw_Q!$M$2:$M$600,Raw_Q!$A$2:$A$600,Stock_Card!$B$2,Raw_Q!$C$2:$C$600,$A5,Raw_Q!$D$2:$D$600,4,Raw_Q!$F$2:$F$600,"N"),SUMIFS(Raw_Q!$M$2:$M$600,Raw_Q!$A$2:$A$600,Stock_Card!$B$2,Raw_Q!$C$2:$C$600,$A5-1,Raw_Q!$D$2:$D$600,4,Raw_Q!$F$2:$F$600,"N"))<=0,"N/M",SUMPRODUCT((Raw_Q!$A$2:$A$600=Stock_Card!$B$2)*(Raw_Q!$C$2:$C$600=$A5)*(Raw_Q!$F$2:$F$600="N")*Raw_Q!$K$2:$K$600*Raw_Q!$L$2:$L$600)/((SUMIFS(Raw_Q!$M$2:$M$600,Raw_Q!$A$2:$A$600,Stock_Card!$B$2,Raw_Q!$C$2:$C$600,$A5,Raw_Q!$D$2:$D$600,4,Raw_Q!$F$2:$F$600,"N")+SUMIFS(Raw_Q!$M$2:$M$600,Raw_Q!$A$2:$A$600,Stock_Card!$B$2,Raw_Q!$C$2:$C$600,$A5-1,Raw_Q!$D$2:$D$600,4,Raw_Q!$F$2:$F$600,"N"))/2)),"N/M"),"") -> 1.1565623 | J5: =IF($B5>=4,SUMIFS(Raw_Q!$N$2:$N$600,Raw_Q!$A$2:$A$600,Stock_Card!$B$2,Raw_Q!$C$2:$C$600,$A5,Raw_Q!$F$2:$F$600,"N"),"") -> 0.85 | K5: =IFERROR(IF(SUMIFS(Raw_Q!$O$2:$O$600,Raw_Q!$A$2:$A$600,Stock_Card!$B$2,Raw_Q!$C$2:$C$600,$A5,Raw_Q!$D$2:$D$600,4,Raw_Q!$F$2:$F$600,"N")=0,"",SUMIFS(Raw_Q!$O$2:$O$600,Raw_Q!$A$2:$A$600,Stock_Card!$B$2,Raw_Q!$C$2:$C$600,$A5,Raw_Q!$D$2:$D$600,4,Raw_Q!$F$2:$F$600,"N")),"") -> 141.5 | L5: =IFERROR(IF(OR(NOT(ISNUMBER(K5)),NOT(ISNUMBER(J5)),J5=0),"",J5/K5),"") -> 0.0060070671 | M5: =IFERROR(IF(OR(NOT(ISNUMBER(K5)),NOT(ISNUMBER(G5)),G5<=0),"",K5/G5),"") -> 25.177936 | N5: =IFERROR(IF(OR(NOT(ISNUMBER(M5)),NOT(ISNUMBER(H5))),"",IF(H5<Config!$B$6,"N/M",M5/(H5*100))),"")
A6: =IF(Stock_Card!$B$2="","",IFERROR($Z$1-4,"")) -> 2022 | B6: =IF(Stock_Card!$B$2="","",COUNTIFS(Raw_Q!$A$2:$A$600,Stock_Card!$B$2,Raw_Q!$C$2:$C$600,$A6,Raw_Q!$F$2:$F$600,"N")) -> 4 | C6: =IF($B6>=4,SUMIFS(Raw_Q!$I$2:$I$600,Raw_Q!$A$2:$A$600,Stock_Card!$B$2,Raw_Q!$C$2:$C$600,$A6,Raw_Q!$F$2:$F$600,"N"),"") -> 394328 | D6: =IFERROR(IF(AND(ISNUMBER(C6),ISNUMBER(C5)),C6/C5-1,""),"") -> 0.077937876 | E6: =IF($B6>=4,IFERROR(SUMIFS(Raw_Q!$J$2:$J$600,Raw_Q!$A$2:$A$600,Stock_Card!$B$2,Raw_Q!$C$2:$C$600,$A6,Raw_Q!$F$2:$F$600,"N")/C6,""),"") -> 0.43309631 | F6: =IFERROR(IF(AND(ISNUMBER(E6),ISNUMBER(E5)),(E6-E5)*10000,""),"") -> 153.02709 | G6: =IF($B6>=4,SUMIFS(Raw_Q!$K$2:$K$600,Raw_Q!$A$2:$A$600,Stock_Card!$B$2,Raw_Q!$C$2:$C$600,$A6,Raw_Q!$F$2:$F$600,"N"),"") -> 6.11 | H6: =IFERROR(IF(AND(ISNUMBER(G6),ISNUMBER(G5)),G6/G5-1,""),"") -> 0.087188612 | I6: =IF($B6>=4,IFERROR(IF(MIN(SUMIFS(Raw_Q!$M$2:$M$600,Raw_Q!$A$2:$A$600,Stock_Card!$B$2,Raw_Q!$C$2:$C$600,$A6,Raw_Q!$D$2:$D$600,4,Raw_Q!$F$2:$F$600,"N"),SUMIFS(Raw_Q!$M$2:$M$600,Raw_Q!$A$2:$A$600,Stock_Card!$B$2,Raw_Q!$C$2:$C$600,$A6-1,Raw_Q!$D$2:$D$600,4,Raw_Q!$F$2:$F$600,"N"))<=0,"N/M",SUMPRODUCT((Raw_Q!$A$2:$A$600=Stock_Card!$B$2)*(Raw_Q!$C$2:$C$600=$A6)*(Raw_Q!$F$2:$F$600="N")*Raw_Q!$K$2:$K$600*Raw_Q!$L$2:$L$600)/((SUMIFS(Raw_Q!$M$2:$M$600,Raw_Q!$A$2:$A$600,Stock_Card!$B$2,Raw_Q!$C$2:$C$600,$A6,Raw_Q!$D$2:$D$600,4,Raw_Q!$F$2:$F$600,"N")+SUMIFS(Raw_Q!$M$2:$M$600,Raw_Q!$A$2:$A$600,Stock_Card!$B$2,Raw_Q!$C$2:$C$600,$A6-1,Raw_Q!$D$2:$D$600,4,Raw_Q!$F$2:$F$600,"N"))/2)),"N/M"),"") -> 1.391294 | J6: =IF($B6>=4,SUMIFS(Raw_Q!$N$2:$N$600,Raw_Q!$A$2:$A$600,Stock_Card!$B$2,Raw_Q!$C$2:$C$600,$A6,Raw_Q!$F$2:$F$600,"N"),"") -> 0.9 | K6: =IFERROR(IF(SUMIFS(Raw_Q!$O$2:$O$600,Raw_Q!$A$2:$A$600,Stock_Card!$B$2,Raw_Q!$C$2:$C$600,$A6,Raw_Q!$D$2:$D$600,4,Raw_Q!$F$2:$F$600,"N")=0,"",SUMIFS(Raw_Q!$O$2:$O$600,Raw_Q!$A$2:$A$600,Stock_Card!$B$2,Raw_Q!$C$2:$C$600,$A6,Raw_Q!$D$2:$D$600,4,Raw_Q!$F$2:$F$600,"N")),"") -> 138.2 | L6: =IFERROR(IF(OR(NOT(ISNUMBER(K6)),NOT(ISNUMBER(J6)),J6=0),"",J6/K6),"") -> 0.0065123012 | M6: =IFERROR(IF(OR(NOT(ISNUMBER(K6)),NOT(ISNUMBER(G6)),G6<=0),"",K6/G6),"") -> 22.618657 | N6: =IFERROR(IF(OR(NOT(ISNUMBER(M6)),NOT(ISNUMBER(H6))),"",IF(H6<Config!$B$6,"N/M",M6/(H6*100))),"") -> 2.5942215
A7: =IF(Stock_Card!$B$2="","",IFERROR($Z$1-3,"")) -> 2023 | B7: =IF(Stock_Card!$B$2="","",COUNTIFS(Raw_Q!$A$2:$A$600,Stock_Card!$B$2,Raw_Q!$C$2:$C$600,$A7,Raw_Q!$F$2:$F$600,"N")) -> 4 | C7: =IF($B7>=4,SUMIFS(Raw_Q!$I$2:$I$600,Raw_Q!$A$2:$A$600,Stock_Card!$B$2,Raw_Q!$C$2:$C$600,$A7,Raw_Q!$F$2:$F$600,"N"),"") -> 383285 | D7: =IFERROR(IF(AND(ISNUMBER(C7),ISNUMBER(C6)),C7/C6-1,""),"") -> -0.028004605 | E7: =IF($B7>=4,IFERROR(SUMIFS(Raw_Q!$J$2:$J$600,Raw_Q!$A$2:$A$600,Stock_Card!$B$2,Raw_Q!$C$2:$C$600,$A7,Raw_Q!$F$2:$F$600,"N")/C7,""),"") -> 0.4413113 | F7: =IFERROR(IF(AND(ISNUMBER(E7),ISNUMBER(E6)),(E7-E6)*10000,""),"") -> 82.149902 | G7: =IF($B7>=4,SUMIFS(Raw_Q!$K$2:$K$600,Raw_Q!$A$2:$A$600,Stock_Card!$B$2,Raw_Q!$C$2:$C$600,$A7,Raw_Q!$F$2:$F$600,"N"),"") -> 6.12 | H7: =IFERROR(IF(AND(ISNUMBER(G7),ISNUMBER(G6)),G7/G6-1,""),"") -> 0.0016366612 | I7: =IF($B7>=4,IFERROR(IF(MIN(SUMIFS(Raw_Q!$M$2:$M$600,Raw_Q!$A$2:$A$600,Stock_Card!$B$2,Raw_Q!$C$2:$C$600,$A7,Raw_Q!$D$2:$D$600,4,Raw_Q!$F$2:$F$600,"N"),SUMIFS(Raw_Q!$M$2:$M$600,Raw_Q!$A$2:$A$600,Stock_Card!$B$2,Raw_Q!$C$2:$C$600,$A7-1,Raw_Q!$D$2:$D$600,4,Raw_Q!$F$2:$F$600,"N"))<=0,"N/M",SUMPRODUCT((Raw_Q!$A$2:$A$600=Stock_Card!$B$2)*(Raw_Q!$C$2:$C$600=$A7)*(Raw_Q!$F$2:$F$600="N")*Raw_Q!$K$2:$K$600*Raw_Q!$L$2:$L$600)/((SUMIFS(Raw_Q!$M$2:$M$600,Raw_Q!$A$2:$A$600,Stock_Card!$B$2,Raw_Q!$C$2:$C$600,$A7,Raw_Q!$D$2:$D$600,4,Raw_Q!$F$2:$F$600,"N")+SUMIFS(Raw_Q!$M$2:$M$600,Raw_Q!$A$2:$A$600,Stock_Card!$B$2,Raw_Q!$C$2:$C$600,$A7-1,Raw_Q!$D$2:$D$600,4,Raw_Q!$F$2:$F$600,"N"))/2)),"N/M"),"") -> 1.7204189 | J7: =IF($B7>=4,SUMIFS(Raw_Q!$N$2:$N$600,Raw_Q!$A$2:$A$600,Stock_Card!$B$2,Raw_Q!$C$2:$C$600,$A7,Raw_Q!$F$2:$F$600,"N"),"") -> 0.94 | K7: =IFERROR(IF(SUMIFS(Raw_Q!$O$2:$O$600,Raw_Q!$A$2:$A$600,Stock_Card!$B$2,Raw_Q!$C$2:$C$600,$A7,Raw_Q!$D$2:$D$600,4,Raw_Q!$F$2:$F$600,"N")=0,"",SUMIFS(Raw_Q!$O$2:$O$600,Raw_Q!$A$2:$A$600,Stock_Card!$B$2,Raw_Q!$C$2:$C$600,$A7,Raw_Q!$D$2:$D$600,4,Raw_Q!$F$2:$F$600,"N")),"") -> 171.21001 | L7: =IFERROR(IF(OR(NOT(ISNUMBER(K7)),NOT(ISNUMBER(J7)),J7=0),"",J7/K7),"") -> 0.0054903333 | M7: =IFERROR(IF(OR(NOT(ISNUMBER(K7)),NOT(ISNUMBER(G7)),G7<=0),"",K7/G7),"") -> 27.975491 | N7: =IFERROR(IF(OR(NOT(ISNUMBER(M7)),NOT(ISNUMBER(H7))),"",IF(H7<Config!$B$6,"N/M",M7/(H7*100))),"") -> N/M
A8: =IF(Stock_Card!$B$2="","",IFERROR($Z$1-2,"")) -> 2024 | B8: =IF(Stock_Card!$B$2="","",COUNTIFS(Raw_Q!$A$2:$A$600,Stock_Card!$B$2,Raw_Q!$C$2:$C$600,$A8,Raw_Q!$F$2:$F$600,"N")) -> 4 | C8: =IF($B8>=4,SUMIFS(Raw_Q!$I$2:$I$600,Raw_Q!$A$2:$A$600,Stock_Card!$B$2,Raw_Q!$C$2:$C$600,$A8,Raw_Q!$F$2:$F$600,"N"),"") -> 391035 | D8: =IFERROR(IF(AND(ISNUMBER(C8),ISNUMBER(C7)),C8/C7-1,""),"") -> 0.020219941 | E8: =IF($B8>=4,IFERROR(SUMIFS(Raw_Q!$J$2:$J$600,Raw_Q!$A$2:$A$600,Stock_Card!$B$2,Raw_Q!$C$2:$C$600,$A8,Raw_Q!$F$2:$F$600,"N")/C8,""),"") -> 0.4620635 | F8: =IFERROR(IF(AND(ISNUMBER(E8),ISNUMBER(E7)),(E8-E7)*10000,""),"") -> 207.52202 | G8: =IF($B8>=4,SUMIFS(Raw_Q!$K$2:$K$600,Raw_Q!$A$2:$A$600,Stock_Card!$B$2,Raw_Q!$C$2:$C$600,$A8,Raw_Q!$F$2:$F$600,"N"),"") -> 6.08 | H8: =IFERROR(IF(AND(ISNUMBER(G8),ISNUMBER(G7)),G8/G7-1,""),"") -> -0.0065359477 | I8: =IF($B8>=4,IFERROR(IF(MIN(SUMIFS(Raw_Q!$M$2:$M$600,Raw_Q!$A$2:$A$600,Stock_Card!$B$2,Raw_Q!$C$2:$C$600,$A8,Raw_Q!$D$2:$D$600,4,Raw_Q!$F$2:$F$600,"N"),SUMIFS(Raw_Q!$M$2:$M$600,Raw_Q!$A$2:$A$600,Stock_Card!$B$2,Raw_Q!$C$2:$C$600,$A8-1,Raw_Q!$D$2:$D$600,4,Raw_Q!$F$2:$F$600,"N"))<=0,"N/M",SUMPRODUCT((Raw_Q!$A$2:$A$600=Stock_Card!$B$2)*(Raw_Q!$C$2:$C$600=$A8)*(Raw_Q!$F$2:$F$600="N")*Raw_Q!$K$2:$K$600*Raw_Q!$L$2:$L$600)/((SUMIFS(Raw_Q!$M$2:$M$600,Raw_Q!$A$2:$A$600,Stock_Card!$B$2,Raw_Q!$C$2:$C$600,$A8,Raw_Q!$D$2:$D$600,4,Raw_Q!$F$2:$F$600,"N")+SUMIFS(Raw_Q!$M$2:$M$600,Raw_Q!$A$2:$A$600,Stock_Card!$B$2,Raw_Q!$C$2:$C$600,$A8-1,Raw_Q!$D$2:$D$600,4,Raw_Q!$F$2:$F$600,"N"))/2)),"N/M"),"") -> 1.5925679 | J8: =IF($B8>=4,SUMIFS(Raw_Q!$N$2:$N$600,Raw_Q!$A$2:$A$600,Stock_Card!$B$2,Raw_Q!$C$2:$C$600,$A8,Raw_Q!$F$2:$F$600,"N"),"") -> 0.98 | K8: =IFERROR(IF(SUMIFS(Raw_Q!$O$2:$O$600,Raw_Q!$A$2:$A$600,Stock_Card!$B$2,Raw_Q!$C$2:$C$600,$A8,Raw_Q!$D$2:$D$600,4,Raw_Q!$F$2:$F$600,"N")=0,"",SUMIFS(Raw_Q!$O$2:$O$600,Raw_Q!$A$2:$A$600,Stock_Card!$B$2,Raw_Q!$C$2:$C$600,$A8,Raw_Q!$D$2:$D$600,4,Raw_Q!$F$2:$F$600,"N")),"") -> 233 | L8: =IFERROR(IF(OR(NOT(ISNUMBER(K8)),NOT(ISNUMBER(J8)),J8=0),"",J8/K8),"") -> 0.0042060086 | M8: =IFERROR(IF(OR(NOT(ISNUMBER(K8)),NOT(ISNUMBER(G8)),G8<=0),"",K8/G8),"") -> 38.322368 | N8: =IFERROR(IF(OR(NOT(ISNUMBER(M8)),NOT(ISNUMBER(H8))),"",IF(H8<Config!$B$6,"N/M",M8/(H8*100))),"") -> N/M
A9: =IF(Stock_Card!$B$2="","",IFERROR($Z$1-1,"")) -> 2025 | B9: =IF(Stock_Card!$B$2="","",COUNTIFS(Raw_Q!$A$2:$A$600,Stock_Card!$B$2,Raw_Q!$C$2:$C$600,$A9,Raw_Q!$F$2:$F$600,"N")) -> 4 | C9: =IF($B9>=4,SUMIFS(Raw_Q!$I$2:$I$600,Raw_Q!$A$2:$A$600,Stock_Card!$B$2,Raw_Q!$C$2:$C$600,$A9,Raw_Q!$F$2:$F$600,"N"),"") -> 416161 | D9: =IFERROR(IF(AND(ISNUMBER(C9),ISNUMBER(C8)),C9/C8-1,""),"") -> 0.064255118 | E9: =IF($B9>=4,IFERROR(SUMIFS(Raw_Q!$J$2:$J$600,Raw_Q!$A$2:$A$600,Stock_Card!$B$2,Raw_Q!$C$2:$C$600,$A9,Raw_Q!$F$2:$F$600,"N")/C9,""),"") -> 0.46905164 | F9: =IFERROR(IF(AND(ISNUMBER(E9),ISNUMBER(E8)),(E9-E8)*10000,""),"") -> 69.881429 | G9: =IF($B9>=4,SUMIFS(Raw_Q!$K$2:$K$600,Raw_Q!$A$2:$A$600,Stock_Card!$B$2,Raw_Q!$C$2:$C$600,$A9,Raw_Q!$F$2:$F$600,"N"),"") -> 7.47 | H9: =IFERROR(IF(AND(ISNUMBER(G9),ISNUMBER(G8)),G9/G8-1,""),"") -> 0.22861842 | I9: =IF($B9>=4,IFERROR(IF(MIN(SUMIFS(Raw_Q!$M$2:$M$600,Raw_Q!$A$2:$A$600,Stock_Card!$B$2,Raw_Q!$C$2:$C$600,$A9,Raw_Q!$D$2:$D$600,4,Raw_Q!$F$2:$F$600,"N"),SUMIFS(Raw_Q!$M$2:$M$600,Raw_Q!$A$2:$A$600,Stock_Card!$B$2,Raw_Q!$C$2:$C$600,$A9-1,Raw_Q!$D$2:$D$600,4,Raw_Q!$F$2:$F$600,"N"))<=0,"N/M",SUMPRODUCT((Raw_Q!$A$2:$A$600=Stock_Card!$B$2)*(Raw_Q!$C$2:$C$600=$A9)*(Raw_Q!$F$2:$F$600="N")*Raw_Q!$K$2:$K$600*Raw_Q!$L$2:$L$600)/((SUMIFS(Raw_Q!$M$2:$M$600,Raw_Q!$A$2:$A$600,Stock_Card!$B$2,Raw_Q!$C$2:$C$600,$A9,Raw_Q!$D$2:$D$600,4,Raw_Q!$F$2:$F$600,"N")+SUMIFS(Raw_Q!$M$2:$M$600,Raw_Q!$A$2:$A$600,Stock_Card!$B$2,Raw_Q!$C$2:$C$600,$A9-1,Raw_Q!$D$2:$D$600,4,Raw_Q!$F$2:$F$600,"N"))/2)),"N/M"),"") -> 1.7258475 | J9: =IF($B9>=4,SUMIFS(Raw_Q!$N$2:$N$600,Raw_Q!$A$2:$A$600,Stock_Card!$B$2,Raw_Q!$C$2:$C$600,$A9,Raw_Q!$F$2:$F$600,"N"),"") -> 1.02 | K9: =IFERROR(IF(SUMIFS(Raw_Q!$O$2:$O$600,Raw_Q!$A$2:$A$600,Stock_Card!$B$2,Raw_Q!$C$2:$C$600,$A9,Raw_Q!$D$2:$D$600,4,Raw_Q!$F$2:$F$600,"N")=0,"",SUMIFS(Raw_Q!$O$2:$O$600,Raw_Q!$A$2:$A$600,Stock_Card!$B$2,Raw_Q!$C$2:$C$600,$A9,Raw_Q!$D$2:$D$600,4,Raw_Q!$F$2:$F$600,"N")),"") -> 254.63 | L9: =IFERROR(IF(OR(NOT(ISNUMBER(K9)),NOT(ISNUMBER(J9)),J9=0),"",J9/K9),"") -> 0.0040058123 | M9: =IFERROR(IF(OR(NOT(ISNUMBER(K9)),NOT(ISNUMBER(G9)),G9<=0),"",K9/G9),"") -> 34.087015 | N9: =IFERROR(IF(OR(NOT(ISNUMBER(M9)),NOT(ISNUMBER(H9))),"",IF(H9<Config!$B$6,"N/M",M9/(H9*100))),"") -> 1.4910004
A10: =IF(Stock_Card!$B$2="","",IFERROR($Z$1-0,"")) -> 2026 | B10: =IF(Stock_Card!$B$2="","",COUNTIFS(Raw_Q!$A$2:$A$600,Stock_Card!$B$2,Raw_Q!$C$2:$C$600,$A10,Raw_Q!$F$2:$F$600,"N")) -> 3 | C10: =IF($B10>=4,SUMIFS(Raw_Q!$I$2:$I$600,Raw_Q!$A$2:$A$600,Stock_Card!$B$2,Raw_Q!$C$2:$C$600,$A10,Raw_Q!$F$2:$F$600,"N"),"") | D10: =IFERROR(IF(AND(ISNUMBER(C10),ISNUMBER(C9)),C10/C9-1,""),"") | E10: =IF($B10>=4,IFERROR(SUMIFS(Raw_Q!$J$2:$J$600,Raw_Q!$A$2:$A$600,Stock_Card!$B$2,Raw_Q!$C$2:$C$600,$A10,Raw_Q!$F$2:$F$600,"N")/C10,""),"") | F10: =IFERROR(IF(AND(ISNUMBER(E10),ISNUMBER(E9)),(E10-E9)*10000,""),"") | G10: =IF($B10>=4,SUMIFS(Raw_Q!$K$2:$K$600,Raw_Q!$A$2:$A$600,Stock_Card!$B$2,Raw_Q!$C$2:$C$600,$A10,Raw_Q!$F$2:$F$600,"N"),"") | H10: =IFERROR(IF(AND(ISNUMBER(G10),ISNUMBER(G9)),G10/G9-1,""),"") | I10: =IF($B10>=4,IFERROR(IF(MIN(SUMIFS(Raw_Q!$M$2:$M$600,Raw_Q!$A$2:$A$600,Stock_Card!$B$2,Raw_Q!$C$2:$C$600,$A10,Raw_Q!$D$2:$D$600,4,Raw_Q!$F$2:$F$600,"N"),SUMIFS(Raw_Q!$M$2:$M$600,Raw_Q!$A$2:$A$600,Stock_Card!$B$2,Raw_Q!$C$2:$C$600,$A10-1,Raw_Q!$D$2:$D$600,4,Raw_Q!$F$2:$F$600,"N"))<=0,"N/M",SUMPRODUCT((Raw_Q!$A$2:$A$600=Stock_Card!$B$2)*(Raw_Q!$C$2:$C$600=$A10)*(Raw_Q!$F$2:$F$600="N")*Raw_Q!$K$2:$K$600*Raw_Q!$L$2:$L$600)/((SUMIFS(Raw_Q!$M$2:$M$600,Raw_Q!$A$2:$A$600,Stock_Card!$B$2,Raw_Q!$C$2:$C$600,$A10,Raw_Q!$D$2:$D$600,4,Raw_Q!$F$2:$F$600,"N")+SUMIFS(Raw_Q!$M$2:$M$600,Raw_Q!$A$2:$A$600,Stock_Card!$B$2,Raw_Q!$C$2:$C$600,$A10-1,Raw_Q!$D$2:$D$600,4,Raw_Q!$F$2:$F$600,"N"))/2)),"N/M"),"") | J10: =IF($B10>=4,SUMIFS(Raw_Q!$N$2:$N$600,Raw_Q!$A$2:$A$600,Stock_Card!$B$2,Raw_Q!$C$2:$C$600,$A10,Raw_Q!$F$2:$F$600,"N"),"") | K10: =IFERROR(IF(SUMIFS(Raw_Q!$O$2:$O$600,Raw_Q!$A$2:$A$600,Stock_Card!$B$2,Raw_Q!$C$2:$C$600,$A10,Raw_Q!$D$2:$D$600,4,Raw_Q!$F$2:$F$600,"N")=0,"",SUMIFS(Raw_Q!$O$2:$O$600,Raw_Q!$A$2:$A$600,Stock_Card!$B$2,Raw_Q!$C$2:$C$600,$A10,Raw_Q!$D$2:$D$600,4,Raw_Q!$F$2:$F$600,"N")),"") | L10: =IFERROR(IF(OR(NOT(ISNUMBER(K10)),NOT(ISNUMBER(J10)),J10=0),"",J10/K10),"") | M10: =IFERROR(IF(OR(NOT(ISNUMBER(K10)),NOT(ISNUMBER(G10)),G10<=0),"",K10/G10),"") | N10: =IFERROR(IF(OR(NOT(ISNUMBER(M10)),NOT(ISNUMBER(H10))),"",IF(H10<Config!$B$6,"N/M",M10/(H10*100))),"")
A11: ↓ 以下兩列是「現況」，不是年度值。F 欄在 TTM 列是「最新毛利率 − 5 年平均」。
A12: TTM / 最新季 | C12: =IF(Stock_Card!$B$2="","",IFERROR(INDEX(Calc!$E$2:$E$100,MATCH(Stock_Card!$B$2,Calc!$A$2:$A$100,0)),"")) -> 466823 | D12: =IF(Stock_Card!$B$2="","",IFERROR(INDEX(Calc!$S$2:$S$100,MATCH(Stock_Card!$B$2,Calc!$A$2:$A$100,0)),"")) -> 0.16356502 | E12: =IF(Stock_Card!$B$2="","",IFERROR(INDEX(Calc!$Z$2:$Z$100,MATCH(Stock_Card!$B$2,Calc!$A$2:$A$100,0)),"")) -> 0.48652916 | F12: =IF(Stock_Card!$B$2="","",IFERROR(INDEX(Calc!$AB$2:$AB$100,MATCH(Stock_Card!$B$2,Calc!$A$2:$A$100,0)),"")) -> 290.83593 | G12: =IF(Stock_Card!$B$2="","",IFERROR(INDEX(Calc!$F$2:$F$100,MATCH(Stock_Card!$B$2,Calc!$A$2:$A$100,0)),"")) -> 8.72 | H12: =IF(Stock_Card!$B$2="","",IFERROR(INDEX(Calc!$I$2:$I$100,MATCH(Stock_Card!$B$2,Calc!$A$2:$A$100,0)),"")) -> 0.323217 | I12: =IF(Stock_Card!$B$2="","",IFERROR(INDEX(Calc!$AF$2:$AF$100,MATCH(Stock_Card!$B$2,Calc!$A$2:$A$100,0)),"")) -> 1.486954 | J12: =IF(Stock_Card!$B$2="","",IFERROR(INDEX(Calc!$P$2:$P$100,MATCH(Stock_Card!$B$2,Calc!$A$2:$A$100,0)),"")) -> 1.05 | K12: =IF(Stock_Card!$B$2="","",IFERROR(INDEX(Calc!$D$2:$D$100,MATCH(Stock_Card!$B$2,Calc!$A$2:$A$100,0)),"")) -> 329.35999 | L12: =IF(Stock_Card!$B$2="","",IFERROR(INDEX(Calc!$Q$2:$Q$100,MATCH(Stock_Card!$B$2,Calc!$A$2:$A$100,0)),"")) -> 0.0031880011 | M12: =IF(Stock_Card!$B$2="","",IFERROR(INDEX(Calc!$J$2:$J$100,MATCH(Stock_Card!$B$2,Calc!$A$2:$A$100,0)),"")) -> 37.770641 | N12: =IF(Stock_Card!$B$2="","",IFERROR(INDEX(Calc!$N$2:$N$100,MATCH(Stock_Card!$B$2,Calc!$A$2:$A$100,0)),"")) -> 1.1685846
A13: Forward（分析師共識） | G13: =IF(Stock_Card!$B$2="","",IFERROR(INDEX(Calc!$H$2:$H$100,MATCH(Stock_Card!$B$2,Calc!$A$2:$A$100,0)),"")) -> 9.5445177 | H13: =IF(Stock_Card!$B$2="","",IFERROR(INDEX(Calc!$M$2:$M$100,MATCH(Stock_Card!$B$2,Calc!$A$2:$A$100,0)),"")) -> 0.086327246 | I13: =IF(Stock_Card!$B$2="","",IFERROR(INDEX(Calc!$AH$2:$AH$100,MATCH(Stock_Card!$B$2,Calc!$A$2:$A$100,0)),"")) -> 1.2063557 | M13: =IF(Stock_Card!$B$2="","",IFERROR(INDEX(Calc!$L$2:$L$100,MATCH(Stock_Card!$B$2,Calc!$A$2:$A$100,0)),"")) -> 34.507766 | N13: =IF(Stock_Card!$B$2="","",IFERROR(INDEX(Calc!$O$2:$O$100,MATCH(Stock_Card!$B$2,Calc!$A$2:$A$100,0)),"")) -> 3.9973204
A15: 近五年摘要
A16: 5 年平均毛利率 | C16: =IF(Stock_Card!$B$2="","",IFERROR(AVERAGE(E5:E9),"")) -> 0.44466327 | D16: 五個完整財年的算術平均
A17: 最新毛利率 − 5 年平均 (bps) | C17: =IF(Stock_Card!$B$2="","",IFERROR((E12-AVERAGE(E5:E9))*10000,"")) -> 418.65888 | D17: 正值＝目前毛利率高於五年常態
A18: 5 年平均 ROE | C18: =IF(Stock_Card!$B$2="","",IFERROR(AVERAGE(I5:I9),"")) -> 1.5173381 | D18: N/M 的年度會被自動略過
A19: 5 年平均殖利率 | C19: =IF(Stock_Card!$B$2="","",IFERROR(AVERAGE(L5:L9),"")) -> 0.0052443045 | D19: 以各財年年末股價計算
A22: PE 與殖利率都用「該財年年末股價」計算，不是用今天的股價除歷史數字——後者沒有估值意義。這需要 Raw_Q 的 price_at_end 欄。
A23: PEG_T ＝ 當年 PE ÷ 當年 EPS 成長率，是「市場當時為已實現成長付了多少」；PEG_F ＝ 前瞻 PE ÷ 預估成長率，才是估值指標。兩者不要混著解讀。
A24: 年度層刻意不放加速度——加速度是季度層的訊號（這一季有沒有比上一季快），放在年度層會遲鈍到失去意義。

Sheet 季度檢視
A1: 季度檢視 · 近 12 季 + 當季預估 | Z1: =IF(Stock_Card!$B$2="","",IFERROR(SUMIFS(Raw_Q!$C$2:$C$600,Raw_Q!$A$2:$A$600,Stock_Card!$B$2,Raw_Q!$P$2:$P$600,0),"")) -> 2026
A2: 股票 | B2: =Stock_Card!$B$2 -> AAPL | C2: ← 與 Stock_Card / 年度檢視 同步。每一列＝一個財季。加速度只做在這一層。
A4: 期別 | B4: 期末日 | C4: 營收($M) | D4: 營收QoQ | E4: 上一季QoQ | F4: 加速度(pp) | G4: 動能判讀 | H4: 同期加速度(pp) | I4: 營收YoY | J4: 毛利率 | K4: ΔGM_YoY(bps) | L4: EPS(Adj) | M4: EPS YoY | N4: 每股配息 | O4: 狀態
A5: =IF(Stock_Card!$B$2="","",IFERROR(INDEX(Raw_Q!$B$2:$B$600,MATCH(Stock_Card!$B$2&"|"&12,Raw_Q!$Q$2:$Q$600,0)),"")) -> FY2023Q4 | B5: =IF(Stock_Card!$B$2="","",IFERROR(IF(SUMIFS(Raw_Q!$E$2:$E$600,Raw_Q!$A$2:$A$600,Stock_Card!$B$2,Raw_Q!$P$2:$P$600,12)=0,"",SUMIFS(Raw_Q!$E$2:$E$600,Raw_Q!$A$2:$A$600,Stock_Card!$B$2,Raw_Q!$P$2:$P$600,12)),"")) -> 45199 | C5: =IF(Stock_Card!$B$2="","",IFERROR(SUMIFS(Raw_Q!$I$2:$I$600,Raw_Q!$A$2:$A$600,Stock_Card!$B$2,Raw_Q!$P$2:$P$600,12),"")) -> 89498 | D5: =IF(Stock_Card!$B$2="","",IFERROR((SUMIFS(Raw_Q!$I$2:$I$600,Raw_Q!$A$2:$A$600,Stock_Card!$B$2,Raw_Q!$P$2:$P$600,12)/SUMIFS(Raw_Q!$I$2:$I$600,Raw_Q!$A$2:$A$600,Stock_Card!$B$2,Raw_Q!$P$2:$P$600,13)-1),"")) -> 0.094147707 | E5: =IF(Stock_Card!$B$2="","",IFERROR((SUMIFS(Raw_Q!$I$2:$I$600,Raw_Q!$A$2:$A$600,Stock_Card!$B$2,Raw_Q!$P$2:$P$600,13)/SUMIFS(Raw_Q!$I$2:$I$600,Raw_Q!$A$2:$A$600,Stock_Card!$B$2,Raw_Q!$P$2:$P$600,14)-1),"")) -> -0.13748998 | F5: =IF(Stock_Card!$B$2="","",IFERROR(((SUMIFS(Raw_Q!$I$2:$I$600,Raw_Q!$A$2:$A$600,Stock_Card!$B$2,Raw_Q!$P$2:$P$600,12)/SUMIFS(Raw_Q!$I$2:$I$600,Raw_Q!$A$2:$A$600,Stock_Card!$B$2,Raw_Q!$P$2:$P$600,13)-1)-(SUMIFS(Raw_Q!$I$2:$I$600,Raw_Q!$A$2:$A$600,Stock_Card!$B$2,Raw_Q!$P$2:$P$600,13)/SUMIFS(Raw_Q!$I$2:$I$600,Raw_Q!$A$2:$A$600,Stock_Card!$B$2,Raw_Q!$P$2:$P$600,14)-1))*100,"")) -> 23.163769 | G5: =IF(Stock_Card!$B$2="","",IFERROR(IF(NOT(ISNUMBER(D5)),"",IF(D5>0,IF(F5>0,"成長且加速","成長但減速"),IF(F5>0,"衰退但收斂","衰退且惡化"))),"")) -> 成長且加速 | H5: =IF(Stock_Card!$B$2="","",IFERROR(((SUMIFS(Raw_Q!$I$2:$I$600,Raw_Q!$A$2:$A$600,Stock_Card!$B$2,Raw_Q!$P$2:$P$600,12)/SUMIFS(Raw_Q!$I$2:$I$600,Raw_Q!$A$2:$A$600,Stock_Card!$B$2,Raw_Q!$P$2:$P$600,13)-1)-(SUMIFS(Raw_Q!$I$2:$I$600,Raw_Q!$A$2:$A$600,Stock_Card!$B$2,Raw_Q!$P$2:$P$600,16)/SUMIFS(Raw_Q!$I$2:$I$600,Raw_Q!$A$2:$A$600,Stock_Card!$B$2,Raw_Q!$P$2:$P$600,17)-1))*100,"")) -> 0.7514551 | I5: =IF(Stock_Card!$B$2="","",IFERROR((SUMIFS(Raw_Q!$I$2:$I$600,Raw_Q!$A$2:$A$600,Stock_Card!$B$2,Raw_Q!$P$2:$P$600,12)/SUMIFS(Raw_Q!$I$2:$I$600,Raw_Q!$A$2:$A$600,Stock_Card!$B$2,Raw_Q!$P$2:$P$600,16)-1),"")) -> -0.0071883389 | J5: =IF(Stock_Card!$B$2="","",IFERROR(SUMIFS(Raw_Q!$J$2:$J$600,Raw_Q!$A$2:$A$600,Stock_Card!$B$2,Raw_Q!$P$2:$P$600,12)/SUMIFS(Raw_Q!$I$2:$I$600,Raw_Q!$A$2:$A$600,Stock_Card!$B$2,Raw_Q!$P$2:$P$600,12),"")) -> 0.45170842 | K5: =IF(Stock_Card!$B$2="","",IFERROR((SUMIFS(Raw_Q!$J$2:$J$600,Raw_Q!$A$2:$A$600,Stock_Card!$B$2,Raw_Q!$P$2:$P$600,12)/SUMIFS(Raw_Q!$I$2:$I$600,Raw_Q!$A$2:$A$600,Stock_Card!$B$2,Raw_Q!$P$2:$P$600,12)-SUMIFS(Raw_Q!$J$2:$J$600,Raw_Q!$A$2:$A$600,Stock_Card!$B$2,Raw_Q!$P$2:$P$600,16)/SUMIFS(Raw_Q!$I$2:$I$600,Raw_Q!$A$2:$A$600,Stock_Card!$B$2,Raw_Q!$P$2:$P$600,16))*10000,"")) -> 291.16179 | L5: =IF(Stock_Card!$B$2="","",IFERROR(SUMIFS(Raw_Q!$K$2:$K$600,Raw_Q!$A$2:$A$600,Stock_Card!$B$2,Raw_Q!$P$2:$P$600,12),"")) -> 1.46 | M5: =IF(Stock_Card!$B$2="","",IFERROR((SUMIFS(Raw_Q!$K$2:$K$600,Raw_Q!$A$2:$A$600,Stock_Card!$B$2,Raw_Q!$P$2:$P$600,12)/SUMIFS(Raw_Q!$K$2:$K$600,Raw_Q!$A$2:$A$600,Stock_Card!$B$2,Raw_Q!$P$2:$P$600,16)-1),"")) -> 0.13178295 | N5: =IF(Stock_Card!$B$2="","",IFERROR(SUMIFS(Raw_Q!$N$2:$N$600,Raw_Q!$A$2:$A$600,Stock_Card!$B$2,Raw_Q!$P$2:$P$600,12),"")) -> 0.24 | O5: =IF(Stock_Card!$B$2="","",IF(12=0,"預估","實際")) -> 實際
A6: =IF(Stock_Card!$B$2="","",IFERROR(INDEX(Raw_Q!$B$2:$B$600,MATCH(Stock_Card!$B$2&"|"&11,Raw_Q!$Q$2:$Q$600,0)),"")) -> FY2024Q1 | B6: =IF(Stock_Card!$B$2="","",IFERROR(IF(SUMIFS(Raw_Q!$E$2:$E$600,Raw_Q!$A$2:$A$600,Stock_Card!$B$2,Raw_Q!$P$2:$P$600,11)=0,"",SUMIFS(Raw_Q!$E$2:$E$600,Raw_Q!$A$2:$A$600,Stock_Card!$B$2,Raw_Q!$P$2:$P$600,11)),"")) -> 45291 | C6: =IF(Stock_Card!$B$2="","",IFERROR(SUMIFS(Raw_Q!$I$2:$I$600,Raw_Q!$A$2:$A$600,Stock_Card!$B$2,Raw_Q!$P$2:$P$600,11),"")) -> 119575 | D6: =IF(Stock_Card!$B$2="","",IFERROR((SUMIFS(Raw_Q!$I$2:$I$600,Raw_Q!$A$2:$A$600,Stock_Card!$B$2,Raw_Q!$P$2:$P$600,11)/SUMIFS(Raw_Q!$I$2:$I$600,Raw_Q!$A$2:$A$600,Stock_Card!$B$2,Raw_Q!$P$2:$P$600,12)-1),"")) -> 0.33606338 | E6: =IF(Stock_Card!$B$2="","",IFERROR((SUMIFS(Raw_Q!$I$2:$I$600,Raw_Q!$A$2:$A$600,Stock_Card!$B$2,Raw_Q!$P$2:$P$600,12)/SUMIFS(Raw_Q!$I$2:$I$600,Raw_Q!$A$2:$A$600,Stock_Card!$B$2,Raw_Q!$P$2:$P$600,13)-1),"")) -> 0.094147707 | F6: =IF(Stock_Card!$B$2="","",IFERROR(((SUMIFS(Raw_Q!$I$2:$I$600,Raw_Q!$A$2:$A$600,Stock_Card!$B$2,Raw_Q!$P$2:$P$600,11)/SUMIFS(Raw_Q!$I$2:$I$600,Raw_Q!$A$2:$A$600,Stock_Card!$B$2,Raw_Q!$P$2:$P$600,12)-1)-(SUMIFS(Raw_Q!$I$2:$I$600,Raw_Q!$A$2:$A$600,Stock_Card!$B$2,Raw_Q!$P$2:$P$600,12)/SUMIFS(Raw_Q!$I$2:$I$600,Raw_Q!$A$2:$A$600,Stock_Card!$B$2,Raw_Q!$P$2:$P$600,13)-1))*100,"")) -> 24.191567 | G6: =IF(Stock_Card!$B$2="","",IFERROR(IF(NOT(ISNUMBER(D6)),"",IF(D6>0,IF(F6>0,"成長且加速","成長但減速"),IF(F6>0,"衰退但收斂","衰退且惡化"))),"")) -> 成長且加速 | H6: =IF(Stock_Card!$B$2="","",IFERROR(((SUMIFS(Raw_Q!$I$2:$I$600,Raw_Q!$A$2:$A$600,Stock_Card!$B$2,Raw_Q!$P$2:$P$600,11)/SUMIFS(Raw_Q!$I$2:$I$600,Raw_Q!$A$2:$A$600,Stock_Card!$B$2,Raw_Q!$P$2:$P$600,12)-1)-(SUMIFS(Raw_Q!$I$2:$I$600,Raw_Q!$A$2:$A$600,Stock_Card!$B$2,Raw_Q!$P$2:$P$600,15)/SUMIFS(Raw_Q!$I$2:$I$600,Raw_Q!$A$2:$A$600,Stock_Card!$B$2,Raw_Q!$P$2:$P$600,16)-1))*100,"")) -> 3.6460509 | I6: =IF(Stock_Card!$B$2="","",IFERROR((SUMIFS(Raw_Q!$I$2:$I$600,Raw_Q!$A$2:$A$600,Stock_Card!$B$2,Raw_Q!$P$2:$P$600,11)/SUMIFS(Raw_Q!$I$2:$I$600,Raw_Q!$A$2:$A$600,Stock_Card!$B$2,Raw_Q!$P$2:$P$600,15)-1),"")) -> 0.020665107 | J6: =IF(Stock_Card!$B$2="","",IFERROR(SUMIFS(Raw_Q!$J$2:$J$600,Raw_Q!$A$2:$A$600,Stock_Card!$B$2,Raw_Q!$P$2:$P$600,11)/SUMIFS(Raw_Q!$I$2:$I$600,Raw_Q!$A$2:$A$600,Stock_Card!$B$2,Raw_Q!$P$2:$P$600,11),"")) -> 0.45874974 | K6: =IF(Stock_Card!$B$2="","",IFERROR((SUMIFS(Raw_Q!$J$2:$J$600,Raw_Q!$A$2:$A$600,Stock_Card!$B$2,Raw_Q!$P$2:$P$600,11)/SUMIFS(Raw_Q!$I$2:$I$600,Raw_Q!$A$2:$A$600,Stock_Card!$B$2,Raw_Q!$P$2:$P$600,11)-SUMIFS(Raw_Q!$J$2:$J$600,Raw_Q!$A$2:$A$600,Stock_Card!$B$2,Raw_Q!$P$2:$P$600,15)/SUMIFS(Raw_Q!$I$2:$I$600,Raw_Q!$A$2:$A$600,Stock_Card!$B$2,Raw_Q!$P$2:$P$600,15))*10000,"")) -> 291.27191 | L6: =IF(Stock_Card!$B$2="","",IFERROR(SUMIFS(Raw_Q!$K$2:$K$600,Raw_Q!$A$2:$A$600,Stock_Card!$B$2,Raw_Q!$P$2:$P$600,11),"")) -> 2.18 | M6: =IF(Stock_Card!$B$2="","",IFERROR((SUMIFS(Raw_Q!$K$2:$K$600,Raw_Q!$A$2:$A$600,Stock_Card!$B$2,Raw_Q!$P$2:$P$600,11)/SUMIFS(Raw_Q!$K$2:$K$600,Raw_Q!$A$2:$A$600,Stock_Card!$B$2,Raw_Q!$P$2:$P$600,15)-1),"")) -> 0.15957447 | N6: =IF(Stock_Card!$B$2="","",IFERROR(SUMIFS(Raw_Q!$N$2:$N$600,Raw_Q!$A$2:$A$600,Stock_Card!$B$2,Raw_Q!$P$2:$P$600,11),"")) -> 0.24 | O6: =IF(Stock_Card!$B$2="","",IF(11=0,"預估","實際")) -> 實際
A7: =IF(Stock_Card!$B$2="","",IFERROR(INDEX(Raw_Q!$B$2:$B$600,MATCH(Stock_Card!$B$2&"|"&10,Raw_Q!$Q$2:$Q$600,0)),"")) -> FY2024Q2 | B7: =IF(Stock_Card!$B$2="","",IFERROR(IF(SUMIFS(Raw_Q!$E$2:$E$600,Raw_Q!$A$2:$A$600,Stock_Card!$B$2,Raw_Q!$P$2:$P$600,10)=0,"",SUMIFS(Raw_Q!$E$2:$E$600,Raw_Q!$A$2:$A$600,Stock_Card!$B$2,Raw_Q!$P$2:$P$600,10)),"")) -> 45382 | C7: =IF(Stock_Card!$B$2="","",IFERROR(SUMIFS(Raw_Q!$I$2:$I$600,Raw_Q!$A$2:$A$600,Stock_Card!$B$2,Raw_Q!$P$2:$P$600,10),"")) -> 90753 | D7: =IF(Stock_Card!$B$2="","",IFERROR((SUMIFS(Raw_Q!$I$2:$I$600,Raw_Q!$A$2:$A$600,Stock_Card!$B$2,Raw_Q!$P$2:$P$600,10)/SUMIFS(Raw_Q!$I$2:$I$600,Raw_Q!$A$2:$A$600,Stock_Card!$B$2,Raw_Q!$P$2:$P$600,11)-1),"")) -> -0.24103701 | E7: =IF(Stock_Card!$B$2="","",IFERROR((SUMIFS(Raw_Q!$I$2:$I$600,Raw_Q!$A$2:$A$600,Stock_Card!$B$2,Raw_Q!$P$2:$P$600,11)/SUMIFS(Raw_Q!$I$2:$I$600,Raw_Q!$A$2:$A$600,Stock_Card!$B$2,Raw_Q!$P$2:$P$600,12)-1),"")) -> 0.33606338 | F7: =IF(Stock_Card!$B$2="","",IFERROR(((SUMIFS(Raw_Q!$I$2:$I$600,Raw_Q!$A$2:$A$600,Stock_Card!$B$2,Raw_Q!$P$2:$P$600,10)/SUMIFS(Raw_Q!$I$2:$I$600,Raw_Q!$A$2:$A$600,Stock_Card!$B$2,Raw_Q!$P$2:$P$600,11)-1)-(SUMIFS(Raw_Q!$I$2:$I$600,Raw_Q!$A$2:$A$600,Stock_Card!$B$2,Raw_Q!$P$2:$P$600,11)/SUMIFS(Raw_Q!$I$2:$I$600,Raw_Q!$A$2:$A$600,Stock_Card!$B$2,Raw_Q!$P$2:$P$600,12)-1))*100,"")) -> -57.710038 | G7: =IF(Stock_Card!$B$2="","",IFERROR(IF(NOT(ISNUMBER(D7)),"",IF(D7>0,IF(F7>0,"成長且加速","成長但減速"),IF(F7>0,"衰退但收斂","衰退且惡化"))),"")) -> 衰退且惡化 | H7: =IF(Stock_Card!$B$2="","",IFERROR(((SUMIFS(Raw_Q!$I$2:$I$600,Raw_Q!$A$2:$A$600,Stock_Card!$B$2,Raw_Q!$P$2:$P$600,10)/SUMIFS(Raw_Q!$I$2:$I$600,Raw_Q!$A$2:$A$600,Stock_Card!$B$2,Raw_Q!$P$2:$P$600,11)-1)-(SUMIFS(Raw_Q!$I$2:$I$600,Raw_Q!$A$2:$A$600,Stock_Card!$B$2,Raw_Q!$P$2:$P$600,14)/SUMIFS(Raw_Q!$I$2:$I$600,Raw_Q!$A$2:$A$600,Stock_Card!$B$2,Raw_Q!$P$2:$P$600,15)-1))*100,"")) -> -5.0535615 | I7: =IF(Stock_Card!$B$2="","",IFERROR((SUMIFS(Raw_Q!$I$2:$I$600,Raw_Q!$A$2:$A$600,Stock_Card!$B$2,Raw_Q!$P$2:$P$600,10)/SUMIFS(Raw_Q!$I$2:$I$600,Raw_Q!$A$2:$A$600,Stock_Card!$B$2,Raw_Q!$P$2:$P$600,14)-1),"")) -> -0.043053271 | J7: =IF(Stock_Card!$B$2="","",IFERROR(SUMIFS(Raw_Q!$J$2:$J$600,Raw_Q!$A$2:$A$600,Stock_Card!$B$2,Raw_Q!$P$2:$P$600,10)/SUMIFS(Raw_Q!$I$2:$I$600,Raw_Q!$A$2:$A$600,Stock_Card!$B$2,Raw_Q!$P$2:$P$600,10),"")) -> 0.46578075 | K7: =IF(Stock_Card!$B$2="","",IFERROR((SUMIFS(Raw_Q!$J$2:$J$600,Raw_Q!$A$2:$A$600,Stock_Card!$B$2,Raw_Q!$P$2:$P$600,10)/SUMIFS(Raw_Q!$I$2:$I$600,Raw_Q!$A$2:$A$600,Stock_Card!$B$2,Raw_Q!$P$2:$P$600,10)-SUMIFS(Raw_Q!$J$2:$J$600,Raw_Q!$A$2:$A$600,Stock_Card!$B$2,Raw_Q!$P$2:$P$600,14)/SUMIFS(Raw_Q!$I$2:$I$600,Raw_Q!$A$2:$A$600,Stock_Card!$B$2,Raw_Q!$P$2:$P$600,14))*10000,"")) -> 231.64018 | L7: =IF(Stock_Card!$B$2="","",IFERROR(SUMIFS(Raw_Q!$K$2:$K$600,Raw_Q!$A$2:$A$600,Stock_Card!$B$2,Raw_Q!$P$2:$P$600,10),"")) -> 1.53 | M7: =IF(Stock_Card!$B$2="","",IFERROR((SUMIFS(Raw_Q!$K$2:$K$600,Raw_Q!$A$2:$A$600,Stock_Card!$B$2,Raw_Q!$P$2:$P$600,10)/SUMIFS(Raw_Q!$K$2:$K$600,Raw_Q!$A$2:$A$600,Stock_Card!$B$2,Raw_Q!$P$2:$P$600,14)-1),"")) -> 0.0065789474 | N7: =IF(Stock_Card!$B$2="","",IFERROR(SUMIFS(Raw_Q!$N$2:$N$600,Raw_Q!$A$2:$A$600,Stock_Card!$B$2,Raw_Q!$P$2:$P$600,10),"")) -> 0.24 | O7: =IF(Stock_Card!$B$2="","",IF(10=0,"預估","實際")) -> 實際
A8: =IF(Stock_Card!$B$2="","",IFERROR(INDEX(Raw_Q!$B$2:$B$600,MATCH(Stock_Card!$B$2&"|"&9,Raw_Q!$Q$2:$Q$600,0)),"")) -> FY2024Q3 | B8: =IF(Stock_Card!$B$2="","",IFERROR(IF(SUMIFS(Raw_Q!$E$2:$E$600,Raw_Q!$A$2:$A$600,Stock_Card!$B$2,Raw_Q!$P$2:$P$600,9)=0,"",SUMIFS(Raw_Q!$E$2:$E$600,Raw_Q!$A$2:$A$600,Stock_Card!$B$2,Raw_Q!$P$2:$P$600,9)),"")) -> 45473 | C8: =IF(Stock_Card!$B$2="","",IFERROR(SUMIFS(Raw_Q!$I$2:$I$600,Raw_Q!$A$2:$A$600,Stock_Card!$B$2,Raw_Q!$P$2:$P$600,9),"")) -> 85777 | D8: =IF(Stock_Card!$B$2="","",IFERROR((SUMIFS(Raw_Q!$I$2:$I$600,Raw_Q!$A$2:$A$600,Stock_Card!$B$2,Raw_Q!$P$2:$P$600,9)/SUMIFS(Raw_Q!$I$2:$I$600,Raw_Q!$A$2:$A$600,Stock_Card!$B$2,Raw_Q!$P$2:$P$600,10)-1),"")) -> -0.054830143 | E8: =IF(Stock_Card!$B$2="","",IFERROR((SUMIFS(Raw_Q!$I$2:$I$600,Raw_Q!$A$2:$A$600,Stock_Card!$B$2,Raw_Q!$P$2:$P$600,10)/SUMIFS(Raw_Q!$I$2:$I$600,Raw_Q!$A$2:$A$600,Stock_Card!$B$2,Raw_Q!$P$2:$P$600,11)-1),"")) -> -0.24103701 | F8: =IF(Stock_Card!$B$2="","",IFERROR(((SUMIFS(Raw_Q!$I$2:$I$600,Raw_Q!$A$2:$A$600,Stock_Card!$B$2,Raw_Q!$P$2:$P$600,9)/SUMIFS(Raw_Q!$I$2:$I$600,Raw_Q!$A$2:$A$600,Stock_Card!$B$2,Raw_Q!$P$2:$P$600,10)-1)-(SUMIFS(Raw_Q!$I$2:$I$600,Raw_Q!$A$2:$A$600,Stock_Card!$B$2,Raw_Q!$P$2:$P$600,10)/SUMIFS(Raw_Q!$I$2:$I$600,Raw_Q!$A$2:$A$600,Stock_Card!$B$2,Raw_Q!$P$2:$P$600,11)-1))*100,"")) -> 18.620686 | G8: =IF(Stock_Card!$B$2="","",IFERROR(IF(NOT(ISNUMBER(D8)),"",IF(D8>0,IF(F8>0,"成長且加速","成長但減速"),IF(F8>0,"衰退但收斂","衰退且惡化"))),"")) -> 衰退但收斂 | H8: =IF(Stock_Card!$B$2="","",IFERROR(((SUMIFS(Raw_Q!$I$2:$I$600,Raw_Q!$A$2:$A$600,Stock_Card!$B$2,Raw_Q!$P$2:$P$600,9)/SUMIFS(Raw_Q!$I$2:$I$600,Raw_Q!$A$2:$A$600,Stock_Card!$B$2,Raw_Q!$P$2:$P$600,10)-1)-(SUMIFS(Raw_Q!$I$2:$I$600,Raw_Q!$A$2:$A$600,Stock_Card!$B$2,Raw_Q!$P$2:$P$600,13)/SUMIFS(Raw_Q!$I$2:$I$600,Raw_Q!$A$2:$A$600,Stock_Card!$B$2,Raw_Q!$P$2:$P$600,14)-1))*100,"")) -> 8.2659839 | I8: =IF(Stock_Card!$B$2="","",IFERROR((SUMIFS(Raw_Q!$I$2:$I$600,Raw_Q!$A$2:$A$600,Stock_Card!$B$2,Raw_Q!$P$2:$P$600,9)/SUMIFS(Raw_Q!$I$2:$I$600,Raw_Q!$A$2:$A$600,Stock_Card!$B$2,Raw_Q!$P$2:$P$600,13)-1),"")) -> 0.048657041 | J8: =IF(Stock_Card!$B$2="","",IFERROR(SUMIFS(Raw_Q!$J$2:$J$600,Raw_Q!$A$2:$A$600,Stock_Card!$B$2,Raw_Q!$P$2:$P$600,9)/SUMIFS(Raw_Q!$I$2:$I$600,Raw_Q!$A$2:$A$600,Stock_Card!$B$2,Raw_Q!$P$2:$P$600,9),"")) -> 0.46257155 | K8: =IF(Stock_Card!$B$2="","",IFERROR((SUMIFS(Raw_Q!$J$2:$J$600,Raw_Q!$A$2:$A$600,Stock_Card!$B$2,Raw_Q!$P$2:$P$600,9)/SUMIFS(Raw_Q!$I$2:$I$600,Raw_Q!$A$2:$A$600,Stock_Card!$B$2,Raw_Q!$P$2:$P$600,9)-SUMIFS(Raw_Q!$J$2:$J$600,Raw_Q!$A$2:$A$600,Stock_Card!$B$2,Raw_Q!$P$2:$P$600,13)/SUMIFS(Raw_Q!$I$2:$I$600,Raw_Q!$A$2:$A$600,Stock_Card!$B$2,Raw_Q!$P$2:$P$600,13))*10000,"")) -> 174.08526 | L8: =IF(Stock_Card!$B$2="","",IFERROR(SUMIFS(Raw_Q!$K$2:$K$600,Raw_Q!$A$2:$A$600,Stock_Card!$B$2,Raw_Q!$P$2:$P$600,9),"")) -> 1.4 | M8: =IF(Stock_Card!$B$2="","",IFERROR((SUMIFS(Raw_Q!$K$2:$K$600,Raw_Q!$A$2:$A$600,Stock_Card!$B$2,Raw_Q!$P$2:$P$600,9)/SUMIFS(Raw_Q!$K$2:$K$600,Raw_Q!$A$2:$A$600,Stock_Card!$B$2,Raw_Q!$P$2:$P$600,13)-1),"")) -> 0.11111111 | N8: =IF(Stock_Card!$B$2="","",IFERROR(SUMIFS(Raw_Q!$N$2:$N$600,Raw_Q!$A$2:$A$600,Stock_Card!$B$2,Raw_Q!$P$2:$P$600,9),"")) -> 0.25 | O8: =IF(Stock_Card!$B$2="","",IF(9=0,"預估","實際")) -> 實際
A9: =IF(Stock_Card!$B$2="","",IFERROR(INDEX(Raw_Q!$B$2:$B$600,MATCH(Stock_Card!$B$2&"|"&8,Raw_Q!$Q$2:$Q$600,0)),"")) -> FY2024Q4 | B9: =IF(Stock_Card!$B$2="","",IFERROR(IF(SUMIFS(Raw_Q!$E$2:$E$600,Raw_Q!$A$2:$A$600,Stock_Card!$B$2,Raw_Q!$P$2:$P$600,8)=0,"",SUMIFS(Raw_Q!$E$2:$E$600,Raw_Q!$A$2:$A$600,Stock_Card!$B$2,Raw_Q!$P$2:$P$600,8)),"")) -> 45565 | C9: =IF(Stock_Card!$B$2="","",IFERROR(SUMIFS(Raw_Q!$I$2:$I$600,Raw_Q!$A$2:$A$600,Stock_Card!$B$2,Raw_Q!$P$2:$P$600,8),"")) -> 94930 | D9: =IF(Stock_Card!$B$2="","",IFERROR((SUMIFS(Raw_Q!$I$2:$I$600,Raw_Q!$A$2:$A$600,Stock_Card!$B$2,Raw_Q!$P$2:$P$600,8)/SUMIFS(Raw_Q!$I$2:$I$600,Raw_Q!$A$2:$A$600,Stock_Card!$B$2,Raw_Q!$P$2:$P$600,9)-1),"")) -> 0.10670693 | E9: =IF(Stock_Card!$B$2="","",IFERROR((SUMIFS(Raw_Q!$I$2:$I$600,Raw_Q!$A$2:$A$600,Stock_Card!$B$2,Raw_Q!$P$2:$P$600,9)/SUMIFS(Raw_Q!$I$2:$I$600,Raw_Q!$A$2:$A$600,Stock_Card!$B$2,Raw_Q!$P$2:$P$600,10)-1),"")) -> -0.054830143 | F9: =IF(Stock_Card!$B$2="","",IFERROR(((SUMIFS(Raw_Q!$I$2:$I$600,Raw_Q!$A$2:$A$600,Stock_Card!$B$2,Raw_Q!$P$2:$P$600,8)/SUMIFS(Raw_Q!$I$2:$I$600,Raw_Q!$A$2:$A$600,Stock_Card!$B$2,Raw_Q!$P$2:$P$600,9)-1)-(SUMIFS(Raw_Q!$I$2:$I$600,Raw_Q!$A$2:$A$600,Stock_Card!$B$2,Raw_Q!$P$2:$P$600,9)/SUMIFS(Raw_Q!$I$2:$I$600,Raw_Q!$A$2:$A$600,Stock_Card!$B$2,Raw_Q!$P$2:$P$600,10)-1))*100,"")) -> 16.153707 | G9: =IF(Stock_Card!$B$2="","",IFERROR(IF(NOT(ISNUMBER(D9)),"",IF(D9>0,IF(F9>0,"成長且加速","成長但減速"),IF(F9>0,"衰退但收斂","衰退且惡化"))),"")) -> 成長且加速 | H9: =IF(Stock_Card!$B$2="","",IFERROR(((SUMIFS(Raw_Q!$I$2:$I$600,Raw_Q!$A$2:$A$600,Stock_Card!$B$2,Raw_Q!$P$2:$P$600,8)/SUMIFS(Raw_Q!$I$2:$I$600,Raw_Q!$A$2:$A$600,Stock_Card!$B$2,Raw_Q!$P$2:$P$600,9)-1)-(SUMIFS(Raw_Q!$I$2:$I$600,Raw_Q!$A$2:$A$600,Stock_Card!$B$2,Raw_Q!$P$2:$P$600,12)/SUMIFS(Raw_Q!$I$2:$I$600,Raw_Q!$A$2:$A$600,Stock_Card!$B$2,Raw_Q!$P$2:$P$600,13)-1))*100,"")) -> 1.2559219 | I9: =IF(Stock_Card!$B$2="","",IFERROR((SUMIFS(Raw_Q!$I$2:$I$600,Raw_Q!$A$2:$A$600,Stock_Card!$B$2,Raw_Q!$P$2:$P$600,8)/SUMIFS(Raw_Q!$I$2:$I$600,Raw_Q!$A$2:$A$600,Stock_Card!$B$2,Raw_Q!$P$2:$P$600,12)-1),"")) -> 0.060694094 | J9: =IF(Stock_Card!$B$2="","",IFERROR(SUMIFS(Raw_Q!$J$2:$J$600,Raw_Q!$A$2:$A$600,Stock_Card!$B$2,Raw_Q!$P$2:$P$600,8)/SUMIFS(Raw_Q!$I$2:$I$600,Raw_Q!$A$2:$A$600,Stock_Card!$B$2,Raw_Q!$P$2:$P$600,8),"")) -> 0.4622248 | K9: =IF(Stock_Card!$B$2="","",IFERROR((SUMIFS(Raw_Q!$J$2:$J$600,Raw_Q!$A$2:$A$600,Stock_Card!$B$2,Raw_Q!$P$2:$P$600,8)/SUMIFS(Raw_Q!$I$2:$I$600,Raw_Q!$A$2:$A$600,Stock_Card!$B$2,Raw_Q!$P$2:$P$600,8)-SUMIFS(Raw_Q!$J$2:$J$600,Raw_Q!$A$2:$A$600,Stock_Card!$B$2,Raw_Q!$P$2:$P$600,12)/SUMIFS(Raw_Q!$I$2:$I$600,Raw_Q!$A$2:$A$600,Stock_Card!$B$2,Raw_Q!$P$2:$P$600,12))*10000,"")) -> 105.16379 | L9: =IF(Stock_Card!$B$2="","",IFERROR(SUMIFS(Raw_Q!$K$2:$K$600,Raw_Q!$A$2:$A$600,Stock_Card!$B$2,Raw_Q!$P$2:$P$600,8),"")) -> 0.97 | M9: =IF(Stock_Card!$B$2="","",IFERROR((SUMIFS(Raw_Q!$K$2:$K$600,Raw_Q!$A$2:$A$600,Stock_Card!$B$2,Raw_Q!$P$2:$P$600,8)/SUMIFS(Raw_Q!$K$2:$K$600,Raw_Q!$A$2:$A$600,Stock_Card!$B$2,Raw_Q!$P$2:$P$600,12)-1),"")) -> -0.33561644 | N9: =IF(Stock_Card!$B$2="","",IFERROR(SUMIFS(Raw_Q!$N$2:$N$600,Raw_Q!$A$2:$A$600,Stock_Card!$B$2,Raw_Q!$P$2:$P$600,8),"")) -> 0.25 | O9: =IF(Stock_Card!$B$2="","",IF(8=0,"預估","實際")) -> 實際
A10: =IF(Stock_Card!$B$2="","",IFERROR(INDEX(Raw_Q!$B$2:$B$600,MATCH(Stock_Card!$B$2&"|"&7,Raw_Q!$Q$2:$Q$600,0)),"")) -> FY2025Q1 | B10: =IF(Stock_Card!$B$2="","",IFERROR(IF(SUMIFS(Raw_Q!$E$2:$E$600,Raw_Q!$A$2:$A$600,Stock_Card!$B$2,Raw_Q!$P$2:$P$600,7)=0,"",SUMIFS(Raw_Q!$E$2:$E$600,Raw_Q!$A$2:$A$600,Stock_Card!$B$2,Raw_Q!$P$2:$P$600,7)),"")) -> 45657 | C10: =IF(Stock_Card!$B$2="","",IFERROR(SUMIFS(Raw_Q!$I$2:$I$600,Raw_Q!$A$2:$A$600,Stock_Card!$B$2,Raw_Q!$P$2:$P$600,7),"")) -> 124300 | D10: =IF(Stock_Card!$B$2="","",IFERROR((SUMIFS(Raw_Q!$I$2:$I$600,Raw_Q!$A$2:$A$600,Stock_Card!$B$2,Raw_Q!$P$2:$P$600,7)/SUMIFS(Raw_Q!$I$2:$I$600,Raw_Q!$A$2:$A$600,Stock_Card!$B$2,Raw_Q!$P$2:$P$600,8)-1),"")) -> 0.30938586 | E10: =IF(Stock_Card!$B$2="","",IFERROR((SUMIFS(Raw_Q!$I$2:$I$600,Raw_Q!$A$2:$A$600,Stock_Card!$B$2,Raw_Q!$P$2:$P$600,8)/SUMIFS(Raw_Q!$I$2:$I$600,Raw_Q!$A$2:$A$600,Stock_Card!$B$2,Raw_Q!$P$2:$P$600,9)-1),"")) -> 0.10670693 | F10: =IF(Stock_Card!$B$2="","",IFERROR(((SUMIFS(Raw_Q!$I$2:$I$600,Raw_Q!$A$2:$A$600,Stock_Card!$B$2,Raw_Q!$P$2:$P$600,7)/SUMIFS(Raw_Q!$I$2:$I$600,Raw_Q!$A$2:$A$600,Stock_Card!$B$2,Raw_Q!$P$2:$P$600,8)-1)-(SUMIFS(Raw_Q!$I$2:$I$600,Raw_Q!$A$2:$A$600,Stock_Card!$B$2,Raw_Q!$P$2:$P$600,8)/SUMIFS(Raw_Q!$I$2:$I$600,Raw_Q!$A$2:$A$600,Stock_Card!$B$2,Raw_Q!$P$2:$P$600,9)-1))*100,"")) -> 20.267894 | G10: =IF(Stock_Card!$B$2="","",IFERROR(IF(NOT(ISNUMBER(D10)),"",IF(D10>0,IF(F10>0,"成長且加速","成長但減速"),IF(F10>0,"衰退但收斂","衰退且惡化"))),"")) -> 成長且加速 | H10: =IF(Stock_Card!$B$2="","",IFERROR(((SUMIFS(Raw_Q!$I$2:$I$600,Raw_Q!$A$2:$A$600,Stock_Card!$B$2,Raw_Q!$P$2:$P$600,7)/SUMIFS(Raw_Q!$I$2:$I$600,Raw_Q!$A$2:$A$600,Stock_Card!$B$2,Raw_Q!$P$2:$P$600,8)-1)-(SUMIFS(Raw_Q!$I$2:$I$600,Raw_Q!$A$2:$A$600,Stock_Card!$B$2,Raw_Q!$P$2:$P$600,11)/SUMIFS(Raw_Q!$I$2:$I$600,Raw_Q!$A$2:$A$600,Stock_Card!$B$2,Raw_Q!$P$2:$P$600,12)-1))*100,"")) -> -2.6677512 | I10: =IF(Stock_Card!$B$2="","",IFERROR((SUMIFS(Raw_Q!$I$2:$I$600,Raw_Q!$A$2:$A$600,Stock_Card!$B$2,Raw_Q!$P$2:$P$600,7)/SUMIFS(Raw_Q!$I$2:$I$600,Raw_Q!$A$2:$A$600,Stock_Card!$B$2,Raw_Q!$P$2:$P$600,11)-1),"")) -> 0.039514949 | J10: =IF(Stock_Card!$B$2="","",IFERROR(SUMIFS(Raw_Q!$J$2:$J$600,Raw_Q!$A$2:$A$600,Stock_Card!$B$2,Raw_Q!$P$2:$P$600,7)/SUMIFS(Raw_Q!$I$2:$I$600,Raw_Q!$A$2:$A$600,Stock_Card!$B$2,Raw_Q!$P$2:$P$600,7),"")) -> 0.46882542 | K10: =IF(Stock_Card!$B$2="","",IFERROR((SUMIFS(Raw_Q!$J$2:$J$600,Raw_Q!$A$2:$A$600,Stock_Card!$B$2,Raw_Q!$P$2:$P$600,7)/SUMIFS(Raw_Q!$I$2:$I$600,Raw_Q!$A$2:$A$600,Stock_Card!$B$2,Raw_Q!$P$2:$P$600,7)-SUMIFS(Raw_Q!$J$2:$J$600,Raw_Q!$A$2:$A$600,Stock_Card!$B$2,Raw_Q!$P$2:$P$600,11)/SUMIFS(Raw_Q!$I$2:$I$600,Raw_Q!$A$2:$A$600,Stock_Card!$B$2,Raw_Q!$P$2:$P$600,11))*10000,"")) -> 100.75684 | L10: =IF(Stock_Card!$B$2="","",IFERROR(SUMIFS(Raw_Q!$K$2:$K$600,Raw_Q!$A$2:$A$600,Stock_Card!$B$2,Raw_Q!$P$2:$P$600,7),"")) -> 2.4 | M10: =IF(Stock_Card!$B$2="","",IFERROR((SUMIFS(Raw_Q!$K$2:$K$600,Raw_Q!$A$2:$A$600,Stock_Card!$B$2,Raw_Q!$P$2:$P$600,7)/SUMIFS(Raw_Q!$K$2:$K$600,Raw_Q!$A$2:$A$600,Stock_Card!$B$2,Raw_Q!$P$2:$P$600,11)-1),"")) -> 0.10091743 | N10: =IF(Stock_Card!$B$2="","",IFERROR(SUMIFS(Raw_Q!$N$2:$N$600,Raw_Q!$A$2:$A$600,Stock_Card!$B$2,Raw_Q!$P$2:$P$600,7),"")) -> 0.25 | O10: =IF(Stock_Card!$B$2="","",IF(7=0,"預估","實際")) -> 實際
A11: =IF(Stock_Card!$B$2="","",IFERROR(INDEX(Raw_Q!$B$2:$B$600,MATCH(Stock_Card!$B$2&"|"&6,Raw_Q!$Q$2:$Q$600,0)),"")) -> FY2025Q2 | B11: =IF(Stock_Card!$B$2="","",IFERROR(IF(SUMIFS(Raw_Q!$E$2:$E$600,Raw_Q!$A$2:$A$600,Stock_Card!$B$2,Raw_Q!$P$2:$P$600,6)=0,"",SUMIFS(Raw_Q!$E$2:$E$600,Raw_Q!$A$2:$A$600,Stock_Card!$B$2,Raw_Q!$P$2:$P$600,6)),"")) -> 45747 | C11: =IF(Stock_Card!$B$2="","",IFERROR(SUMIFS(Raw_Q!$I$2:$I$600,Raw_Q!$A$2:$A$600,Stock_Card!$B$2,Raw_Q!$P$2:$P$600,6),"")) -> 95359 | D11: =IF(Stock_Card!$B$2="","",IFERROR((SUMIFS(Raw_Q!$I$2:$I$600,Raw_Q!$A$2:$A$600,Stock_Card!$B$2,Raw_Q!$P$2:$P$600,6)/SUMIFS(Raw_Q!$I$2:$I$600,Raw_Q!$A$2:$A$600,Stock_Card!$B$2,Raw_Q!$P$2:$P$600,7)-1),"")) -> -0.23283186 | E11: =IF(Stock_Card!$B$2="","",IFERROR((SUMIFS(Raw_Q!$I$2:$I$600,Raw_Q!$A$2:$A$600,Stock_Card!$B$2,Raw_Q!$P$2:$P$600,7)/SUMIFS(Raw_Q!$I$2:$I$600,Raw_Q!$A$2:$A$600,Stock_Card!$B$2,Raw_Q!$P$2:$P$600,8)-1),"")) -> 0.30938586 | F11: =IF(Stock_Card!$B$2="","",IFERROR(((SUMIFS(Raw_Q!$I$2:$I$600,Raw_Q!$A$2:$A$600,Stock_Card!$B$2,Raw_Q!$P$2:$P$600,6)/SUMIFS(Raw_Q!$I$2:$I$600,Raw_Q!$A$2:$A$600,Stock_Card!$B$2,Raw_Q!$P$2:$P$600,7)-1)-(SUMIFS(Raw_Q!$I$2:$I$600,Raw_Q!$A$2:$A$600,Stock_Card!$B$2,Raw_Q!$P$2:$P$600,7)/SUMIFS(Raw_Q!$I$2:$I$600,Raw_Q!$A$2:$A$600,Stock_Card!$B$2,Raw_Q!$P$2:$P$600,8)-1))*100,"")) -> -54.221772 | G11: =IF(Stock_Card!$B$2="","",IFERROR(IF(NOT(ISNUMBER(D11)),"",IF(D11>0,IF(F11>0,"成長且加速","成長但減速"),IF(F11>0,"衰退但收斂","衰退且惡化"))),"")) -> 衰退且惡化 | H11: =IF(Stock_Card!$B$2="","",IFERROR(((SUMIFS(Raw_Q!$I$2:$I$600,Raw_Q!$A$2:$A$600,Stock_Card!$B$2,Raw_Q!$P$2:$P$600,6)/SUMIFS(Raw_Q!$I$2:$I$600,Raw_Q!$A$2:$A$600,Stock_Card!$B$2,Raw_Q!$P$2:$P$600,7)-1)-(SUMIFS(Raw_Q!$I$2:$I$600,Raw_Q!$A$2:$A$600,Stock_Card!$B$2,Raw_Q!$P$2:$P$600,10)/SUMIFS(Raw_Q!$I$2:$I$600,Raw_Q!$A$2:$A$600,Stock_Card!$B$2,Raw_Q!$P$2:$P$600,11)-1))*100,"")) -> 0.82051477 | I11: =IF(Stock_Card!$B$2="","",IFERROR((SUMIFS(Raw_Q!$I$2:$I$600,Raw_Q!$A$2:$A$600,Stock_Card!$B$2,Raw_Q!$P$2:$P$600,6)/SUMIFS(Raw_Q!$I$2:$I$600,Raw_Q!$A$2:$A$600,Stock_Card!$B$2,Raw_Q!$P$2:$P$600,10)-1),"")) -> 0.050753143 | J11: =IF(Stock_Card!$B$2="","",IFERROR(SUMIFS(Raw_Q!$J$2:$J$600,Raw_Q!$A$2:$A$600,Stock_Card!$B$2,Raw_Q!$P$2:$P$600,6)/SUMIFS(Raw_Q!$I$2:$I$600,Raw_Q!$A$2:$A$600,Stock_Card!$B$2,Raw_Q!$P$2:$P$600,6),"")) -> 0.47050619 | K11: =IF(Stock_Card!$B$2="","",IFERROR((SUMIFS(Raw_Q!$J$2:$J$600,Raw_Q!$A$2:$A$600,Stock_Card!$B$2,Raw_Q!$P$2:$P$600,6)/SUMIFS(Raw_Q!$I$2:$I$600,Raw_Q!$A$2:$A$600,Stock_Card!$B$2,Raw_Q!$P$2:$P$600,6)-SUMIFS(Raw_Q!$J$2:$J$600,Raw_Q!$A$2:$A$600,Stock_Card!$B$2,Raw_Q!$P$2:$P$600,10)/SUMIFS(Raw_Q!$I$2:$I$600,Raw_Q!$A$2:$A$600,Stock_Card!$B$2,Raw_Q!$P$2:$P$600,10))*10000,"")) -> 47.254468 | L11: =IF(Stock_Card!$B$2="","",IFERROR(SUMIFS(Raw_Q!$K$2:$K$600,Raw_Q!$A$2:$A$600,Stock_Card!$B$2,Raw_Q!$P$2:$P$600,6),"")) -> 1.65 | M11: =IF(Stock_Card!$B$2="","",IFERROR((SUMIFS(Raw_Q!$K$2:$K$600,Raw_Q!$A$2:$A$600,Stock_Card!$B$2,Raw_Q!$P$2:$P$600,6)/SUMIFS(Raw_Q!$K$2:$K$600,Raw_Q!$A$2:$A$600,Stock_Card!$B$2,Raw_Q!$P$2:$P$600,10)-1),"")) -> 0.078431373 | N11: =IF(Stock_Card!$B$2="","",IFERROR(SUMIFS(Raw_Q!$N$2:$N$600,Raw_Q!$A$2:$A$600,Stock_Card!$B$2,Raw_Q!$P$2:$P$600,6),"")) -> 0.25 | O11: =IF(Stock_Card!$B$2="","",IF(6=0,"預估","實際")) -> 實際
A12: =IF(Stock_Card!$B$2="","",IFERROR(INDEX(Raw_Q!$B$2:$B$600,MATCH(Stock_Card!$B$2&"|"&5,Raw_Q!$Q$2:$Q$600,0)),"")) -> FY2025Q3 | B12: =IF(Stock_Card!$B$2="","",IFERROR(IF(SUMIFS(Raw_Q!$E$2:$E$600,Raw_Q!$A$2:$A$600,Stock_Card!$B$2,Raw_Q!$P$2:$P$600,5)=0,"",SUMIFS(Raw_Q!$E$2:$E$600,Raw_Q!$A$2:$A$600,Stock_Card!$B$2,Raw_Q!$P$2:$P$600,5)),"")) -> 45838 | C12: =IF(Stock_Card!$B$2="","",IFERROR(SUMIFS(Raw_Q!$I$2:$I$600,Raw_Q!$A$2:$A$600,Stock_Card!$B$2,Raw_Q!$P$2:$P$600,5),"")) -> 94036 | D12: =IF(Stock_Card!$B$2="","",IFERROR((SUMIFS(Raw_Q!$I$2:$I$600,Raw_Q!$A$2:$A$600,Stock_Card!$B$2,Raw_Q!$P$2:$P$600,5)/SUMIFS(Raw_Q!$I$2:$I$600,Raw_Q!$A$2:$A$600,Stock_Card!$B$2,Raw_Q!$P$2:$P$600,6)-1),"")) -> -0.013873887 | E12: =IF(Stock_Card!$B$2="","",IFERROR((SUMIFS(Raw_Q!$I$2:$I$600,Raw_Q!$A$2:$A$600,Stock_Card!$B$2,Raw_Q!$P$2:$P$600,6)/SUMIFS(Raw_Q!$I$2:$I$600,Raw_Q!$A$2:$A$600,Stock_Card!$B$2,Raw_Q!$P$2:$P$600,7)-1),"")) -> -0.23283186 | F12: =IF(Stock_Card!$B$2="","",IFERROR(((SUMIFS(Raw_Q!$I$2:$I$600,Raw_Q!$A$2:$A$600,Stock_Card!$B$2,Raw_Q!$P$2:$P$600,5)/SUMIFS(Raw_Q!$I$2:$I$600,Raw_Q!$A$2:$A$600,Stock_Card!$B$2,Raw_Q!$P$2:$P$600,6)-1)-(SUMIFS(Raw_Q!$I$2:$I$600,Raw_Q!$A$2:$A$600,Stock_Card!$B$2,Raw_Q!$P$2:$P$600,6)/SUMIFS(Raw_Q!$I$2:$I$600,Raw_Q!$A$2:$A$600,Stock_Card!$B$2,Raw_Q!$P$2:$P$600,7)-1))*100,"")) -> 21.895797 | G12: =IF(Stock_Card!$B$2="","",IFERROR(IF(NOT(ISNUMBER(D12)),"",IF(D12>0,IF(F12>0,"成長且加速","成長但減速"),IF(F12>0,"衰退但收斂","衰退且惡化"))),"")) -> 衰退但收斂 | H12: =IF(Stock_Card!$B$2="","",IFERROR(((SUMIFS(Raw_Q!$I$2:$I$600,Raw_Q!$A$2:$A$600,Stock_Card!$B$2,Raw_Q!$P$2:$P$600,5)/SUMIFS(Raw_Q!$I$2:$I$600,Raw_Q!$A$2:$A$600,Stock_Card!$B$2,Raw_Q!$P$2:$P$600,6)-1)-(SUMIFS(Raw_Q!$I$2:$I$600,Raw_Q!$A$2:$A$600,Stock_Card!$B$2,Raw_Q!$P$2:$P$600,9)/SUMIFS(Raw_Q!$I$2:$I$600,Raw_Q!$A$2:$A$600,Stock_Card!$B$2,Raw_Q!$P$2:$P$600,10)-1))*100,"")) -> 4.0956256 | I12: =IF(Stock_Card!$B$2="","",IFERROR((SUMIFS(Raw_Q!$I$2:$I$600,Raw_Q!$A$2:$A$600,Stock_Card!$B$2,Raw_Q!$P$2:$P$600,5)/SUMIFS(Raw_Q!$I$2:$I$600,Raw_Q!$A$2:$A$600,Stock_Card!$B$2,Raw_Q!$P$2:$P$600,9)-1),"")) -> 0.096284552 | J12: =IF(Stock_Card!$B$2="","",IFERROR(SUMIFS(Raw_Q!$J$2:$J$600,Raw_Q!$A$2:$A$600,Stock_Card!$B$2,Raw_Q!$P$2:$P$600,5)/SUMIFS(Raw_Q!$I$2:$I$600,Raw_Q!$A$2:$A$600,Stock_Card!$B$2,Raw_Q!$P$2:$P$600,5),"")) -> 0.46490706 | K12: =IF(Stock_Card!$B$2="","",IFERROR((SUMIFS(Raw_Q!$J$2:$J$600,Raw_Q!$A$2:$A$600,Stock_Card!$B$2,Raw_Q!$P$2:$P$600,5)/SUMIFS(Raw_Q!$I$2:$I$600,Raw_Q!$A$2:$A$600,Stock_Card!$B$2,Raw_Q!$P$2:$P$600,5)-SUMIFS(Raw_Q!$J$2:$J$600,Raw_Q!$A$2:$A$600,Stock_Card!$B$2,Raw_Q!$P$2:$P$600,9)/SUMIFS(Raw_Q!$I$2:$I$600,Raw_Q!$A$2:$A$600,Stock_Card!$B$2,Raw_Q!$P$2:$P$600,9))*10000,"")) -> 23.355051 | L12: =IF(Stock_Card!$B$2="","",IFERROR(SUMIFS(Raw_Q!$K$2:$K$600,Raw_Q!$A$2:$A$600,Stock_Card!$B$2,Raw_Q!$P$2:$P$600,5),"")) -> 1.57 | M12: =IF(Stock_Card!$B$2="","",IFERROR((SUMIFS(Raw_Q!$K$2:$K$600,Raw_Q!$A$2:$A$600,Stock_Card!$B$2,Raw_Q!$P$2:$P$600,5)/SUMIFS(Raw_Q!$K$2:$K$600,Raw_Q!$A$2:$A$600,Stock_Card!$B$2,Raw_Q!$P$2:$P$600,9)-1),"")) -> 0.12142857 | N12: =IF(Stock_Card!$B$2="","",IFERROR(SUMIFS(Raw_Q!$N$2:$N$600,Raw_Q!$A$2:$A$600,Stock_Card!$B$2,Raw_Q!$P$2:$P$600,5),"")) -> 0.26 | O12: =IF(Stock_Card!$B$2="","",IF(5=0,"預估","實際")) -> 實際
A13: =IF(Stock_Card!$B$2="","",IFERROR(INDEX(Raw_Q!$B$2:$B$600,MATCH(Stock_Card!$B$2&"|"&4,Raw_Q!$Q$2:$Q$600,0)),"")) -> FY2025Q4 | B13: =IF(Stock_Card!$B$2="","",IFERROR(IF(SUMIFS(Raw_Q!$E$2:$E$600,Raw_Q!$A$2:$A$600,Stock_Card!$B$2,Raw_Q!$P$2:$P$600,4)=0,"",SUMIFS(Raw_Q!$E$2:$E$600,Raw_Q!$A$2:$A$600,Stock_Card!$B$2,Raw_Q!$P$2:$P$600,4)),"")) -> 45930 | C13: =IF(Stock_Card!$B$2="","",IFERROR(SUMIFS(Raw_Q!$I$2:$I$600,Raw_Q!$A$2:$A$600,Stock_Card!$B$2,Raw_Q!$P$2:$P$600,4),"")) -> 102466 | D13: =IF(Stock_Card!$B$2="","",IFERROR((SUMIFS(Raw_Q!$I$2:$I$600,Raw_Q!$A$2:$A$600,Stock_Card!$B$2,Raw_Q!$P$2:$P$600,4)/SUMIFS(Raw_Q!$I$2:$I$600,Raw_Q!$A$2:$A$600,Stock_Card!$B$2,Raw_Q!$P$2:$P$600,5)-1),"")) -> 0.089646518 | E13: =IF(Stock_Card!$B$2="","",IFERROR((SUMIFS(Raw_Q!$I$2:$I$600,Raw_Q!$A$2:$A$600,Stock_Card!$B$2,Raw_Q!$P$2:$P$600,5)/SUMIFS(Raw_Q!$I$2:$I$600,Raw_Q!$A$2:$A$600,Stock_Card!$B$2,Raw_Q!$P$2:$P$600,6)-1),"")) -> -0.013873887 | F13: =IF(Stock_Card!$B$2="","",IFERROR(((SUMIFS(Raw_Q!$I$2:$I$600,Raw_Q!$A$2:$A$600,Stock_Card!$B$2,Raw_Q!$P$2:$P$600,4)/SUMIFS(Raw_Q!$I$2:$I$600,Raw_Q!$A$2:$A$600,Stock_Card!$B$2,Raw_Q!$P$2:$P$600,5)-1)-(SUMIFS(Raw_Q!$I$2:$I$600,Raw_Q!$A$2:$A$600,Stock_Card!$B$2,Raw_Q!$P$2:$P$600,5)/SUMIFS(Raw_Q!$I$2:$I$600,Raw_Q!$A$2:$A$600,Stock_Card!$B$2,Raw_Q!$P$2:$P$600,6)-1))*100,"")) -> 10.352041 | G13: =IF(Stock_Card!$B$2="","",IFERROR(IF(NOT(ISNUMBER(D13)),"",IF(D13>0,IF(F13>0,"成長且加速","成長但減速"),IF(F13>0,"衰退但收斂","衰退且惡化"))),"")) -> 成長且加速 | H13: =IF(Stock_Card!$B$2="","",IFERROR(((SUMIFS(Raw_Q!$I$2:$I$600,Raw_Q!$A$2:$A$600,Stock_Card!$B$2,Raw_Q!$P$2:$P$600,4)/SUMIFS(Raw_Q!$I$2:$I$600,Raw_Q!$A$2:$A$600,Stock_Card!$B$2,Raw_Q!$P$2:$P$600,5)-1)-(SUMIFS(Raw_Q!$I$2:$I$600,Raw_Q!$A$2:$A$600,Stock_Card!$B$2,Raw_Q!$P$2:$P$600,8)/SUMIFS(Raw_Q!$I$2:$I$600,Raw_Q!$A$2:$A$600,Stock_Card!$B$2,Raw_Q!$P$2:$P$600,9)-1))*100,"")) -> -1.7060408 | I13: =IF(Stock_Card!$B$2="","",IFERROR((SUMIFS(Raw_Q!$I$2:$I$600,Raw_Q!$A$2:$A$600,Stock_Card!$B$2,Raw_Q!$P$2:$P$600,4)/SUMIFS(Raw_Q!$I$2:$I$600,Raw_Q!$A$2:$A$600,Stock_Card!$B$2,Raw_Q!$P$2:$P$600,8)-1),"")) -> 0.07938481 | J13: =IF(Stock_Card!$B$2="","",IFERROR(SUMIFS(Raw_Q!$J$2:$J$600,Raw_Q!$A$2:$A$600,Stock_Card!$B$2,Raw_Q!$P$2:$P$600,4)/SUMIFS(Raw_Q!$I$2:$I$600,Raw_Q!$A$2:$A$600,Stock_Card!$B$2,Raw_Q!$P$2:$P$600,4),"")) -> 0.471776 | K13: =IF(Stock_Card!$B$2="","",IFERROR((SUMIFS(Raw_Q!$J$2:$J$600,Raw_Q!$A$2:$A$600,Stock_Card!$B$2,Raw_Q!$P$2:$P$600,4)/SUMIFS(Raw_Q!$I$2:$I$600,Raw_Q!$A$2:$A$600,Stock_Card!$B$2,Raw_Q!$P$2:$P$600,4)-SUMIFS(Raw_Q!$J$2:$J$600,Raw_Q!$A$2:$A$600,Stock_Card!$B$2,Raw_Q!$P$2:$P$600,8)/SUMIFS(Raw_Q!$I$2:$I$600,Raw_Q!$A$2:$A$600,Stock_Card!$B$2,Raw_Q!$P$2:$P$600,8))*10000,"")) -> 95.512065 | L13: =IF(Stock_Card!$B$2="","",IFERROR(SUMIFS(Raw_Q!$K$2:$K$600,Raw_Q!$A$2:$A$600,Stock_Card!$B$2,Raw_Q!$P$2:$P$600,4),"")) -> 1.85 | M13: =IF(Stock_Card!$B$2="","",IFERROR((SUMIFS(Raw_Q!$K$2:$K$600,Raw_Q!$A$2:$A$600,Stock_Card!$B$2,Raw_Q!$P$2:$P$600,4)/SUMIFS(Raw_Q!$K$2:$K$600,Raw_Q!$A$2:$A$600,Stock_Card!$B$2,Raw_Q!$P$2:$P$600,8)-1),"")) -> 0.90721649 | N13: =IF(Stock_Card!$B$2="","",IFERROR(SUMIFS(Raw_Q!$N$2:$N$600,Raw_Q!$A$2:$A$600,Stock_Card!$B$2,Raw_Q!$P$2:$P$600,4),"")) -> 0.26 | O13: =IF(Stock_Card!$B$2="","",IF(4=0,"預估","實際")) -> 實際
A14: =IF(Stock_Card!$B$2="","",IFERROR(INDEX(Raw_Q!$B$2:$B$600,MATCH(Stock_Card!$B$2&"|"&3,Raw_Q!$Q$2:$Q$600,0)),"")) -> FY2026Q1 | B14: =IF(Stock_Card!$B$2="","",IFERROR(IF(SUMIFS(Raw_Q!$E$2:$E$600,Raw_Q!$A$2:$A$600,Stock_Card!$B$2,Raw_Q!$P$2:$P$600,3)=0,"",SUMIFS(Raw_Q!$E$2:$E$600,Raw_Q!$A$2:$A$600,Stock_Card!$B$2,Raw_Q!$P$2:$P$600,3)),"")) -> 46022 | C14: =IF(Stock_Card!$B$2="","",IFERROR(SUMIFS(Raw_Q!$I$2:$I$600,Raw_Q!$A$2:$A$600,Stock_Card!$B$2,Raw_Q!$P$2:$P$600,3),"")) -> 143756 | D14: =IF(Stock_Card!$B$2="","",IFERROR((SUMIFS(Raw_Q!$I$2:$I$600,Raw_Q!$A$2:$A$600,Stock_Card!$B$2,Raw_Q!$P$2:$P$600,3)/SUMIFS(Raw_Q!$I$2:$I$600,Raw_Q!$A$2:$A$600,Stock_Card!$B$2,Raw_Q!$P$2:$P$600,4)-1),"")) -> 0.40296293 | E14: =IF(Stock_Card!$B$2="","",IFERROR((SUMIFS(Raw_Q!$I$2:$I$600,Raw_Q!$A$2:$A$600,Stock_Card!$B$2,Raw_Q!$P$2:$P$600,4)/SUMIFS(Raw_Q!$I$2:$I$600,Raw_Q!$A$2:$A$600,Stock_Card!$B$2,Raw_Q!$P$2:$P$600,5)-1),"")) -> 0.089646518 | F14: =IF(Stock_Card!$B$2="","",IFERROR(((SUMIFS(Raw_Q!$I$2:$I$600,Raw_Q!$A$2:$A$600,Stock_Card!$B$2,Raw_Q!$P$2:$P$600,3)/SUMIFS(Raw_Q!$I$2:$I$600,Raw_Q!$A$2:$A$600,Stock_Card!$B$2,Raw_Q!$P$2:$P$600,4)-1)-(SUMIFS(Raw_Q!$I$2:$I$600,Raw_Q!$A$2:$A$600,Stock_Card!$B$2,Raw_Q!$P$2:$P$600,4)/SUMIFS(Raw_Q!$I$2:$I$600,Raw_Q!$A$2:$A$600,Stock_Card!$B$2,Raw_Q!$P$2:$P$600,5)-1))*100,"")) -> 31.331642 | G14: =IF(Stock_Card!$B$2="","",IFERROR(IF(NOT(ISNUMBER(D14)),"",IF(D14>0,IF(F14>0,"成長且加速","成長但減速"),IF(F14>0,"衰退但收斂","衰退且惡化"))),"")) -> 成長且加速 | H14: =IF(Stock_Card!$B$2="","",IFERROR(((SUMIFS(Raw_Q!$I$2:$I$600,Raw_Q!$A$2:$A$600,Stock_Card!$B$2,Raw_Q!$P$2:$P$600,3)/SUMIFS(Raw_Q!$I$2:$I$600,Raw_Q!$A$2:$A$600,Stock_Card!$B$2,Raw_Q!$P$2:$P$600,4)-1)-(SUMIFS(Raw_Q!$I$2:$I$600,Raw_Q!$A$2:$A$600,Stock_Card!$B$2,Raw_Q!$P$2:$P$600,7)/SUMIFS(Raw_Q!$I$2:$I$600,Raw_Q!$A$2:$A$600,Stock_Card!$B$2,Raw_Q!$P$2:$P$600,8)-1))*100,"")) -> 9.3577071 | I14: =IF(Stock_Card!$B$2="","",IFERROR((SUMIFS(Raw_Q!$I$2:$I$600,Raw_Q!$A$2:$A$600,Stock_Card!$B$2,Raw_Q!$P$2:$P$600,3)/SUMIFS(Raw_Q!$I$2:$I$600,Raw_Q!$A$2:$A$600,Stock_Card!$B$2,Raw_Q!$P$2:$P$600,7)-1),"")) -> 0.15652454 | J14: =IF(Stock_Card!$B$2="","",IFERROR(SUMIFS(Raw_Q!$J$2:$J$600,Raw_Q!$A$2:$A$600,Stock_Card!$B$2,Raw_Q!$P$2:$P$600,3)/SUMIFS(Raw_Q!$I$2:$I$600,Raw_Q!$A$2:$A$600,Stock_Card!$B$2,Raw_Q!$P$2:$P$600,3),"")) -> 0.48158686 | K14: =IF(Stock_Card!$B$2="","",IFERROR((SUMIFS(Raw_Q!$J$2:$J$600,Raw_Q!$A$2:$A$600,Stock_Card!$B$2,Raw_Q!$P$2:$P$600,3)/SUMIFS(Raw_Q!$I$2:$I$600,Raw_Q!$A$2:$A$600,Stock_Card!$B$2,Raw_Q!$P$2:$P$600,3)-SUMIFS(Raw_Q!$J$2:$J$600,Raw_Q!$A$2:$A$600,Stock_Card!$B$2,Raw_Q!$P$2:$P$600,7)/SUMIFS(Raw_Q!$I$2:$I$600,Raw_Q!$A$2:$A$600,Stock_Card!$B$2,Raw_Q!$P$2:$P$600,7))*10000,"")) -> 127.61433 | L14: =IF(Stock_Card!$B$2="","",IFERROR(SUMIFS(Raw_Q!$K$2:$K$600,Raw_Q!$A$2:$A$600,Stock_Card!$B$2,Raw_Q!$P$2:$P$600,3),"")) -> 2.84 | M14: =IF(Stock_Card!$B$2="","",IFERROR((SUMIFS(Raw_Q!$K$2:$K$600,Raw_Q!$A$2:$A$600,Stock_Card!$B$2,Raw_Q!$P$2:$P$600,3)/SUMIFS(Raw_Q!$K$2:$K$600,Raw_Q!$A$2:$A$600,Stock_Card!$B$2,Raw_Q!$P$2:$P$600,7)-1),"")) -> 0.18333333 | N14: =IF(Stock_Card!$B$2="","",IFERROR(SUMIFS(Raw_Q!$N$2:$N$600,Raw_Q!$A$2:$A$600,Stock_Card!$B$2,Raw_Q!$P$2:$P$600,3),"")) -> 0.26 | O14: =IF(Stock_Card!$B$2="","",IF(3=0,"預估","實際")) -> 實際
A15: =IF(Stock_Card!$B$2="","",IFERROR(INDEX(Raw_Q!$B$2:$B$600,MATCH(Stock_Card!$B$2&"|"&2,Raw_Q!$Q$2:$Q$600,0)),"")) -> FY2026Q2 | B15: =IF(Stock_Card!$B$2="","",IFERROR(IF(SUMIFS(Raw_Q!$E$2:$E$600,Raw_Q!$A$2:$A$600,Stock_Card!$B$2,Raw_Q!$P$2:$P$600,2)=0,"",SUMIFS(Raw_Q!$E$2:$E$600,Raw_Q!$A$2:$A$600,Stock_Card!$B$2,Raw_Q!$P$2:$P$600,2)),"")) -> 46112 | C15: =IF(Stock_Card!$B$2="","",IFERROR(SUMIFS(Raw_Q!$I$2:$I$600,Raw_Q!$A$2:$A$600,Stock_Card!$B$2,Raw_Q!$P$2:$P$600,2),"")) -> 111184 | D15: =IF(Stock_Card!$B$2="","",IFERROR((SUMIFS(Raw_Q!$I$2:$I$600,Raw_Q!$A$2:$A$600,Stock_Card!$B$2,Raw_Q!$P$2:$P$600,2)/SUMIFS(Raw_Q!$I$2:$I$600,Raw_Q!$A$2:$A$600,Stock_Card!$B$2,Raw_Q!$P$2:$P$600,3)-1),"")) -> -0.22657837 | E15: =IF(Stock_Card!$B$2="","",IFERROR((SUMIFS(Raw_Q!$I$2:$I$600,Raw_Q!$A$2:$A$600,Stock_Card!$B$2,Raw_Q!$P$2:$P$600,3)/SUMIFS(Raw_Q!$I$2:$I$600,Raw_Q!$A$2:$A$600,Stock_Card!$B$2,Raw_Q!$P$2:$P$600,4)-1),"")) -> 0.40296293 | F15: =IF(Stock_Card!$B$2="","",IFERROR(((SUMIFS(Raw_Q!$I$2:$I$600,Raw_Q!$A$2:$A$600,Stock_Card!$B$2,Raw_Q!$P$2:$P$600,2)/SUMIFS(Raw_Q!$I$2:$I$600,Raw_Q!$A$2:$A$600,Stock_Card!$B$2,Raw_Q!$P$2:$P$600,3)-1)-(SUMIFS(Raw_Q!$I$2:$I$600,Raw_Q!$A$2:$A$600,Stock_Card!$B$2,Raw_Q!$P$2:$P$600,3)/SUMIFS(Raw_Q!$I$2:$I$600,Raw_Q!$A$2:$A$600,Stock_Card!$B$2,Raw_Q!$P$2:$P$600,4)-1))*100,"")) -> -62.95413 | G15: =IF(Stock_Card!$B$2="","",IFERROR(IF(NOT(ISNUMBER(D15)),"",IF(D15>0,IF(F15>0,"成長且加速","成長但減速"),IF(F15>0,"衰退但收斂","衰退且惡化"))),"")) -> 衰退且惡化 | H15: =IF(Stock_Card!$B$2="","",IFERROR(((SUMIFS(Raw_Q!$I$2:$I$600,Raw_Q!$A$2:$A$600,Stock_Card!$B$2,Raw_Q!$P$2:$P$600,2)/SUMIFS(Raw_Q!$I$2:$I$600,Raw_Q!$A$2:$A$600,Stock_Card!$B$2,Raw_Q!$P$2:$P$600,3)-1)-(SUMIFS(Raw_Q!$I$2:$I$600,Raw_Q!$A$2:$A$600,Stock_Card!$B$2,Raw_Q!$P$2:$P$600,6)/SUMIFS(Raw_Q!$I$2:$I$600,Raw_Q!$A$2:$A$600,Stock_Card!$B$2,Raw_Q!$P$2:$P$600,7)-1))*100,"")) -> 0.62534895 | I15: =IF(Stock_Card!$B$2="","",IFERROR((SUMIFS(Raw_Q!$I$2:$I$600,Raw_Q!$A$2:$A$600,Stock_Card!$B$2,Raw_Q!$P$2:$P$600,2)/SUMIFS(Raw_Q!$I$2:$I$600,Raw_Q!$A$2:$A$600,Stock_Card!$B$2,Raw_Q!$P$2:$P$600,6)-1),"")) -> 0.16595182 | J15: =IF(Stock_Card!$B$2="","",IFERROR(SUMIFS(Raw_Q!$J$2:$J$600,Raw_Q!$A$2:$A$600,Stock_Card!$B$2,Raw_Q!$P$2:$P$600,2)/SUMIFS(Raw_Q!$I$2:$I$600,Raw_Q!$A$2:$A$600,Stock_Card!$B$2,Raw_Q!$P$2:$P$600,2),"")) -> 0.49270579 | K15: =IF(Stock_Card!$B$2="","",IFERROR((SUMIFS(Raw_Q!$J$2:$J$600,Raw_Q!$A$2:$A$600,Stock_Card!$B$2,Raw_Q!$P$2:$P$600,2)/SUMIFS(Raw_Q!$I$2:$I$600,Raw_Q!$A$2:$A$600,Stock_Card!$B$2,Raw_Q!$P$2:$P$600,2)-SUMIFS(Raw_Q!$J$2:$J$600,Raw_Q!$A$2:$A$600,Stock_Card!$B$2,Raw_Q!$P$2:$P$600,6)/SUMIFS(Raw_Q!$I$2:$I$600,Raw_Q!$A$2:$A$600,Stock_Card!$B$2,Raw_Q!$P$2:$P$600,6))*10000,"")) -> 221.99593 | L15: =IF(Stock_Card!$B$2="","",IFERROR(SUMIFS(Raw_Q!$K$2:$K$600,Raw_Q!$A$2:$A$600,Stock_Card!$B$2,Raw_Q!$P$2:$P$600,2),"")) -> 2.01 | M15: =IF(Stock_Card!$B$2="","",IFERROR((SUMIFS(Raw_Q!$K$2:$K$600,Raw_Q!$A$2:$A$600,Stock_Card!$B$2,Raw_Q!$P$2:$P$600,2)/SUMIFS(Raw_Q!$K$2:$K$600,Raw_Q!$A$2:$A$600,Stock_Card!$B$2,Raw_Q!$P$2:$P$600,6)-1),"")) -> 0.21818182 | N15: =IF(Stock_Card!$B$2="","",IFERROR(SUMIFS(Raw_Q!$N$2:$N$600,Raw_Q!$A$2:$A$600,Stock_Card!$B$2,Raw_Q!$P$2:$P$600,2),"")) -> 0.26 | O15: =IF(Stock_Card!$B$2="","",IF(2=0,"預估","實際")) -> 實際
A16: =IF(Stock_Card!$B$2="","",IFERROR(INDEX(Raw_Q!$B$2:$B$600,MATCH(Stock_Card!$B$2&"|"&1,Raw_Q!$Q$2:$Q$600,0)),"")) -> FY2026Q3 | B16: =IF(Stock_Card!$B$2="","",IFERROR(IF(SUMIFS(Raw_Q!$E$2:$E$600,Raw_Q!$A$2:$A$600,Stock_Card!$B$2,Raw_Q!$P$2:$P$600,1)=0,"",SUMIFS(Raw_Q!$E$2:$E$600,Raw_Q!$A$2:$A$600,Stock_Card!$B$2,Raw_Q!$P$2:$P$600,1)),"")) -> 46203 | C16: =IF(Stock_Card!$B$2="","",IFERROR(SUMIFS(Raw_Q!$I$2:$I$600,Raw_Q!$A$2:$A$600,Stock_Card!$B$2,Raw_Q!$P$2:$P$600,1),"")) -> 109417 | D16: =IF(Stock_Card!$B$2="","",IFERROR((SUMIFS(Raw_Q!$I$2:$I$600,Raw_Q!$A$2:$A$600,Stock_Card!$B$2,Raw_Q!$P$2:$P$600,1)/SUMIFS(Raw_Q!$I$2:$I$600,Raw_Q!$A$2:$A$600,Stock_Card!$B$2,Raw_Q!$P$2:$P$600,2)-1),"")) -> -0.015892574 | E16: =IF(Stock_Card!$B$2="","",IFERROR((SUMIFS(Raw_Q!$I$2:$I$600,Raw_Q!$A$2:$A$600,Stock_Card!$B$2,Raw_Q!$P$2:$P$600,2)/SUMIFS(Raw_Q!$I$2:$I$600,Raw_Q!$A$2:$A$600,Stock_Card!$B$2,Raw_Q!$P$2:$P$600,3)-1),"")) -> -0.22657837 | F16: =IF(Stock_Card!$B$2="","",IFERROR(((SUMIFS(Raw_Q!$I$2:$I$600,Raw_Q!$A$2:$A$600,Stock_Card!$B$2,Raw_Q!$P$2:$P$600,1)/SUMIFS(Raw_Q!$I$2:$I$600,Raw_Q!$A$2:$A$600,Stock_Card!$B$2,Raw_Q!$P$2:$P$600,2)-1)-(SUMIFS(Raw_Q!$I$2:$I$600,Raw_Q!$A$2:$A$600,Stock_Card!$B$2,Raw_Q!$P$2:$P$600,2)/SUMIFS(Raw_Q!$I$2:$I$600,Raw_Q!$A$2:$A$600,Stock_Card!$B$2,Raw_Q!$P$2:$P$600,3)-1))*100,"")) -> 21.068579 | G16: =IF(Stock_Card!$B$2="","",IFERROR(IF(NOT(ISNUMBER(D16)),"",IF(D16>0,IF(F16>0,"成長且加速","成長但減速"),IF(F16>0,"衰退但收斂","衰退且惡化"))),"")) -> 衰退但收斂 | H16: =IF(Stock_Card!$B$2="","",IFERROR(((SUMIFS(Raw_Q!$I$2:$I$600,Raw_Q!$A$2:$A$600,Stock_Card!$B$2,Raw_Q!$P$2:$P$600,1)/SUMIFS(Raw_Q!$I$2:$I$600,Raw_Q!$A$2:$A$600,Stock_Card!$B$2,Raw_Q!$P$2:$P$600,2)-1)-(SUMIFS(Raw_Q!$I$2:$I$600,Raw_Q!$A$2:$A$600,Stock_Card!$B$2,Raw_Q!$P$2:$P$600,5)/SUMIFS(Raw_Q!$I$2:$I$600,Raw_Q!$A$2:$A$600,Stock_Card!$B$2,Raw_Q!$P$2:$P$600,6)-1))*100,"")) -> -0.20186874 | I16: =IF(Stock_Card!$B$2="","",IFERROR((SUMIFS(Raw_Q!$I$2:$I$600,Raw_Q!$A$2:$A$600,Stock_Card!$B$2,Raw_Q!$P$2:$P$600,1)/SUMIFS(Raw_Q!$I$2:$I$600,Raw_Q!$A$2:$A$600,Stock_Card!$B$2,Raw_Q!$P$2:$P$600,5)-1),"")) -> 0.16356502 | J16: =IF(Stock_Card!$B$2="","",IFERROR(SUMIFS(Raw_Q!$J$2:$J$600,Raw_Q!$A$2:$A$600,Stock_Card!$B$2,Raw_Q!$P$2:$P$600,1)/SUMIFS(Raw_Q!$I$2:$I$600,Raw_Q!$A$2:$A$600,Stock_Card!$B$2,Raw_Q!$P$2:$P$600,1),"")) -> 0.50056207 | K16: =IF(Stock_Card!$B$2="","",IFERROR((SUMIFS(Raw_Q!$J$2:$J$600,Raw_Q!$A$2:$A$600,Stock_Card!$B$2,Raw_Q!$P$2:$P$600,1)/SUMIFS(Raw_Q!$I$2:$I$600,Raw_Q!$A$2:$A$600,Stock_Card!$B$2,Raw_Q!$P$2:$P$600,1)-SUMIFS(Raw_Q!$J$2:$J$600,Raw_Q!$A$2:$A$600,Stock_Card!$B$2,Raw_Q!$P$2:$P$600,5)/SUMIFS(Raw_Q!$I$2:$I$600,Raw_Q!$A$2:$A$600,Stock_Card!$B$2,Raw_Q!$P$2:$P$600,5))*10000,"")) -> 356.55013 | L16: =IF(Stock_Card!$B$2="","",IFERROR(SUMIFS(Raw_Q!$K$2:$K$600,Raw_Q!$A$2:$A$600,Stock_Card!$B$2,Raw_Q!$P$2:$P$600,1),"")) -> 2.02 | M16: =IF(Stock_Card!$B$2="","",IFERROR((SUMIFS(Raw_Q!$K$2:$K$600,Raw_Q!$A$2:$A$600,Stock_Card!$B$2,Raw_Q!$P$2:$P$600,1)/SUMIFS(Raw_Q!$K$2:$K$600,Raw_Q!$A$2:$A$600,Stock_Card!$B$2,Raw_Q!$P$2:$P$600,5)-1),"")) -> 0.2866242 | N16: =IF(Stock_Card!$B$2="","",IFERROR(SUMIFS(Raw_Q!$N$2:$N$600,Raw_Q!$A$2:$A$600,Stock_Card!$B$2,Raw_Q!$P$2:$P$600,1),"")) -> 0.27 | O16: =IF(Stock_Card!$B$2="","",IF(1=0,"預估","實際")) -> 實際
A17: =IF(Stock_Card!$B$2="","",IFERROR(INDEX(Raw_Q!$B$2:$B$600,MATCH(Stock_Card!$B$2&"|"&0,Raw_Q!$Q$2:$Q$600,0)),"")) -> FY2026Q4E | B17: =IF(Stock_Card!$B$2="","",IFERROR(IF(SUMIFS(Raw_Q!$E$2:$E$600,Raw_Q!$A$2:$A$600,Stock_Card!$B$2,Raw_Q!$P$2:$P$600,0)=0,"",SUMIFS(Raw_Q!$E$2:$E$600,Raw_Q!$A$2:$A$600,Stock_Card!$B$2,Raw_Q!$P$2:$P$600,0)),"")) -> 46294 | C17: =IF(Stock_Card!$B$2="","",IFERROR(SUMIFS(Raw_Q!$I$2:$I$600,Raw_Q!$A$2:$A$600,Stock_Card!$B$2,Raw_Q!$P$2:$P$600,0),"")) -> 0 | D17: =IF(Stock_Card!$B$2="","",IFERROR((SUMIFS(Raw_Q!$I$2:$I$600,Raw_Q!$A$2:$A$600,Stock_Card!$B$2,Raw_Q!$P$2:$P$600,0)/SUMIFS(Raw_Q!$I$2:$I$600,Raw_Q!$A$2:$A$600,Stock_Card!$B$2,Raw_Q!$P$2:$P$600,1)-1),"")) -> -1 | E17: =IF(Stock_Card!$B$2="","",IFERROR((SUMIFS(Raw_Q!$I$2:$I$600,Raw_Q!$A$2:$A$600,Stock_Card!$B$2,Raw_Q!$P$2:$P$600,1)/SUMIFS(Raw_Q!$I$2:$I$600,Raw_Q!$A$2:$A$600,Stock_Card!$B$2,Raw_Q!$P$2:$P$600,2)-1),"")) -> -0.015892574 | F17: =IF(Stock_Card!$B$2="","",IFERROR(((SUMIFS(Raw_Q!$I$2:$I$600,Raw_Q!$A$2:$A$600,Stock_Card!$B$2,Raw_Q!$P$2:$P$600,0)/SUMIFS(Raw_Q!$I$2:$I$600,Raw_Q!$A$2:$A$600,Stock_Card!$B$2,Raw_Q!$P$2:$P$600,1)-1)-(SUMIFS(Raw_Q!$I$2:$I$600,Raw_Q!$A$2:$A$600,Stock_Card!$B$2,Raw_Q!$P$2:$P$600,1)/SUMIFS(Raw_Q!$I$2:$I$600,Raw_Q!$A$2:$A$600,Stock_Card!$B$2,Raw_Q!$P$2:$P$600,2)-1))*100,"")) -> -98.410743 | G17: =IF(Stock_Card!$B$2="","",IFERROR(IF(NOT(ISNUMBER(D17)),"",IF(D17>0,IF(F17>0,"成長且加速","成長但減速"),IF(F17>0,"衰退但收斂","衰退且惡化"))),"")) -> 衰退且惡化 | H17: =IF(Stock_Card!$B$2="","",IFERROR(((SUMIFS(Raw_Q!$I$2:$I$600,Raw_Q!$A$2:$A$600,Stock_Card!$B$2,Raw_Q!$P$2:$P$600,0)/SUMIFS(Raw_Q!$I$2:$I$600,Raw_Q!$A$2:$A$600,Stock_Card!$B$2,Raw_Q!$P$2:$P$600,1)-1)-(SUMIFS(Raw_Q!$I$2:$I$600,Raw_Q!$A$2:$A$600,Stock_Card!$B$2,Raw_Q!$P$2:$P$600,4)/SUMIFS(Raw_Q!$I$2:$I$600,Raw_Q!$A$2:$A$600,Stock_Card!$B$2,Raw_Q!$P$2:$P$600,5)-1))*100,"")) -> -108.96465 | I17: =IF(Stock_Card!$B$2="","",IFERROR((SUMIFS(Raw_Q!$I$2:$I$600,Raw_Q!$A$2:$A$600,Stock_Card!$B$2,Raw_Q!$P$2:$P$600,0)/SUMIFS(Raw_Q!$I$2:$I$600,Raw_Q!$A$2:$A$600,Stock_Card!$B$2,Raw_Q!$P$2:$P$600,4)-1),"")) -> -1 | J17: =IF(Stock_Card!$B$2="","",IFERROR(SUMIFS(Raw_Q!$J$2:$J$600,Raw_Q!$A$2:$A$600,Stock_Card!$B$2,Raw_Q!$P$2:$P$600,0)/SUMIFS(Raw_Q!$I$2:$I$600,Raw_Q!$A$2:$A$600,Stock_Card!$B$2,Raw_Q!$P$2:$P$600,0),"")) | K17: =IF(Stock_Card!$B$2="","",IFERROR((SUMIFS(Raw_Q!$J$2:$J$600,Raw_Q!$A$2:$A$600,Stock_Card!$B$2,Raw_Q!$P$2:$P$600,0)/SUMIFS(Raw_Q!$I$2:$I$600,Raw_Q!$A$2:$A$600,Stock_Card!$B$2,Raw_Q!$P$2:$P$600,0)-SUMIFS(Raw_Q!$J$2:$J$600,Raw_Q!$A$2:$A$600,Stock_Card!$B$2,Raw_Q!$P$2:$P$600,4)/SUMIFS(Raw_Q!$I$2:$I$600,Raw_Q!$A$2:$A$600,Stock_Card!$B$2,Raw_Q!$P$2:$P$600,4))*10000,"")) | L17: =IF(Stock_Card!$B$2="","",IFERROR(SUMIFS(Raw_Q!$K$2:$K$600,Raw_Q!$A$2:$A$600,Stock_Card!$B$2,Raw_Q!$P$2:$P$600,0),"")) -> 1.97656 | M17: =IF(Stock_Card!$B$2="","",IFERROR((SUMIFS(Raw_Q!$K$2:$K$600,Raw_Q!$A$2:$A$600,Stock_Card!$B$2,Raw_Q!$P$2:$P$600,0)/SUMIFS(Raw_Q!$K$2:$K$600,Raw_Q!$A$2:$A$600,Stock_Card!$B$2,Raw_Q!$P$2:$P$600,4)-1),"")) -> 0.068410811 | N17: =IF(Stock_Card!$B$2="","",IFERROR(SUMIFS(Raw_Q!$N$2:$N$600,Raw_Q!$A$2:$A$600,Stock_Card!$B$2,Raw_Q!$P$2:$P$600,0),"")) -> 0 | O17: =IF(Stock_Card!$B$2="","",IF(0=0,"預估","實際")) -> 預估
A18: 營收QoQ（季度成長率）＝ 本季營收 ÷ 上一季營收 − 1。加速度(pp) ＝ 本季QoQ − 上一季QoQ。注意：加速度是「成長率的變化」，不是營收的變化——營收在衰退但衰退幅度縮小時，加速度一樣是正的。「動能判讀」欄就是為了讓正負號不再誤導。
A19: ⚠ 加速度(pp) 會被季節性主宰：旺季那一季 QoQ 天生就高、淡季天生就低，所以這一欄每年會在同一季出現同樣的大幅震盪，那是季節性不是動能。同期加速度(pp) ＝ 本季QoQ − 去年同一財季的QoQ：一樣是在比「季度成長率」，但拿去年同一季當基準，季節性自動抵消，剩下的才是真正的動能變化。最後一列黃底＝當季預估。
A21: 以下兩張矩陣同一欄＝同一個財季。長條排列會把旺季誤讀成成長，排成矩陣才看得出季節性與真實趨勢。黃底斜體＝當季預估。
A22: EPS (Adjusted) · 年 × 季矩陣
A23: 財年 | B23: Q1 | C23: Q2 | D23: Q3 | E23: Q4 | F23: FY 合計 | G23: FY YoY
A24: =IF(Stock_Card!$B$2="","",IFERROR($Z$1-4,"")) -> 2022 | B24: =IF(Stock_Card!$B$2="","",IF(COUNTIFS(Raw_Q!$A$2:$A$600,Stock_Card!$B$2,Raw_Q!$C$2:$C$600,$A24,Raw_Q!$D$2:$D$600,1)=0,"",SUMIFS(Raw_Q!$K$2:$K$600,Raw_Q!$A$2:$A$600,Stock_Card!$B$2,Raw_Q!$C$2:$C$600,$A24,Raw_Q!$D$2:$D$600,1))) -> 2.1 | C24: =IF(Stock_Card!$B$2="","",IF(COUNTIFS(Raw_Q!$A$2:$A$600,Stock_Card!$B$2,Raw_Q!$C$2:$C$600,$A24,Raw_Q!$D$2:$D$600,2)=0,"",SUMIFS(Raw_Q!$K$2:$K$600,Raw_Q!$A$2:$A$600,Stock_Card!$B$2,Raw_Q!$C$2:$C$600,$A24,Raw_Q!$D$2:$D$600,2))) -> 1.52 | D24: =IF(Stock_Card!$B$2="","",IF(COUNTIFS(Raw_Q!$A$2:$A$600,Stock_Card!$B$2,Raw_Q!$C$2:$C$600,$A24,Raw_Q!$D$2:$D$600,3)=0,"",SUMIFS(Raw_Q!$K$2:$K$600,Raw_Q!$A$2:$A$600,Stock_Card!$B$2,Raw_Q!$C$2:$C$600,$A24,Raw_Q!$D$2:$D$600,3))) -> 1.2 | E24: =IF(Stock_Card!$B$2="","",IF(COUNTIFS(Raw_Q!$A$2:$A$600,Stock_Card!$B$2,Raw_Q!$C$2:$C$600,$A24,Raw_Q!$D$2:$D$600,4)=0,"",SUMIFS(Raw_Q!$K$2:$K$600,Raw_Q!$A$2:$A$600,Stock_Card!$B$2,Raw_Q!$C$2:$C$600,$A24,Raw_Q!$D$2:$D$600,4))) -> 1.29 | F24: =IF(Stock_Card!$B$2="","",IF(COUNTIFS(Raw_Q!$A$2:$A$600,Stock_Card!$B$2,Raw_Q!$C$2:$C$600,$A24)<4,"未滿4季",SUM(B24:E24))) -> 6.11
A25: =IF(Stock_Card!$B$2="","",IFERROR($Z$1-3,"")) -> 2023 | B25: =IF(Stock_Card!$B$2="","",IF(COUNTIFS(Raw_Q!$A$2:$A$600,Stock_Card!$B$2,Raw_Q!$C$2:$C$600,$A25,Raw_Q!$D$2:$D$600,1)=0,"",SUMIFS(Raw_Q!$K$2:$K$600,Raw_Q!$A$2:$A$600,Stock_Card!$B$2,Raw_Q!$C$2:$C$600,$A25,Raw_Q!$D$2:$D$600,1))) -> 1.88 | C25: =IF(Stock_Card!$B$2="","",IF(COUNTIFS(Raw_Q!$A$2:$A$600,Stock_Card!$B$2,Raw_Q!$C$2:$C$600,$A25,Raw_Q!$D$2:$D$600,2)=0,"",SUMIFS(Raw_Q!$K$2:$K$600,Raw_Q!$A$2:$A$600,Stock_Card!$B$2,Raw_Q!$C$2:$C$600,$A25,Raw_Q!$D$2:$D$600,2))) -> 1.52 | D25: =IF(Stock_Card!$B$2="","",IF(COUNTIFS(Raw_Q!$A$2:$A$600,Stock_Card!$B$2,Raw_Q!$C$2:$C$600,$A25,Raw_Q!$D$2:$D$600,3)=0,"",SUMIFS(Raw_Q!$K$2:$K$600,Raw_Q!$A$2:$A$600,Stock_Card!$B$2,Raw_Q!$C$2:$C$600,$A25,Raw_Q!$D$2:$D$600,3))) -> 1.26 | E25: =IF(Stock_Card!$B$2="","",IF(COUNTIFS(Raw_Q!$A$2:$A$600,Stock_Card!$B$2,Raw_Q!$C$2:$C$600,$A25,Raw_Q!$D$2:$D$600,4)=0,"",SUMIFS(Raw_Q!$K$2:$K$600,Raw_Q!$A$2:$A$600,Stock_Card!$B$2,Raw_Q!$C$2:$C$600,$A25,Raw_Q!$D$2:$D$600,4))) -> 1.46 | F25: =IF(Stock_Card!$B$2="","",IF(COUNTIFS(Raw_Q!$A$2:$A$600,Stock_Card!$B$2,Raw_Q!$C$2:$C$600,$A25)<4,"未滿4季",SUM(B25:E25))) -> 6.12 | G25: =IFERROR(IF(OR(NOT(ISNUMBER(F25)),NOT(ISNUMBER(F24))),"",F25/F24-1),"") -> 0.0016366612
A26: =IF(Stock_Card!$B$2="","",IFERROR($Z$1-2,"")) -> 2024 | B26: =IF(Stock_Card!$B$2="","",IF(COUNTIFS(Raw_Q!$A$2:$A$600,Stock_Card!$B$2,Raw_Q!$C$2:$C$600,$A26,Raw_Q!$D$2:$D$600,1)=0,"",SUMIFS(Raw_Q!$K$2:$K$600,Raw_Q!$A$2:$A$600,Stock_Card!$B$2,Raw_Q!$C$2:$C$600,$A26,Raw_Q!$D$2:$D$600,1))) -> 2.18 | C26: =IF(Stock_Card!$B$2="","",IF(COUNTIFS(Raw_Q!$A$2:$A$600,Stock_Card!$B$2,Raw_Q!$C$2:$C$600,$A26,Raw_Q!$D$2:$D$600,2)=0,"",SUMIFS(Raw_Q!$K$2:$K$600,Raw_Q!$A$2:$A$600,Stock_Card!$B$2,Raw_Q!$C$2:$C$600,$A26,Raw_Q!$D$2:$D$600,2))) -> 1.53 | D26: =IF(Stock_Card!$B$2="","",IF(COUNTIFS(Raw_Q!$A$2:$A$600,Stock_Card!$B$2,Raw_Q!$C$2:$C$600,$A26,Raw_Q!$D$2:$D$600,3)=0,"",SUMIFS(Raw_Q!$K$2:$K$600,Raw_Q!$A$2:$A$600,Stock_Card!$B$2,Raw_Q!$C$2:$C$600,$A26,Raw_Q!$D$2:$D$600,3))) -> 1.4 | E26: =IF(Stock_Card!$B$2="","",IF(COUNTIFS(Raw_Q!$A$2:$A$600,Stock_Card!$B$2,Raw_Q!$C$2:$C$600,$A26,Raw_Q!$D$2:$D$600,4)=0,"",SUMIFS(Raw_Q!$K$2:$K$600,Raw_Q!$A$2:$A$600,Stock_Card!$B$2,Raw_Q!$C$2:$C$600,$A26,Raw_Q!$D$2:$D$600,4))) -> 0.97 | F26: =IF(Stock_Card!$B$2="","",IF(COUNTIFS(Raw_Q!$A$2:$A$600,Stock_Card!$B$2,Raw_Q!$C$2:$C$600,$A26)<4,"未滿4季",SUM(B26:E26))) -> 6.08 | G26: =IFERROR(IF(OR(NOT(ISNUMBER(F26)),NOT(ISNUMBER(F25))),"",F26/F25-1),"") -> -0.0065359477
A27: =IF(Stock_Card!$B$2="","",IFERROR($Z$1-1,"")) -> 2025 | B27: =IF(Stock_Card!$B$2="","",IF(COUNTIFS(Raw_Q!$A$2:$A$600,Stock_Card!$B$2,Raw_Q!$C$2:$C$600,$A27,Raw_Q!$D$2:$D$600,1)=0,"",SUMIFS(Raw_Q!$K$2:$K$600,Raw_Q!$A$2:$A$600,Stock_Card!$B$2,Raw_Q!$C$2:$C$600,$A27,Raw_Q!$D$2:$D$600,1))) -> 2.4 | C27: =IF(Stock_Card!$B$2="","",IF(COUNTIFS(Raw_Q!$A$2:$A$600,Stock_Card!$B$2,Raw_Q!$C$2:$C$600,$A27,Raw_Q!$D$2:$D$600,2)=0,"",SUMIFS(Raw_Q!$K$2:$K$600,Raw_Q!$A$2:$A$600,Stock_Card!$B$2,Raw_Q!$C$2:$C$600,$A27,Raw_Q!$D$2:$D$600,2))) -> 1.65 | D27: =IF(Stock_Card!$B$2="","",IF(COUNTIFS(Raw_Q!$A$2:$A$600,Stock_Card!$B$2,Raw_Q!$C$2:$C$600,$A27,Raw_Q!$D$2:$D$600,3)=0,"",SUMIFS(Raw_Q!$K$2:$K$600,Raw_Q!$A$2:$A$600,Stock_Card!$B$2,Raw_Q!$C$2:$C$600,$A27,Raw_Q!$D$2:$D$600,3))) -> 1.57 | E27: =IF(Stock_Card!$B$2="","",IF(COUNTIFS(Raw_Q!$A$2:$A$600,Stock_Card!$B$2,Raw_Q!$C$2:$C$600,$A27,Raw_Q!$D$2:$D$600,4)=0,"",SUMIFS(Raw_Q!$K$2:$K$600,Raw_Q!$A$2:$A$600,Stock_Card!$B$2,Raw_Q!$C$2:$C$600,$A27,Raw_Q!$D$2:$D$600,4))) -> 1.85 | F27: =IF(Stock_Card!$B$2="","",IF(COUNTIFS(Raw_Q!$A$2:$A$600,Stock_Card!$B$2,Raw_Q!$C$2:$C$600,$A27)<4,"未滿4季",SUM(B27:E27))) -> 7.47 | G27: =IFERROR(IF(OR(NOT(ISNUMBER(F27)),NOT(ISNUMBER(F26))),"",F27/F26-1),"") -> 0.22861842
A28: =IF(Stock_Card!$B$2="","",IFERROR($Z$1-0,"")) -> 2026 | B28: =IF(Stock_Card!$B$2="","",IF(COUNTIFS(Raw_Q!$A$2:$A$600,Stock_Card!$B$2,Raw_Q!$C$2:$C$600,$A28,Raw_Q!$D$2:$D$600,1)=0,"",SUMIFS(Raw_Q!$K$2:$K$600,Raw_Q!$A$2:$A$600,Stock_Card!$B$2,Raw_Q!$C$2:$C$600,$A28,Raw_Q!$D$2:$D$600,1))) -> 2.84 | C28: =IF(Stock_Card!$B$2="","",IF(COUNTIFS(Raw_Q!$A$2:$A$600,Stock_Card!$B$2,Raw_Q!$C$2:$C$600,$A28,Raw_Q!$D$2:$D$600,2)=0,"",SUMIFS(Raw_Q!$K$2:$K$600,Raw_Q!$A$2:$A$600,Stock_Card!$B$2,Raw_Q!$C$2:$C$600,$A28,Raw_Q!$D$2:$D$600,2))) -> 2.01 | D28: =IF(Stock_Card!$B$2="","",IF(COUNTIFS(Raw_Q!$A$2:$A$600,Stock_Card!$B$2,Raw_Q!$C$2:$C$600,$A28,Raw_Q!$D$2:$D$600,3)=0,"",SUMIFS(Raw_Q!$K$2:$K$600,Raw_Q!$A$2:$A$600,Stock_Card!$B$2,Raw_Q!$C$2:$C$600,$A28,Raw_Q!$D$2:$D$600,3))) -> 2.02 | E28: =IF(Stock_Card!$B$2="","",IF(COUNTIFS(Raw_Q!$A$2:$A$600,Stock_Card!$B$2,Raw_Q!$C$2:$C$600,$A28,Raw_Q!$D$2:$D$600,4)=0,"",SUMIFS(Raw_Q!$K$2:$K$600,Raw_Q!$A$2:$A$600,Stock_Card!$B$2,Raw_Q!$C$2:$C$600,$A28,Raw_Q!$D$2:$D$600,4))) -> 1.97656 | F28: =IF(Stock_Card!$B$2="","",IF(COUNTIFS(Raw_Q!$A$2:$A$600,Stock_Card!$B$2,Raw_Q!$C$2:$C$600,$A28)<4,"未滿4季",SUM(B28:E28))) -> 8.84656 | G28: =IFERROR(IF(OR(NOT(ISNUMBER(F28)),NOT(ISNUMBER(F27))),"",F28/F27-1),"") -> 0.18427845
A30: ↓ 這張就是「每季營收成長率」，季節可比。
A31: 營收 YoY 成長率 · 年 × 季矩陣
A32: 財年 | B32: Q1 | C32: Q2 | D32: Q3 | E32: Q4
A33: =IF(Stock_Card!$B$2="","",IFERROR($Z$1-4,"")) -> 2022 | B33: =IF(Stock_Card!$B$2="","",IF(COUNTIFS(Raw_Q!$A$2:$A$600,Stock_Card!$B$2,Raw_Q!$C$2:$C$600,$A33,Raw_Q!$D$2:$D$600,1)=0,"",IFERROR(SUMIFS(Raw_Q!$I$2:$I$600,Raw_Q!$A$2:$A$600,Stock_Card!$B$2,Raw_Q!$C$2:$C$600,$A33,Raw_Q!$D$2:$D$600,1)/SUMIFS(Raw_Q!$I$2:$I$600,Raw_Q!$A$2:$A$600,Stock_Card!$B$2,Raw_Q!$C$2:$C$600,$A33-1,Raw_Q!$D$2:$D$600,1)-1,""))) -> 0.11222283 | C33: =IF(Stock_Card!$B$2="","",IF(COUNTIFS(Raw_Q!$A$2:$A$600,Stock_Card!$B$2,Raw_Q!$C$2:$C$600,$A33,Raw_Q!$D$2:$D$600,2)=0,"",IFERROR(SUMIFS(Raw_Q!$I$2:$I$600,Raw_Q!$A$2:$A$600,Stock_Card!$B$2,Raw_Q!$C$2:$C$600,$A33,Raw_Q!$D$2:$D$600,2)/SUMIFS(Raw_Q!$I$2:$I$600,Raw_Q!$A$2:$A$600,Stock_Card!$B$2,Raw_Q!$C$2:$C$600,$A33-1,Raw_Q!$D$2:$D$600,2)-1,""))) -> 0.085885872 | D33: =IF(Stock_Card!$B$2="","",IF(COUNTIFS(Raw_Q!$A$2:$A$600,Stock_Card!$B$2,Raw_Q!$C$2:$C$600,$A33,Raw_Q!$D$2:$D$600,3)=0,"",IFERROR(SUMIFS(Raw_Q!$I$2:$I$600,Raw_Q!$A$2:$A$600,Stock_Card!$B$2,Raw_Q!$C$2:$C$600,$A33,Raw_Q!$D$2:$D$600,3)/SUMIFS(Raw_Q!$I$2:$I$600,Raw_Q!$A$2:$A$600,Stock_Card!$B$2,Raw_Q!$C$2:$C$600,$A33-1,Raw_Q!$D$2:$D$600,3)-1,""))) -> 0.018726822 | E33: =IF(Stock_Card!$B$2="","",IF(COUNTIFS(Raw_Q!$A$2:$A$600,Stock_Card!$B$2,Raw_Q!$C$2:$C$600,$A33,Raw_Q!$D$2:$D$600,4)=0,"",IFERROR(SUMIFS(Raw_Q!$I$2:$I$600,Raw_Q!$A$2:$A$600,Stock_Card!$B$2,Raw_Q!$C$2:$C$600,$A33,Raw_Q!$D$2:$D$600,4)/SUMIFS(Raw_Q!$I$2:$I$600,Raw_Q!$A$2:$A$600,Stock_Card!$B$2,Raw_Q!$C$2:$C$600,$A33-1,Raw_Q!$D$2:$D$600,4)-1,""))) -> 0.08140595
A34: =IF(Stock_Card!$B$2="","",IFERROR($Z$1-3,"")) -> 2023 | B34: =IF(Stock_Card!$B$2="","",IF(COUNTIFS(Raw_Q!$A$2:$A$600,Stock_Card!$B$2,Raw_Q!$C$2:$C$600,$A34,Raw_Q!$D$2:$D$600,1)=0,"",IFERROR(SUMIFS(Raw_Q!$I$2:$I$600,Raw_Q!$A$2:$A$600,Stock_Card!$B$2,Raw_Q!$C$2:$C$600,$A34,Raw_Q!$D$2:$D$600,1)/SUMIFS(Raw_Q!$I$2:$I$600,Raw_Q!$A$2:$A$600,Stock_Card!$B$2,Raw_Q!$C$2:$C$600,$A34-1,Raw_Q!$D$2:$D$600,1)-1,""))) -> -0.054790431 | C34: =IF(Stock_Card!$B$2="","",IF(COUNTIFS(Raw_Q!$A$2:$A$600,Stock_Card!$B$2,Raw_Q!$C$2:$C$600,$A34,Raw_Q!$D$2:$D$600,2)=0,"",IFERROR(SUMIFS(Raw_Q!$I$2:$I$600,Raw_Q!$A$2:$A$600,Stock_Card!$B$2,Raw_Q!$C$2:$C$600,$A34,Raw_Q!$D$2:$D$600,2)/SUMIFS(Raw_Q!$I$2:$I$600,Raw_Q!$A$2:$A$600,Stock_Card!$B$2,Raw_Q!$C$2:$C$600,$A34-1,Raw_Q!$D$2:$D$600,2)-1,""))) -> -0.025103312 | D34: =IF(Stock_Card!$B$2="","",IF(COUNTIFS(Raw_Q!$A$2:$A$600,Stock_Card!$B$2,Raw_Q!$C$2:$C$600,$A34,Raw_Q!$D$2:$D$600,3)=0,"",IFERROR(SUMIFS(Raw_Q!$I$2:$I$600,Raw_Q!$A$2:$A$600,Stock_Card!$B$2,Raw_Q!$C$2:$C$600,$A34,Raw_Q!$D$2:$D$600,3)/SUMIFS(Raw_Q!$I$2:$I$600,Raw_Q!$A$2:$A$600,Stock_Card!$B$2,Raw_Q!$C$2:$C$600,$A34-1,Raw_Q!$D$2:$D$600,3)-1,""))) -> -0.014006919 | E34: =IF(Stock_Card!$B$2="","",IF(COUNTIFS(Raw_Q!$A$2:$A$600,Stock_Card!$B$2,Raw_Q!$C$2:$C$600,$A34,Raw_Q!$D$2:$D$600,4)=0,"",IFERROR(SUMIFS(Raw_Q!$I$2:$I$600,Raw_Q!$A$2:$A$600,Stock_Card!$B$2,Raw_Q!$C$2:$C$600,$A34,Raw_Q!$D$2:$D$600,4)/SUMIFS(Raw_Q!$I$2:$I$600,Raw_Q!$A$2:$A$600,Stock_Card!$B$2,Raw_Q!$C$2:$C$600,$A34-1,Raw_Q!$D$2:$D$600,4)-1,""))) -> -0.0071883389
A35: =IF(Stock_Card!$B$2="","",IFERROR($Z$1-2,"")) -> 2024 | B35: =IF(Stock_Card!$B$2="","",IF(COUNTIFS(Raw_Q!$A$2:$A$600,Stock_Card!$B$2,Raw_Q!$C$2:$C$600,$A35,Raw_Q!$D$2:$D$600,1)=0,"",IFERROR(SUMIFS(Raw_Q!$I$2:$I$600,Raw_Q!$A$2:$A$600,Stock_Card!$B$2,Raw_Q!$C$2:$C$600,$A35,Raw_Q!$D$2:$D$600,1)/SUMIFS(Raw_Q!$I$2:$I$600,Raw_Q!$A$2:$A$600,Stock_Card!$B$2,Raw_Q!$C$2:$C$600,$A35-1,Raw_Q!$D$2:$D$600,1)-1,""))) -> 0.020665107 | C35: =IF(Stock_Card!$B$2="","",IF(COUNTIFS(Raw_Q!$A$2:$A$600,Stock_Card!$B$2,Raw_Q!$C$2:$C$600,$A35,Raw_Q!$D$2:$D$600,2)=0,"",IFERROR(SUMIFS(Raw_Q!$I$2:$I$600,Raw_Q!$A$2:$A$600,Stock_Card!$B$2,Raw_Q!$C$2:$C$600,$A35,Raw_Q!$D$2:$D$600,2)/SUMIFS(Raw_Q!$I$2:$I$600,Raw_Q!$A$2:$A$600,Stock_Card!$B$2,Raw_Q!$C$2:$C$600,$A35-1,Raw_Q!$D$2:$D$600,2)-1,""))) -> -0.043053271 | D35: =IF(Stock_Card!$B$2="","",IF(COUNTIFS(Raw_Q!$A$2:$A$600,Stock_Card!$B$2,Raw_Q!$C$2:$C$600,$A35,Raw_Q!$D$2:$D$600,3)=0,"",IFERROR(SUMIFS(Raw_Q!$I$2:$I$600,Raw_Q!$A$2:$A$600,Stock_Card!$B$2,Raw_Q!$C$2:$C$600,$A35,Raw_Q!$D$2:$D$600,3)/SUMIFS(Raw_Q!$I$2:$I$600,Raw_Q!$A$2:$A$600,Stock_Card!$B$2,Raw_Q!$C$2:$C$600,$A35-1,Raw_Q!$D$2:$D$600,3)-1,""))) -> 0.048657041 | E35: =IF(Stock_Card!$B$2="","",IF(COUNTIFS(Raw_Q!$A$2:$A$600,Stock_Card!$B$2,Raw_Q!$C$2:$C$600,$A35,Raw_Q!$D$2:$D$600,4)=0,"",IFERROR(SUMIFS(Raw_Q!$I$2:$I$600,Raw_Q!$A$2:$A$600,Stock_Card!$B$2,Raw_Q!$C$2:$C$600,$A35,Raw_Q!$D$2:$D$600,4)/SUMIFS(Raw_Q!$I$2:$I$600,Raw_Q!$A$2:$A$600,Stock_Card!$B$2,Raw_Q!$C$2:$C$600,$A35-1,Raw_Q!$D$2:$D$600,4)-1,""))) -> 0.060694094
A36: =IF(Stock_Card!$B$2="","",IFERROR($Z$1-1,"")) -> 2025 | B36: =IF(Stock_Card!$B$2="","",IF(COUNTIFS(Raw_Q!$A$2:$A$600,Stock_Card!$B$2,Raw_Q!$C$2:$C$600,$A36,Raw_Q!$D$2:$D$600,1)=0,"",IFERROR(SUMIFS(Raw_Q!$I$2:$I$600,Raw_Q!$A$2:$A$600,Stock_Card!$B$2,Raw_Q!$C$2:$C$600,$A36,Raw_Q!$D$2:$D$600,1)/SUMIFS(Raw_Q!$I$2:$I$600,Raw_Q!$A$2:$A$600,Stock_Card!$B$2,Raw_Q!$C$2:$C$600,$A36-1,Raw_Q!$D$2:$D$600,1)-1,""))) -> 0.039514949 | C36: =IF(Stock_Card!$B$2="","",IF(COUNTIFS(Raw_Q!$A$2:$A$600,Stock_Card!$B$2,Raw_Q!$C$2:$C$600,$A36,Raw_Q!$D$2:$D$600,2)=0,"",IFERROR(SUMIFS(Raw_Q!$I$2:$I$600,Raw_Q!$A$2:$A$600,Stock_Card!$B$2,Raw_Q!$C$2:$C$600,$A36,Raw_Q!$D$2:$D$600,2)/SUMIFS(Raw_Q!$I$2:$I$600,Raw_Q!$A$2:$A$600,Stock_Card!$B$2,Raw_Q!$C$2:$C$600,$A36-1,Raw_Q!$D$2:$D$600,2)-1,""))) -> 0.050753143 | D36: =IF(Stock_Card!$B$2="","",IF(COUNTIFS(Raw_Q!$A$2:$A$600,Stock_Card!$B$2,Raw_Q!$C$2:$C$600,$A36,Raw_Q!$D$2:$D$600,3)=0,"",IFERROR(SUMIFS(Raw_Q!$I$2:$I$600,Raw_Q!$A$2:$A$600,Stock_Card!$B$2,Raw_Q!$C$2:$C$600,$A36,Raw_Q!$D$2:$D$600,3)/SUMIFS(Raw_Q!$I$2:$I$600,Raw_Q!$A$2:$A$600,Stock_Card!$B$2,Raw_Q!$C$2:$C$600,$A36-1,Raw_Q!$D$2:$D$600,3)-1,""))) -> 0.096284552 | E36: =IF(Stock_Card!$B$2="","",IF(COUNTIFS(Raw_Q!$A$2:$A$600,Stock_Card!$B$2,Raw_Q!$C$2:$C$600,$A36,Raw_Q!$D$2:$D$600,4)=0,"",IFERROR(SUMIFS(Raw_Q!$I$2:$I$600,Raw_Q!$A$2:$A$600,Stock_Card!$B$2,Raw_Q!$C$2:$C$600,$A36,Raw_Q!$D$2:$D$600,4)/SUMIFS(Raw_Q!$I$2:$I$600,Raw_Q!$A$2:$A$600,Stock_Card!$B$2,Raw_Q!$C$2:$C$600,$A36-1,Raw_Q!$D$2:$D$600,4)-1,""))) -> 0.07938481
A37: =IF(Stock_Card!$B$2="","",IFERROR($Z$1-0,"")) -> 2026 | B37: =IF(Stock_Card!$B$2="","",IF(COUNTIFS(Raw_Q!$A$2:$A$600,Stock_Card!$B$2,Raw_Q!$C$2:$C$600,$A37,Raw_Q!$D$2:$D$600,1)=0,"",IFERROR(SUMIFS(Raw_Q!$I$2:$I$600,Raw_Q!$A$2:$A$600,Stock_Card!$B$2,Raw_Q!$C$2:$C$600,$A37,Raw_Q!$D$2:$D$600,1)/SUMIFS(Raw_Q!$I$2:$I$600,Raw_Q!$A$2:$A$600,Stock_Card!$B$2,Raw_Q!$C$2:$C$600,$A37-1,Raw_Q!$D$2:$D$600,1)-1,""))) -> 0.15652454 | C37: =IF(Stock_Card!$B$2="","",IF(COUNTIFS(Raw_Q!$A$2:$A$600,Stock_Card!$B$2,Raw_Q!$C$2:$C$600,$A37,Raw_Q!$D$2:$D$600,2)=0,"",IFERROR(SUMIFS(Raw_Q!$I$2:$I$600,Raw_Q!$A$2:$A$600,Stock_Card!$B$2,Raw_Q!$C$2:$C$600,$A37,Raw_Q!$D$2:$D$600,2)/SUMIFS(Raw_Q!$I$2:$I$600,Raw_Q!$A$2:$A$600,Stock_Card!$B$2,Raw_Q!$C$2:$C$600,$A37-1,Raw_Q!$D$2:$D$600,2)-1,""))) -> 0.16595182 | D37: =IF(Stock_Card!$B$2="","",IF(COUNTIFS(Raw_Q!$A$2:$A$600,Stock_Card!$B$2,Raw_Q!$C$2:$C$600,$A37,Raw_Q!$D$2:$D$600,3)=0,"",IFERROR(SUMIFS(Raw_Q!$I$2:$I$600,Raw_Q!$A$2:$A$600,Stock_Card!$B$2,Raw_Q!$C$2:$C$600,$A37,Raw_Q!$D$2:$D$600,3)/SUMIFS(Raw_Q!$I$2:$I$600,Raw_Q!$A$2:$A$600,Stock_Card!$B$2,Raw_Q!$C$2:$C$600,$A37-1,Raw_Q!$D$2:$D$600,3)-1,""))) -> 0.16356502 | E37: =IF(Stock_Card!$B$2="","",IF(COUNTIFS(Raw_Q!$A$2:$A$600,Stock_Card!$B$2,Raw_Q!$C$2:$C$600,$A37,Raw_Q!$D$2:$D$600,4)=0,"",IFERROR(SUMIFS(Raw_Q!$I$2:$I$600,Raw_Q!$A$2:$A$600,Stock_Card!$B$2,Raw_Q!$C$2:$C$600,$A37,Raw_Q!$D$2:$D$600,4)/SUMIFS(Raw_Q!$I$2:$I$600,Raw_Q!$A$2:$A$600,Stock_Card!$B$2,Raw_Q!$C$2:$C$600,$A37-1,Raw_Q!$D$2:$D$600,4)-1,""))) -> -1

Sheet _Manifest
A1: 資料完整度儀表板
A3: ticker | B3: 實際季數 | C3: 目標 | D3: 最舊季 | E3: 最新實際季 | F3: 當季預估期別 | G3: 下次財報日 | H3: 距財報(天) | I3: 資料日期 | J3: 狀態
A4: =IF(Calc!$A$2="","",Calc!$A$2) -> AAPL | B4: =IF($A4="","",COUNTIFS(Raw_Q!$A$2:$A$600,$A4,Raw_Q!$F$2:$F$600,"N")) -> 24 | C4: =IF($A4="","",Config!$B$4) -> 24 | D4: =IF($A4="","",IFERROR(SUMIFS(Raw_Q!$E$2:$E$600,Raw_Q!$A$2:$A$600,$A4,Raw_Q!$P$2:$P$600,$B4),"")) -> 44104 | E4: =IF($A4="","",IFERROR(SUMIFS(Raw_Q!$E$2:$E$600,Raw_Q!$A$2:$A$600,$A4,Raw_Q!$P$2:$P$600,1),"")) -> 46203 | F4: =IF($A4="","",IFERROR(INDEX(Raw_Q!$B$2:$B$600,MATCH($A4&"|"&0,Raw_Q!$Q$2:$Q$600,0)),"")) -> FY2026Q4E | G4: =IF($A4="","",IFERROR(INDEX(Raw_Price!$D$2:$D$100,MATCH($A4,Raw_Price!$A$2:$A$100,0)),"")) -> 46324 | H4: =IF($A4="","",IFERROR(INDEX(Raw_Price!$D$2:$D$100,MATCH($A4,Raw_Price!$A$2:$A$100,0))-TODAY(),"")) -> 44 | I4: =IF($A4="","",IFERROR(INDEX(Raw_Price!$E$2:$E$100,MATCH($A4,Raw_Price!$A$2:$A$100,0)),"")) -> 46280 | J4: =IF($A4="","",IF($B4=0,"未抓取",IF($B4<$C4,"需補歷史 ("&($C4-$B4)&" 季)",IF(TODAY()>$G4,"待更新財報","OK")))) -> OK
A5: =IF(Calc!$A$3="","",Calc!$A$3) -> MSFT | B5: =IF($A5="","",COUNTIFS(Raw_Q!$A$2:$A$600,$A5,Raw_Q!$F$2:$F$600,"N")) -> 24 | C5: =IF($A5="","",Config!$B$4) -> 24 | D5: =IF($A5="","",IFERROR(SUMIFS(Raw_Q!$E$2:$E$600,Raw_Q!$A$2:$A$600,$A5,Raw_Q!$P$2:$P$600,$B5),"")) -> 44104 | E5: =IF($A5="","",IFERROR(SUMIFS(Raw_Q!$E$2:$E$600,Raw_Q!$A$2:$A$600,$A5,Raw_Q!$P$2:$P$600,1),"")) -> 46203 | F5: =IF($A5="","",IFERROR(INDEX(Raw_Q!$B$2:$B$600,MATCH($A5&"|"&0,Raw_Q!$Q$2:$Q$600,0)),"")) -> FY2027Q1E | G5: =IF($A5="","",IFERROR(INDEX(Raw_Price!$D$2:$D$100,MATCH($A5,Raw_Price!$A$2:$A$100,0)),"")) -> 46323 | H5: =IF($A5="","",IFERROR(INDEX(Raw_Price!$D$2:$D$100,MATCH($A5,Raw_Price!$A$2:$A$100,0))-TODAY(),"")) -> 43 | I5: =IF($A5="","",IFERROR(INDEX(Raw_Price!$E$2:$E$100,MATCH($A5,Raw_Price!$A$2:$A$100,0)),"")) -> 46280 | J5: =IF($A5="","",IF($B5=0,"未抓取",IF($B5<$C5,"需補歷史 ("&($C5-$B5)&" 季)",IF(TODAY()>$G5,"待更新財報","OK")))) -> OK
A6: =IF(Calc!$A$4="","",Calc!$A$4) -> NVDA | B6: =IF($A6="","",COUNTIFS(Raw_Q!$A$2:$A$600,$A6,Raw_Q!$F$2:$F$600,"N")) -> 25 | C6: =IF($A6="","",Config!$B$4) -> 24 | D6: =IF($A6="","",IFERROR(SUMIFS(Raw_Q!$E$2:$E$600,Raw_Q!$A$2:$A$600,$A6,Raw_Q!$P$2:$P$600,$B6),"")) -> 44043 | E6: =IF($A6="","",IFERROR(SUMIFS(Raw_Q!$E$2:$E$600,Raw_Q!$A$2:$A$600,$A6,Raw_Q!$P$2:$P$600,1),"")) -> 46234 | F6: =IF($A6="","",IFERROR(INDEX(Raw_Q!$B$2:$B$600,MATCH($A6&"|"&0,Raw_Q!$Q$2:$Q$600,0)),"")) -> FY2027Q3E | G6: =IF($A6="","",IFERROR(INDEX(Raw_Price!$D$2:$D$100,MATCH($A6,Raw_Price!$A$2:$A$100,0)),"")) -> 46343 | H6: =IF($A6="","",IFERROR(INDEX(Raw_Price!$D$2:$D$100,MATCH($A6,Raw_Price!$A$2:$A$100,0))-TODAY(),"")) -> 63 | I6: =IF($A6="","",IFERROR(INDEX(Raw_Price!$E$2:$E$100,MATCH($A6,Raw_Price!$A$2:$A$100,0)),"")) -> 46280 | J6: =IF($A6="","",IF($B6=0,"未抓取",IF($B6<$C6,"需補歷史 ("&($C6-$B6)&" 季)",IF(TODAY()>$G6,"待更新財報","OK")))) -> OK
A7: =IF(Calc!$A$5="","",Calc!$A$5) -> AAOI | B7: =IF($A7="","",COUNTIFS(Raw_Q!$A$2:$A$600,$A7,Raw_Q!$F$2:$F$600,"N")) -> 24 | C7: =IF($A7="","",Config!$B$4) -> 24 | D7: =IF($A7="","",IFERROR(SUMIFS(Raw_Q!$E$2:$E$600,Raw_Q!$A$2:$A$600,$A7,Raw_Q!$P$2:$P$600,$B7),"")) -> 44104 | E7: =IF($A7="","",IFERROR(SUMIFS(Raw_Q!$E$2:$E$600,Raw_Q!$A$2:$A$600,$A7,Raw_Q!$P$2:$P$600,1),"")) -> 46203 | F7: =IF($A7="","",IFERROR(INDEX(Raw_Q!$B$2:$B$600,MATCH($A7&"|"&0,Raw_Q!$Q$2:$Q$600,0)),"")) -> FY2026Q3E | G7: =IF($A7="","",IFERROR(INDEX(Raw_Price!$D$2:$D$100,MATCH($A7,Raw_Price!$A$2:$A$100,0)),"")) -> 46331 | H7: =IF($A7="","",IFERROR(INDEX(Raw_Price!$D$2:$D$100,MATCH($A7,Raw_Price!$A$2:$A$100,0))-TODAY(),"")) -> 51 | I7: =IF($A7="","",IFERROR(INDEX(Raw_Price!$E$2:$E$100,MATCH($A7,Raw_Price!$A$2:$A$100,0)),"")) -> 46280 | J7: =IF($A7="","",IF($B7=0,"未抓取",IF($B7<$C7,"需補歷史 ("&($C7-$B7)&" 季)",IF(TODAY()>$G7,"待更新財報","OK")))) -> OK
A8: =IF(Calc!$A$6="","",Calc!$A$6) -> MRVL | B8: =IF($A8="","",COUNTIFS(Raw_Q!$A$2:$A$600,$A8,Raw_Q!$F$2:$F$600,"N")) -> 24 | C8: =IF($A8="","",Config!$B$4) -> 24 | D8: =IF($A8="","",IFERROR(SUMIFS(Raw_Q!$E$2:$E$600,Raw_Q!$A$2:$A$600,$A8,Raw_Q!$P$2:$P$600,$B8),"")) -> 44135 | E8: =IF($A8="","",IFERROR(SUMIFS(Raw_Q!$E$2:$E$600,Raw_Q!$A$2:$A$600,$A8,Raw_Q!$P$2:$P$600,1),"")) -> 46234 | F8: =IF($A8="","",IFERROR(INDEX(Raw_Q!$B$2:$B$600,MATCH($A8&"|"&0,Raw_Q!$Q$2:$Q$600,0)),"")) -> FY2027Q3E | G8: =IF($A8="","",IFERROR(INDEX(Raw_Price!$D$2:$D$100,MATCH($A8,Raw_Price!$A$2:$A$100,0)),"")) -> 46357 | H8: =IF($A8="","",IFERROR(INDEX(Raw_Price!$D$2:$D$100,MATCH($A8,Raw_Price!$A$2:$A$100,0))-TODAY(),"")) -> 77 | I8: =IF($A8="","",IFERROR(INDEX(Raw_Price!$E$2:$E$100,MATCH($A8,Raw_Price!$A$2:$A$100,0)),"")) -> 46280 | J8: =IF($A8="","",IF($B8=0,"未抓取",IF($B8<$C8,"需補歷史 ("&($C8-$B8)&" 季)",IF(TODAY()>$G8,"待更新財報","OK")))) -> OK
A9: =IF(Calc!$A$7="","",Calc!$A$7) -> MU | B9: =IF($A9="","",COUNTIFS(Raw_Q!$A$2:$A$600,$A9,Raw_Q!$F$2:$F$600,"N")) -> 24 | C9: =IF($A9="","",Config!$B$4) -> 24 | D9: =IF($A9="","",IFERROR(SUMIFS(Raw_Q!$E$2:$E$600,Raw_Q!$A$2:$A$600,$A9,Raw_Q!$P$2:$P$600,$B9),"")) -> 44074 | E9: =IF($A9="","",IFERROR(SUMIFS(Raw_Q!$E$2:$E$600,Raw_Q!$A$2:$A$600,$A9,Raw_Q!$P$2:$P$600,1),"")) -> 46173 | F9: =IF($A9="","",IFERROR(INDEX(Raw_Q!$B$2:$B$600,MATCH($A9&"|"&0,Raw_Q!$Q$2:$Q$600,0)),"")) -> FY2026Q4E | G9: =IF($A9="","",IFERROR(INDEX(Raw_Price!$D$2:$D$100,MATCH($A9,Raw_Price!$A$2:$A$100,0)),"")) -> 46295 | H9: =IF($A9="","",IFERROR(INDEX(Raw_Price!$D$2:$D$100,MATCH($A9,Raw_Price!$A$2:$A$100,0))-TODAY(),"")) -> 15 | I9: =IF($A9="","",IFERROR(INDEX(Raw_Price!$E$2:$E$100,MATCH($A9,Raw_Price!$A$2:$A$100,0)),"")) -> 46280 | J9: =IF($A9="","",IF($B9=0,"未抓取",IF($B9<$C9,"需補歷史 ("&($C9-$B9)&" 季)",IF(TODAY()>$G9,"待更新財報","OK")))) -> OK
A10: =IF(Calc!$A$8="","",Calc!$A$8) -> TER | B10: =IF($A10="","",COUNTIFS(Raw_Q!$A$2:$A$600,$A10,Raw_Q!$F$2:$F$600,"N")) -> 24 | C10: =IF($A10="","",Config!$B$4) -> 24 | D10: =IF($A10="","",IFERROR(SUMIFS(Raw_Q!$E$2:$E$600,Raw_Q!$A$2:$A$600,$A10,Raw_Q!$P$2:$P$600,$B10),"")) -> 44104 | E10: =IF($A10="","",IFERROR(SUMIFS(Raw_Q!$E$2:$E$600,Raw_Q!$A$2:$A$600,$A10,Raw_Q!$P$2:$P$600,1),"")) -> 46203 | F10: =IF($A10="","",IFERROR(INDEX(Raw_Q!$B$2:$B$600,MATCH($A10&"|"&0,Raw_Q!$Q$2:$Q$600,0)),"")) -> FY2026Q3E | G10: =IF($A10="","",IFERROR(INDEX(Raw_Price!$D$2:$D$100,MATCH($A10,Raw_Price!$A$2:$A$100,0)),"")) -> 46316 | H10: =IF($A10="","",IFERROR(INDEX(Raw_Price!$D$2:$D$100,MATCH($A10,Raw_Price!$A$2:$A$100,0))-TODAY(),"")) -> 36 | I10: =IF($A10="","",IFERROR(INDEX(Raw_Price!$E$2:$E$100,MATCH($A10,Raw_Price!$A$2:$A$100,0)),"")) -> 46280 | J10: =IF($A10="","",IF($B10=0,"未抓取",IF($B10<$C10,"需補歷史 ("&($C10-$B10)&" 季)",IF(TODAY()>$G10,"待更新財報","OK")))) -> OK
A11: =IF(Calc!$A$9="","",Calc!$A$9) -> DELL | B11: =IF($A11="","",COUNTIFS(Raw_Q!$A$2:$A$600,$A11,Raw_Q!$F$2:$F$600,"N")) -> 24 | C11: =IF($A11="","",Config!$B$4) -> 24 | D11: =IF($A11="","",IFERROR(SUMIFS(Raw_Q!$E$2:$E$600,Raw_Q!$A$2:$A$600,$A11,Raw_Q!$P$2:$P$600,$B11),"")) -> 44043 | E11: =IF($A11="","",IFERROR(SUMIFS(Raw_Q!$E$2:$E$600,Raw_Q!$A$2:$A$600,$A11,Raw_Q!$P$2:$P$600,1),"")) -> 46142 | F11: =IF($A11="","",IFERROR(INDEX(Raw_Q!$B$2:$B$600,MATCH($A11&"|"&0,Raw_Q!$Q$2:$Q$600,0)),"")) -> FY2027Q2E | G11: =IF($A11="","",IFERROR(INDEX(Raw_Price!$D$2:$D$100,MATCH($A11,Raw_Price!$A$2:$A$100,0)),"")) -> 46353 | H11: =IF($A11="","",IFERROR(INDEX(Raw_Price!$D$2:$D$100,MATCH($A11,Raw_Price!$A$2:$A$100,0))-TODAY(),"")) -> 73 | I11: =IF($A11="","",IFERROR(INDEX(Raw_Price!$E$2:$E$100,MATCH($A11,Raw_Price!$A$2:$A$100,0)),"")) -> 46280 | J11: =IF($A11="","",IF($B11=0,"未抓取",IF($B11<$C11,"需補歷史 ("&($C11-$B11)&" 季)",IF(TODAY()>$G11,"待更新財報","OK")))) -> OK
A12: =IF(Calc!$A$10="","",Calc!$A$10) -> DIOD | B12: =IF($A12="","",COUNTIFS(Raw_Q!$A$2:$A$600,$A12,Raw_Q!$F$2:$F$600,"N")) -> 24 | C12: =IF($A12="","",Config!$B$4) -> 24 | D12: =IF($A12="","",IFERROR(SUMIFS(Raw_Q!$E$2:$E$600,Raw_Q!$A$2:$A$600,$A12,Raw_Q!$P$2:$P$600,$B12),"")) -> 44104 | E12: =IF($A12="","",IFERROR(SUMIFS(Raw_Q!$E$2:$E$600,Raw_Q!$A$2:$A$600,$A12,Raw_Q!$P$2:$P$600,1),"")) -> 46203 | F12: =IF($A12="","",IFERROR(INDEX(Raw_Q!$B$2:$B$600,MATCH($A12&"|"&0,Raw_Q!$Q$2:$Q$600,0)),"")) -> FY2026Q3E | G12: =IF($A12="","",IFERROR(INDEX(Raw_Price!$D$2:$D$100,MATCH($A12,Raw_Price!$A$2:$A$100,0)),"")) -> 46331 | H12: =IF($A12="","",IFERROR(INDEX(Raw_Price!$D$2:$D$100,MATCH($A12,Raw_Price!$A$2:$A$100,0))-TODAY(),"")) -> 51 | I12: =IF($A12="","",IFERROR(INDEX(Raw_Price!$E$2:$E$100,MATCH($A12,Raw_Price!$A$2:$A$100,0)),"")) -> 46280 | J12: =IF($A12="","",IF($B12=0,"未抓取",IF($B12<$C12,"需補歷史 ("&($C12-$B12)&" 季)",IF(TODAY()>$G12,"待更新財報","OK")))) -> OK
A13: =IF(Calc!$A$11="","",Calc!$A$11) -> CRWD | B13: =IF($A13="","",COUNTIFS(Raw_Q!$A$2:$A$600,$A13,Raw_Q!$F$2:$F$600,"N")) -> 24 | C13: =IF($A13="","",Config!$B$4) -> 24 | D13: =IF($A13="","",IFERROR(SUMIFS(Raw_Q!$E$2:$E$600,Raw_Q!$A$2:$A$600,$A13,Raw_Q!$P$2:$P$600,$B13),"")) -> 44135 | E13: =IF($A13="","",IFERROR(SUMIFS(Raw_Q!$E$2:$E$600,Raw_Q!$A$2:$A$600,$A13,Raw_Q!$P$2:$P$600,1),"")) -> 46234 | F13: =IF($A13="","",IFERROR(INDEX(Raw_Q!$B$2:$B$600,MATCH($A13&"|"&0,Raw_Q!$Q$2:$Q$600,0)),"")) -> FY2027Q3E | G13: =IF($A13="","",IFERROR(INDEX(Raw_Price!$D$2:$D$100,MATCH($A13,Raw_Price!$A$2:$A$100,0)),"")) -> 46357 | H13: =IF($A13="","",IFERROR(INDEX(Raw_Price!$D$2:$D$100,MATCH($A13,Raw_Price!$A$2:$A$100,0))-TODAY(),"")) -> 77 | I13: =IF($A13="","",IFERROR(INDEX(Raw_Price!$E$2:$E$100,MATCH($A13,Raw_Price!$A$2:$A$100,0)),"")) -> 46280 | J13: =IF($A13="","",IF($B13=0,"未抓取",IF($B13<$C13,"需補歷史 ("&($C13-$B13)&" 季)",IF(TODAY()>$G13,"待更新財報","OK")))) -> OK
A14: =IF(Calc!$A$12="","",Calc!$A$12) -> NET | B14: =IF($A14="","",COUNTIFS(Raw_Q!$A$2:$A$600,$A14,Raw_Q!$F$2:$F$600,"N")) -> 24 | C14: =IF($A14="","",Config!$B$4) -> 24 | D14: =IF($A14="","",IFERROR(SUMIFS(Raw_Q!$E$2:$E$600,Raw_Q!$A$2:$A$600,$A14,Raw_Q!$P$2:$P$600,$B14),"")) -> 44104 | E14: =IF($A14="","",IFERROR(SUMIFS(Raw_Q!$E$2:$E$600,Raw_Q!$A$2:$A$600,$A14,Raw_Q!$P$2:$P$600,1),"")) -> 46203 | F14: =IF($A14="","",IFERROR(INDEX(Raw_Q!$B$2:$B$600,MATCH($A14&"|"&0,Raw_Q!$Q$2:$Q$600,0)),"")) -> FY2026Q3E | G14: =IF($A14="","",IFERROR(INDEX(Raw_Price!$D$2:$D$100,MATCH($A14,Raw_Price!$A$2:$A$100,0)),"")) -> 46324 | H14: =IF($A14="","",IFERROR(INDEX(Raw_Price!$D$2:$D$100,MATCH($A14,Raw_Price!$A$2:$A$100,0))-TODAY(),"")) -> 44 | I14: =IF($A14="","",IFERROR(INDEX(Raw_Price!$E$2:$E$100,MATCH($A14,Raw_Price!$A$2:$A$100,0)),"")) -> 46280 | J14: =IF($A14="","",IF($B14=0,"未抓取",IF($B14<$C14,"需補歷史 ("&($C14-$B14)&" 季)",IF(TODAY()>$G14,"待更新財報","OK")))) -> OK
A15: =IF(Calc!$A$13="","",Calc!$A$13) -> CEG | B15: =IF($A15="","",COUNTIFS(Raw_Q!$A$2:$A$600,$A15,Raw_Q!$F$2:$F$600,"N")) -> 24 | C15: =IF($A15="","",Config!$B$4) -> 24 | D15: =IF($A15="","",IFERROR(SUMIFS(Raw_Q!$E$2:$E$600,Raw_Q!$A$2:$A$600,$A15,Raw_Q!$P$2:$P$600,$B15),"")) -> 44104 | E15: =IF($A15="","",IFERROR(SUMIFS(Raw_Q!$E$2:$E$600,Raw_Q!$A$2:$A$600,$A15,Raw_Q!$P$2:$P$600,1),"")) -> 46203 | F15: =IF($A15="","",IFERROR(INDEX(Raw_Q!$B$2:$B$600,MATCH($A15&"|"&0,Raw_Q!$Q$2:$Q$600,0)),"")) -> FY2026Q3E | G15: =IF($A15="","",IFERROR(INDEX(Raw_Price!$D$2:$D$100,MATCH($A15,Raw_Price!$A$2:$A$100,0)),"")) -> 46335 | H15: =IF($A15="","",IFERROR(INDEX(Raw_Price!$D$2:$D$100,MATCH($A15,Raw_Price!$A$2:$A$100,0))-TODAY(),"")) -> 55 | I15: =IF($A15="","",IFERROR(INDEX(Raw_Price!$E$2:$E$100,MATCH($A15,Raw_Price!$A$2:$A$100,0)),"")) -> 46280 | J15: =IF($A15="","",IF($B15=0,"未抓取",IF($B15<$C15,"需補歷史 ("&($C15-$B15)&" 季)",IF(TODAY()>$G15,"待更新財報","OK")))) -> OK
A16: =IF(Calc!$A$14="","",Calc!$A$14) -> AMZN | B16: =IF($A16="","",COUNTIFS(Raw_Q!$A$2:$A$600,$A16,Raw_Q!$F$2:$F$600,"N")) -> 24 | C16: =IF($A16="","",Config!$B$4) -> 24 | D16: =IF($A16="","",IFERROR(SUMIFS(Raw_Q!$E$2:$E$600,Raw_Q!$A$2:$A$600,$A16,Raw_Q!$P$2:$P$600,$B16),"")) -> 44104 | E16: =IF($A16="","",IFERROR(SUMIFS(Raw_Q!$E$2:$E$600,Raw_Q!$A$2:$A$600,$A16,Raw_Q!$P$2:$P$600,1),"")) -> 46203 | F16: =IF($A16="","",IFERROR(INDEX(Raw_Q!$B$2:$B$600,MATCH($A16&"|"&0,Raw_Q!$Q$2:$Q$600,0)),"")) -> FY2026Q3E | G16: =IF($A16="","",IFERROR(INDEX(Raw_Price!$D$2:$D$100,MATCH($A16,Raw_Price!$A$2:$A$100,0)),"")) -> 46324 | H16: =IF($A16="","",IFERROR(INDEX(Raw_Price!$D$2:$D$100,MATCH($A16,Raw_Price!$A$2:$A$100,0))-TODAY(),"")) -> 44 | I16: =IF($A16="","",IFERROR(INDEX(Raw_Price!$E$2:$E$100,MATCH($A16,Raw_Price!$A$2:$A$100,0)),"")) -> 46280 | J16: =IF($A16="","",IF($B16=0,"未抓取",IF($B16<$C16,"需補歷史 ("&($C16-$B16)&" 季)",IF(TODAY()>$G16,"待更新財報","OK")))) -> OK
A17: =IF(Calc!$A$15="","",Calc!$A$15) -> GOOG | B17: =IF($A17="","",COUNTIFS(Raw_Q!$A$2:$A$600,$A17,Raw_Q!$F$2:$F$600,"N")) -> 24 | C17: =IF($A17="","",Config!$B$4) -> 24 | D17: =IF($A17="","",IFERROR(SUMIFS(Raw_Q!$E$2:$E$600,Raw_Q!$A$2:$A$600,$A17,Raw_Q!$P$2:$P$600,$B17),"")) -> 44104 | E17: =IF($A17="","",IFERROR(SUMIFS(Raw_Q!$E$2:$E$600,Raw_Q!$A$2:$A$600,$A17,Raw_Q!$P$2:$P$600,1),"")) -> 46203 | F17: =IF($A17="","",IFERROR(INDEX(Raw_Q!$B$2:$B$600,MATCH($A17&"|"&0,Raw_Q!$Q$2:$Q$600,0)),"")) -> FY2026Q3E | G17: =IF($A17="","",IFERROR(INDEX(Raw_Price!$D$2:$D$100,MATCH($A17,Raw_Price!$A$2:$A$100,0)),"")) -> 46323 | H17: =IF($A17="","",IFERROR(INDEX(Raw_Price!$D$2:$D$100,MATCH($A17,Raw_Price!$A$2:$A$100,0))-TODAY(),"")) -> 43 | I17: =IF($A17="","",IFERROR(INDEX(Raw_Price!$E$2:$E$100,MATCH($A17,Raw_Price!$A$2:$A$100,0)),"")) -> 46280 | J17: =IF($A17="","",IF($B17=0,"未抓取",IF($B17<$C17,"需補歷史 ("&($C17-$B17)&" 季)",IF(TODAY()>$G17,"待更新財報","OK")))) -> OK
A18: =IF(Calc!$A$16="","",Calc!$A$16) -> OKTA | B18: =IF($A18="","",COUNTIFS(Raw_Q!$A$2:$A$600,$A18,Raw_Q!$F$2:$F$600,"N")) -> 24 | C18: =IF($A18="","",Config!$B$4) -> 24 | D18: =IF($A18="","",IFERROR(SUMIFS(Raw_Q!$E$2:$E$600,Raw_Q!$A$2:$A$600,$A18,Raw_Q!$P$2:$P$600,$B18),"")) -> 44135 | E18: =IF($A18="","",IFERROR(SUMIFS(Raw_Q!$E$2:$E$600,Raw_Q!$A$2:$A$600,$A18,Raw_Q!$P$2:$P$600,1),"")) -> 46234 | F18: =IF($A18="","",IFERROR(INDEX(Raw_Q!$B$2:$B$600,MATCH($A18&"|"&0,Raw_Q!$Q$2:$Q$600,0)),"")) -> FY2027Q3E | G18: =IF($A18="","",IFERROR(INDEX(Raw_Price!$D$2:$D$100,MATCH($A18,Raw_Price!$A$2:$A$100,0)),"")) -> 46357 | H18: =IF($A18="","",IFERROR(INDEX(Raw_Price!$D$2:$D$100,MATCH($A18,Raw_Price!$A$2:$A$100,0))-TODAY(),"")) -> 77 | I18: =IF($A18="","",IFERROR(INDEX(Raw_Price!$E$2:$E$100,MATCH($A18,Raw_Price!$A$2:$A$100,0)),"")) -> 46280 | J18: =IF($A18="","",IF($B18=0,"未抓取",IF($B18<$C18,"需補歷史 ("&($C18-$B18)&" 季)",IF(TODAY()>$G18,"待更新財報","OK")))) -> OK
A19: =IF(Calc!$A$17="","",Calc!$A$17) -> PLTR | B19: =IF($A19="","",COUNTIFS(Raw_Q!$A$2:$A$600,$A19,Raw_Q!$F$2:$F$600,"N")) -> 24 | C19: =IF($A19="","",Config!$B$4) -> 24 | D19: =IF($A19="","",IFERROR(SUMIFS(Raw_Q!$E$2:$E$600,Raw_Q!$A$2:$A$600,$A19,Raw_Q!$P$2:$P$600,$B19),"")) -> 44104 | E19: =IF($A19="","",IFERROR(SUMIFS(Raw_Q!$E$2:$E$600,Raw_Q!$A$2:$A$600,$A19,Raw_Q!$P$2:$P$600,1),"")) -> 46203 | F19: =IF($A19="","",IFERROR(INDEX(Raw_Q!$B$2:$B$600,MATCH($A19&"|"&0,Raw_Q!$Q$2:$Q$600,0)),"")) -> FY2026Q3E | G19: =IF($A19="","",IFERROR(INDEX(Raw_Price!$D$2:$D$100,MATCH($A19,Raw_Price!$A$2:$A$100,0)),"")) -> 46328 | H19: =IF($A19="","",IFERROR(INDEX(Raw_Price!$D$2:$D$100,MATCH($A19,Raw_Price!$A$2:$A$100,0))-TODAY(),"")) -> 48 | I19: =IF($A19="","",IFERROR(INDEX(Raw_Price!$E$2:$E$100,MATCH($A19,Raw_Price!$A$2:$A$100,0)),"")) -> 46280 | J19: =IF($A19="","",IF($B19=0,"未抓取",IF($B19<$C19,"需補歷史 ("&($C19-$B19)&" 季)",IF(TODAY()>$G19,"待更新財報","OK")))) -> OK
A20: =IF(Calc!$A$18="","",Calc!$A$18) -> SMTC | B20: =IF($A20="","",COUNTIFS(Raw_Q!$A$2:$A$600,$A20,Raw_Q!$F$2:$F$600,"N")) -> 24 | C20: =IF($A20="","",Config!$B$4) -> 24 | D20: =IF($A20="","",IFERROR(SUMIFS(Raw_Q!$E$2:$E$600,Raw_Q!$A$2:$A$600,$A20,Raw_Q!$P$2:$P$600,$B20),"")) -> 44135 | E20: =IF($A20="","",IFERROR(SUMIFS(Raw_Q!$E$2:$E$600,Raw_Q!$A$2:$A$600,$A20,Raw_Q!$P$2:$P$600,1),"")) -> 46234 | F20: =IF($A20="","",IFERROR(INDEX(Raw_Q!$B$2:$B$600,MATCH($A20&"|"&0,Raw_Q!$Q$2:$Q$600,0)),"")) -> FY2027Q3E | G20: =IF($A20="","",IFERROR(INDEX(Raw_Price!$D$2:$D$100,MATCH($A20,Raw_Price!$A$2:$A$100,0)),"")) -> 46349 | H20: =IF($A20="","",IFERROR(INDEX(Raw_Price!$D$2:$D$100,MATCH($A20,Raw_Price!$A$2:$A$100,0))-TODAY(),"")) -> 69 | I20: =IF($A20="","",IFERROR(INDEX(Raw_Price!$E$2:$E$100,MATCH($A20,Raw_Price!$A$2:$A$100,0)),"")) -> 46280 | J20: =IF($A20="","",IF($B20=0,"未抓取",IF($B20<$C20,"需補歷史 ("&($C20-$B20)&" 季)",IF(TODAY()>$G20,"待更新財報","OK")))) -> OK
A21: =IF(Calc!$A$19="","",Calc!$A$19) -> QCOM | B21: =IF($A21="","",COUNTIFS(Raw_Q!$A$2:$A$600,$A21,Raw_Q!$F$2:$F$600,"N")) -> 24 | C21: =IF($A21="","",Config!$B$4) -> 24 | D21: =IF($A21="","",IFERROR(SUMIFS(Raw_Q!$E$2:$E$600,Raw_Q!$A$2:$A$600,$A21,Raw_Q!$P$2:$P$600,$B21),"")) -> 44104 | E21: =IF($A21="","",IFERROR(SUMIFS(Raw_Q!$E$2:$E$600,Raw_Q!$A$2:$A$600,$A21,Raw_Q!$P$2:$P$600,1),"")) -> 46203 | F21: =IF($A21="","",IFERROR(INDEX(Raw_Q!$B$2:$B$600,MATCH($A21&"|"&0,Raw_Q!$Q$2:$Q$600,0)),"")) -> FY2026Q4E | G21: =IF($A21="","",IFERROR(INDEX(Raw_Price!$D$2:$D$100,MATCH($A21,Raw_Price!$A$2:$A$100,0)),"")) -> 46324 | H21: =IF($A21="","",IFERROR(INDEX(Raw_Price!$D$2:$D$100,MATCH($A21,Raw_Price!$A$2:$A$100,0))-TODAY(),"")) -> 44 | I21: =IF($A21="","",IFERROR(INDEX(Raw_Price!$E$2:$E$100,MATCH($A21,Raw_Price!$A$2:$A$100,0)),"")) -> 46280 | J21: =IF($A21="","",IF($B21=0,"未抓取",IF($B21<$C21,"需補歷史 ("&($C21-$B21)&" 季)",IF(TODAY()>$G21,"待更新財報","OK")))) -> OK
A22: =IF(Calc!$A$20="","",Calc!$A$20) -> AVGO | B22: =IF($A22="","",COUNTIFS(Raw_Q!$A$2:$A$600,$A22,Raw_Q!$F$2:$F$600,"N")) -> 24 | C22: =IF($A22="","",Config!$B$4) -> 24 | D22: =IF($A22="","",IFERROR(SUMIFS(Raw_Q!$E$2:$E$600,Raw_Q!$A$2:$A$600,$A22,Raw_Q!$P$2:$P$600,$B22),"")) -> 44135 | E22: =IF($A22="","",IFERROR(SUMIFS(Raw_Q!$E$2:$E$600,Raw_Q!$A$2:$A$600,$A22,Raw_Q!$P$2:$P$600,1),"")) -> 46234 | F22: =IF($A22="","",IFERROR(INDEX(Raw_Q!$B$2:$B$600,MATCH($A22&"|"&0,Raw_Q!$Q$2:$Q$600,0)),"")) -> FY2026Q4E | G22: =IF($A22="","",IFERROR(INDEX(Raw_Price!$D$2:$D$100,MATCH($A22,Raw_Price!$A$2:$A$100,0)),"")) -> 46365 | H22: =IF($A22="","",IFERROR(INDEX(Raw_Price!$D$2:$D$100,MATCH($A22,Raw_Price!$A$2:$A$100,0))-TODAY(),"")) -> 85 | I22: =IF($A22="","",IFERROR(INDEX(Raw_Price!$E$2:$E$100,MATCH($A22,Raw_Price!$A$2:$A$100,0)),"")) -> 46280 | J22: =IF($A22="","",IF($B22=0,"未抓取",IF($B22<$C22,"需補歷史 ("&($C22-$B22)&" 季)",IF(TODAY()>$G22,"待更新財報","OK")))) -> OK
A23: =IF(Calc!$A$21="","",Calc!$A$21) -> FTNT | B23: =IF($A23="","",COUNTIFS(Raw_Q!$A$2:$A$600,$A23,Raw_Q!$F$2:$F$600,"N")) -> 24 | C23: =IF($A23="","",Config!$B$4) -> 24 | D23: =IF($A23="","",IFERROR(SUMIFS(Raw_Q!$E$2:$E$600,Raw_Q!$A$2:$A$600,$A23,Raw_Q!$P$2:$P$600,$B23),"")) -> 44104 | E23: =IF($A23="","",IFERROR(SUMIFS(Raw_Q!$E$2:$E$600,Raw_Q!$A$2:$A$600,$A23,Raw_Q!$P$2:$P$600,1),"")) -> 46203 | F23: =IF($A23="","",IFERROR(INDEX(Raw_Q!$B$2:$B$600,MATCH($A23&"|"&0,Raw_Q!$Q$2:$Q$600,0)),"")) -> FY2026Q3E | G23: =IF($A23="","",IFERROR(INDEX(Raw_Price!$D$2:$D$100,MATCH($A23,Raw_Price!$A$2:$A$100,0)),"")) -> 46330 | H23: =IF($A23="","",IFERROR(INDEX(Raw_Price!$D$2:$D$100,MATCH($A23,Raw_Price!$A$2:$A$100,0))-TODAY(),"")) -> 50 | I23: =IF($A23="","",IFERROR(INDEX(Raw_Price!$E$2:$E$100,MATCH($A23,Raw_Price!$A$2:$A$100,0)),"")) -> 46280 | J23: =IF($A23="","",IF($B23=0,"未抓取",IF($B23<$C23,"需補歷史 ("&($C23-$B23)&" 季)",IF(TODAY()>$G23,"待更新財報","OK")))) -> OK
A24: =IF(Calc!$A$22="","",Calc!$A$22) | B24: =IF($A24="","",COUNTIFS(Raw_Q!$A$2:$A$600,$A24,Raw_Q!$F$2:$F$600,"N")) | C24: =IF($A24="","",Config!$B$4) | D24: =IF($A24="","",IFERROR(SUMIFS(Raw_Q!$E$2:$E$600,Raw_Q!$A$2:$A$600,$A24,Raw_Q!$P$2:$P$600,$B24),"")) | E24: =IF($A24="","",IFERROR(SUMIFS(Raw_Q!$E$2:$E$600,Raw_Q!$A$2:$A$600,$A24,Raw_Q!$P$2:$P$600,1),"")) | F24: =IF($A24="","",IFERROR(INDEX(Raw_Q!$B$2:$B$600,MATCH($A24&"|"&0,Raw_Q!$Q$2:$Q$600,0)),"")) | G24: =IF($A24="","",IFERROR(INDEX(Raw_Price!$D$2:$D$100,MATCH($A24,Raw_Price!$A$2:$A$100,0)),"")) | H24: =IF($A24="","",IFERROR(INDEX(Raw_Price!$D$2:$D$100,MATCH($A24,Raw_Price!$A$2:$A$100,0))-TODAY(),"")) | I24: =IF($A24="","",IFERROR(INDEX(Raw_Price!$E$2:$E$100,MATCH($A24,Raw_Price!$A$2:$A$100,0)),"")) | J24: =IF($A24="","",IF($B24=0,"未抓取",IF($B24<$C24,"需補歷史 ("&($C24-$B24)&" 季)",IF(TODAY()>$G24,"待更新財報","OK"))))
A25: =IF(Calc!$A$23="","",Calc!$A$23) | B25: =IF($A25="","",COUNTIFS(Raw_Q!$A$2:$A$600,$A25,Raw_Q!$F$2:$F$600,"N")) | C25: =IF($A25="","",Config!$B$4) | D25: =IF($A25="","",IFERROR(SUMIFS(Raw_Q!$E$2:$E$600,Raw_Q!$A$2:$A$600,$A25,Raw_Q!$P$2:$P$600,$B25),"")) | E25: =IF($A25="","",IFERROR(SUMIFS(Raw_Q!$E$2:$E$600,Raw_Q!$A$2:$A$600,$A25,Raw_Q!$P$2:$P$600,1),"")) | F25: =IF($A25="","",IFERROR(INDEX(Raw_Q!$B$2:$B$600,MATCH($A25&"|"&0,Raw_Q!$Q$2:$Q$600,0)),"")) | G25: =IF($A25="","",IFERROR(INDEX(Raw_Price!$D$2:$D$100,MATCH($A25,Raw_Price!$A$2:$A$100,0)),"")) | H25: =IF($A25="","",IFERROR(INDEX(Raw_Price!$D$2:$D$100,MATCH($A25,Raw_Price!$A$2:$A$100,0))-TODAY(),"")) | I25: =IF($A25="","",IFERROR(INDEX(Raw_Price!$E$2:$E$100,MATCH($A25,Raw_Price!$A$2:$A$100,0)),"")) | J25: =IF($A25="","",IF($B25=0,"未抓取",IF($B25<$C25,"需補歷史 ("&($C25-$B25)&" 季)",IF(TODAY()>$G25,"待更新財報","OK"))))
A26: =IF(Calc!$A$24="","",Calc!$A$24) -> ↑ 藍字＝手動輸入。新增股票就在第 2~21 列往下打一列，其餘分頁全自動延伸。 | B26: =IF($A26="","",COUNTIFS(Raw_Q!$A$2:$A$600,$A26,Raw_Q!$F$2:$F$600,"N")) -> 0 | C26: =IF($A26="","",Config!$B$4) -> 24 | D26: =IF($A26="","",IFERROR(SUMIFS(Raw_Q!$E$2:$E$600,Raw_Q!$A$2:$A$600,$A26,Raw_Q!$P$2:$P$600,$B26),"")) -> 0 | E26: =IF($A26="","",IFERROR(SUMIFS(Raw_Q!$E$2:$E$600,Raw_Q!$A$2:$A$600,$A26,Raw_Q!$P$2:$P$600,1),"")) -> 0 | F26: =IF($A26="","",IFERROR(INDEX(Raw_Q!$B$2:$B$600,MATCH($A26&"|"&0,Raw_Q!$Q$2:$Q$600,0)),"")) | G26: =IF($A26="","",IFERROR(INDEX(Raw_Price!$D$2:$D$100,MATCH($A26,Raw_Price!$A$2:$A$100,0)),"")) | H26: =IF($A26="","",IFERROR(INDEX(Raw_Price!$D$2:$D$100,MATCH($A26,Raw_Price!$A$2:$A$100,0))-TODAY(),"")) | I26: =IF($A26="","",IFERROR(INDEX(Raw_Price!$E$2:$E$100,MATCH($A26,Raw_Price!$A$2:$A$100,0)),"")) | J26: =IF($A26="","",IF($B26=0,"未抓取",IF($B26<$C26,"需補歷史 ("&($C26-$B26)&" 季)",IF(TODAY()>$G26,"待更新財報","OK")))) -> 未抓取
A27: =IF(Calc!$A$25="","",Calc!$A$25) | B27: =IF($A27="","",COUNTIFS(Raw_Q!$A$2:$A$600,$A27,Raw_Q!$F$2:$F$600,"N")) | C27: =IF($A27="","",Config!$B$4) | D27: =IF($A27="","",IFERROR(SUMIFS(Raw_Q!$E$2:$E$600,Raw_Q!$A$2:$A$600,$A27,Raw_Q!$P$2:$P$600,$B27),"")) | E27: =IF($A27="","",IFERROR(SUMIFS(Raw_Q!$E$2:$E$600,Raw_Q!$A$2:$A$600,$A27,Raw_Q!$P$2:$P$600,1),"")) | F27: =IF($A27="","",IFERROR(INDEX(Raw_Q!$B$2:$B$600,MATCH($A27&"|"&0,Raw_Q!$Q$2:$Q$600,0)),"")) | G27: =IF($A27="","",IFERROR(INDEX(Raw_Price!$D$2:$D$100,MATCH($A27,Raw_Price!$A$2:$A$100,0)),"")) | H27: =IF($A27="","",IFERROR(INDEX(Raw_Price!$D$2:$D$100,MATCH($A27,Raw_Price!$A$2:$A$100,0))-TODAY(),"")) | I27: =IF($A27="","",IFERROR(INDEX(Raw_Price!$E$2:$E$100,MATCH($A27,Raw_Price!$A$2:$A$100,0)),"")) | J27: =IF($A27="","",IF($B27=0,"未抓取",IF($B27<$C27,"需補歷史 ("&($C27-$B27)&" 季)",IF(TODAY()>$G27,"待更新財報","OK"))))
A28: =IF(Calc!$A$26="","",Calc!$A$26) | B28: =IF($A28="","",COUNTIFS(Raw_Q!$A$2:$A$600,$A28,Raw_Q!$F$2:$F$600,"N")) | C28: =IF($A28="","",Config!$B$4) | D28: =IF($A28="","",IFERROR(SUMIFS(Raw_Q!$E$2:$E$600,Raw_Q!$A$2:$A$600,$A28,Raw_Q!$P$2:$P$600,$B28),"")) | E28: =IF($A28="","",IFERROR(SUMIFS(Raw_Q!$E$2:$E$600,Raw_Q!$A$2:$A$600,$A28,Raw_Q!$P$2:$P$600,1),"")) | F28: =IF($A28="","",IFERROR(INDEX(Raw_Q!$B$2:$B$600,MATCH($A28&"|"&0,Raw_Q!$Q$2:$Q$600,0)),"")) | G28: =IF($A28="","",IFERROR(INDEX(Raw_Price!$D$2:$D$100,MATCH($A28,Raw_Price!$A$2:$A$100,0)),"")) | H28: =IF($A28="","",IFERROR(INDEX(Raw_Price!$D$2:$D$100,MATCH($A28,Raw_Price!$A$2:$A$100,0))-TODAY(),"")) | I28: =IF($A28="","",IFERROR(INDEX(Raw_Price!$E$2:$E$100,MATCH($A28,Raw_Price!$A$2:$A$100,0)),"")) | J28: =IF($A28="","",IF($B28=0,"未抓取",IF($B28<$C28,"需補歷史 ("&($C28-$B28)&" 季)",IF(TODAY()>$G28,"待更新財報","OK"))))
A30: 狀態欄告訴資料管線該做什麼：需補歷史 → 只抓缺的那幾季；待更新財報 → 只抓最新 1~2 季；OK → 整檔跳過季度 API。這是增量更新省下絕大部分請求的關鍵。

Sheet Tickers
A1: ticker | B1: 公司名稱 | C1: 產業 | D1: 等級 | E1: 標籤 | F1: 加入日期 | G1: 備註
A2: AAPL | B2: Apple Inc. | C2: 資訊科技硬體
A3: MSFT | B3: Microsoft Corporation | C3: 軟體
A4: NVDA | B4: NVIDIA Corporation | C4: 半導體
A5: AAOI | B5: Applied Optoelectronics, Inc. | C5: 資訊科技硬體 | D5: 觀察 | E5: CPO | F5: 46263
A6: MRVL | B6: Marvell Technology, Inc. | C6: 半導體 | D6: 池子 | F6: 46264
A7: MU | B7: Micron Technology, Inc. | C7: 半導體 | D7: 池子 | F7: 46264
A8: TER | B8: Teradyne, Inc. | C8: 半導體設備 | D8: 池子 | F8: 46265
A9: DELL | B9: Dell Technologies Inc. | C9: 資訊科技硬體 | D9: 池子 | F9: 46265
A10: DIOD | B10: Diodes Incorporated | C10: 半導體 | D10: 池子 | F10: 46265
A11: CRWD | B11: CrowdStrike Holdings, Inc. | C11: 軟體 | D11: 池子 | F11: 46266
A12: NET | B12: Cloudflare, Inc. | C12: 軟體 | D12: 核心 | F12: 46267
A13: CEG | B13: Constellation Energy Corporation | C13: 公用事業 | D13: 池子 | F13: 46274
A14: AMZN | B14: Amazon.com, Inc. | C14: 電商 | D14: 池子 | F14: 46274
A15: GOOG | B15: Alphabet Inc. | C15: 網路服務 | D15: 池子 | F15: 46275
A16: OKTA | B16: Okta, Inc. | C16: 軟體 | D16: 池子 | E16: 資安 | F16: 46275
A17: PLTR | B17: Palantir Technologies Inc. | C17: 軟體 | D17: 池子 | F17: 46275
A18: SMTC | B18: Semtech Corporation | C18: 半導體 | D18: 池子 | F18: 46275
A19: QCOM | B19: QUALCOMM Incorporated | C19: 半導體 | D19: 池子 | F19: 46276
A20: AVGO | B20: Broadcom Inc. | C20: 半導體 | D20: 池子 | F20: 46279
A21: FTNT | B21: Fortinet, Inc. | C21: 軟體 | D21: 池子 | F21: 46280
A24: ↑ 藍字＝手動輸入。新增股票就在第 2~21 列往下打一列，其餘分頁全自動延伸。

Sheet Raw_Q
A1: ticker | B1: period | C1: fy | D1: fq | E1: period_end | F1: is_est | G1: est_source | H1: eps_basis | I1: revenue ($M) | J1: gross_profit ($M) | K1: eps_diluted_adj | L1: shares_diluted (M) | M1: total_equity ($M) | N1: dps (每股配息) | O1: price_at_end | P1: seq | Q1: key
A2: AAOI | B2: FY2026Q2 | C2: 2026 | D2: 2 | E2: 46203 | F2: N | G2: actual | H2: street | I2: 191.922 | J2: 53.207 | K2: 0.06 | L2: 81.568 | M2: 1668.025 | O2: 148.16 | P2: 1 | Q2: AAOI|1
A3: AAOI | B3: FY2026Q1 | C3: 2026 | D3: 1 | E3: 46112 | F3: N | G3: actual | H3: street | I3: 151.144 | J3: 43.916 | K3: -0.07 | L3: 75.98 | M3: 1105.952 | O3: 84.589996 | P3: 2 | Q3: AAOI|2
A4: AAOI | B4: FY2025Q4 | C4: 2025 | D4: 4 | E4: 46022 | F4: N | G4: actual | H4: street | I4: 134.274 | J4: 41.944 | K4: -0.01 | L4: 70.336 | M4: 733.918 | O4: 34.860001 | P4: 3 | Q4: AAOI|3
A5: AAOI | B5: FY2025Q3 | C5: 2025 | D5: 3 | E5: 45930 | F5: N | G5: actual | H5: street | I5: 118.63 | J5: 33.263 | K5: -0.09 | L5: 63.329 | M5: 559.085 | O5: 25.93 | P5: 4 | Q5: AAOI|4
A6: AAOI | B6: FY2025Q2 | C6: 2025 | D6: 2 | E6: 45838 | F6: N | G6: actual | H6: street | I6: 102.952 | J6: 31.162 | K6: -0.16 | L6: 56.772 | M6: 424.981 | O6: 25.690001 | P6: 5 | Q6: AAOI|5
A7: AAOI | B7: FY2025Q1 | C7: 2025 | D7: 1 | E7: 45747 | F7: N | G7: actual | H7: street | I7: 99.859 | J7: 30.544 | K7: -0.02 | L7: 44.458301 | M7: 309.013 | O7: 15.35 | P7: 6 | Q7: AAOI|6
A8: AAOI | B8: FY2024Q4 | C8: 2024 | D8: 4 | E8: 45657 | F8: N | G8: actual | H8: street | I8: 100.271 | J8: 28.729 | K8: -0.02 | L8: 83.077102 | M8: 229.112 | O8: 36.860001 | P8: 7 | Q8: AAOI|7
A9: AAOI | B9: FY2024Q3 | C9: 2024 | D9: 3 | E9: 45565 | F9: N | G9: actual | H9: street | I9: 65.151 | J9: 15.917 | K9: -0.21 | L9: 39.16587 | M9: 212.086 | O9: 14.31 | P9: 8 | Q9: AAOI|8
A10: AAOI | B10: FY2024Q2 | C10: 2024 | D10: 2 | E10: 45473 | F10: N | G10: actual | H10: street | I10: 43.27 | J10: 9.562 | K10: -0.28 | L10: 36.78515 | M10: 186.494 | O10: 8.29 | P10: 9 | Q10: AAOI|9
A11: AAOI | B11: FY2024Q1 | C11: 2024 | D11: 1 | E11: 45382 | F11: N | G11: actual | H11: street | I11: 40.673 | J11: 7.591 | K11: -0.31 | L11: 34.316824 | M11: 195.726 | O11: 13.86 | P11: 10 | Q11: AAOI|10
A12: AAOI | B12: FY2023Q4 | C12: 2023 | D12: 4 | E12: 45291 | F12: N | G12: actual | H12: street | I12: 60.453 | J12: 21.604 | K12: 0.04 | L12: 31.944259 | M12: 214.869 | O12: 19.32 | P12: 11 | Q12: AAOI|11
A13: AAOI | B13: FY2023Q3 | C13: 2023 | D13: 3 | E13: 45199 | F13: N | G13: actual | H13: street | I13: 62.547 | J13: 20.174 | K13: -0.05 | L13: 29.910996 | M13: 178.353 | O13: 10.97 | P13: 12 | Q13: AAOI|12
... A15: AAOI | B15: FY2023Q1 | C15: 2023 | D15: 1 | E15: 45016 | F15: N | G15: actual | H15: street | I15: 53.03 | J15: 9.244 | K15: -0.25 | L15: 28.871857 | M15: 172.637 | O15: 2.21 | P15: 14 | Q15: AAOI|14
A16: AAOI | B16: FY2022Q4 | C16: 2022 | D16: 4 | E16: 44926 | F16: N | G16: actual | H16: street | I16: 61.585 | J16: 6.226 | K16: -0.19 | M16: 184.67 | O16: 1.89 | P16: 15 | Q16: AAOI|15
A17: AAOI | B17: FY2022Q3 | C17: 2022 | D17: 3 | E17: 44834 | F17: N | G17: actual | H17: street | I17: 56.693 | J17: 9.749 | K17: -0.26 | L17: 83.517735 | M17: 198.538 | O17: 2.72 | P17: 16 | Q17: AAOI|16
A18: AAOI | B18: FY2022Q2 | C18: 2022 | D18: 2 | E18: 44742 | F18: N | G18: actual | H18: street | I18: 52.299 | J18: 8.628 | K18: -0.28 | L18: 82.836945 | M18: 219.594 | O18: 1.55 | P18: 17 | Q18: AAOI|17
A19: AAOI | B19: FY2022Q1 | C19: 2022 | D19: 1 | E19: 44651 | F19: N | G19: actual | H19: street | I19: 52.242 | J19: 9.025 | K19: -0.29 | L19: 82.389963 | M19: 239.577 | O19: 3.6500001 | P19: 18 | Q19: AAOI|18
A20: AAOI | B20: FY2021Q4 | C20: 2021 | D20: 4 | E20: 44561 | F20: N | G20: actual | H20: street | I20: 54.408 | J20: 8.095 | K20: -0.2 | M20: 254.57 | O20: 5.1399999 | P20: 19 | Q20: AAOI|19
A21: AAOI | B21: FY2021Q3 | C21: 2021 | D21: 3 | E21: 44469 | F21: N | G21: actual | H21: street | I21: 53.267 | J21: 8.124 | K21: -0.2 | L21: 81.292116 | M21: 263.968 | O21: 7.1799998 | P21: 20 | Q21: AAOI|20
A22: AAOI | B22: FY2021Q2 | C22: 2021 | D22: 2 | E22: 44377 | F22: N | G22: actual | H22: street | I22: 54.189 | J22: 10.778 | K22: -0.15 | L22: 80.550096 | M22: 277.291 | O22: 8.4700003 | P22: 21 | Q22: AAOI|21
A23: AAOI | B23: FY2021Q1 | C23: 2021 | D23: 1 | E23: 44286 | F23: N | G23: actual | H23: street | I23: 49.701 | J23: 10.719 | K23: -0.21 | L23: 79.314213 | M23: 278.472 | O23: 8.3599997 | P23: 22 | Q23: AAOI|22
A24: AAOI | B24: FY2020Q4 | C24: 2020 | D24: 4 | E24: 44196 | F24: N | G24: actual | H24: street | I24: 52.325 | J24: 11.277 | K24: -0.2 | M24: 277.891 | O24: 8.5100002 | P24: 23 | Q24: AAOI|23
A25: AAOI | B25: FY2020Q3 | C25: 2020 | D25: 3 | E25: 44104 | F25: N | G25: actual | H25: street | I25: 76.608 | J25: 19.19 | K25: -0.06 | L25: 22.744361 | M25: 265.166 | O25: 11.25 | P25: 24 | Q25: AAOI|24
A26: AAPL | B26: FY2026Q3 | C26: 2026 | D26: 3 | E26: 46203 | F26: N | G26: actual | H26: street | I26: 109417 | J26: 54770 | K26: 2.02 | L26: 14714.676 | M26: 107520 | N26: 0.27 | O26: 289.35999 | P26: 1 | Q26: AAPL|1
A27: AAPL | B27: FY2026Q2 | C27: 2026 | D27: 2 | E27: 46112 | F27: N | G27: actual | H27: street | I27: 111184 | J27: 54781 | K27: 2.01 | L27: 14725.873 | M27: 106491 | N27: 0.26 | O27: 253.78999 | P27: 2 | Q27: AAPL|2
A28: AAPL | B28: FY2026Q1 | C28: 2026 | D28: 1 | E28: 46022 | F28: N | G28: actual | H28: street | I28: 143756 | J28: 69231 | K28: 2.84 | L28: 14810.356 | M28: 88190 | N28: 0.26 | O28: 271.85999 | P28: 3 | Q28: AAPL|3
A29: AAPL | B29: FY2025Q4 | C29: 2025 | D29: 4 | E29: 45930 | F29: N | G29: actual | H29: street | I29: 102466 | J29: 48341 | K29: 1.85 | L29: 14863.609 | M29: 73733 | N29: 0.26 | O29: 254.63 | P29: 4 | Q29: AAPL|4
A30: AAPL | B30: FY2025Q3 | C30: 2025 | D30: 3 | E30: 45838 | F30: N | G30: actual | H30: street | I30: 94036 | J30: 43718 | K30: 1.57 | L30: 14948.179 | M30: 65830 | N30: 0.26 | O30: 205.17 | P30: 5 | Q30: AAPL|5
A31: AAPL | B31: FY2025Q2 | C31: 2025 | D31: 2 | E31: 45747 | F31: N | G31: actual | H31: street | I31: 95359 | J31: 44867 | K31: 1.65 | L31: 15199.507 | M31: 66796 | N31: 0.25 | O31: 222.13 | P31: 6 | Q31: AAPL|6
A32: AAPL | B32: FY2025Q1 | C32: 2025 | D32: 1 | E32: 45657 | F32: N | G32: actual | H32: street | I32: 124300 | J32: 58275 | K32: 2.4 | L32: 15301.651 | M32: 66758 | N32: 0.25 | O32: 250.42 | P32: 7 | Q32: AAPL|7
A33: AAPL | B33: FY2024Q4 | C33: 2024 | D33: 4 | E33: 45565 | F33: N | G33: actual | H33: street | I33: 94930 | J33: 43879 | K33: 0.97 | L33: 15408.095 | M33: 56950 | N33: 0.25 | O33: 233 | P33: 8 | Q33: AAPL|8
A34: AAPL | B34: FY2024Q3 | C34: 2024 | D34: 3 | E34: 45473 | F34: N | G34: actual | H34: street | I34: 85777 | J34: 39678 | K34: 1.4 | L34: 15515.481 | M34: 66708 | N34: 0.25 | O34: 210.62 | P34: 9 | Q34: AAPL|9
A35: AAPL | B35: FY2024Q2 | C35: 2024 | D35: 2 | E35: 45382 | F35: N | G35: actual | H35: street | I35: 90753 | J35: 42271 | K35: 1.53 | L35: 15622.192 | M35: 74194 | N35: 0.24 | O35: 171.48 | P35: 10 | Q35: AAPL|10
A36: AAPL | B36: FY2024Q1 | C36: 2024 | D36: 1 | E36: 45291 | F36: N | G36: actual | H36: street | I36: 119575 | J36: 54855 | K36: 2.18 | L36: 15717.778 | M36: 74100 | N36: 0.24 | O36: 192.53 | P36: 11 | Q36: AAPL|11
A37: AAPL | B37: FY2023Q4 | C37: 2023 | D37: 4 | E37: 45199 | F37: N | G37: actual | H37: street | I37: 89498 | J37: 40427 | K37: 1.46 | L37: 15812.547 | M37: 62146 | N37: 0.24 | O37: 171.21001 | P37: 12 | Q37: AAPL|12
... A40: AAPL | B40: FY2023Q1 | C40: 2023 | D40: 1 | E40: 44926 | F40: N | G40: actual | H40: street | I40: 117154 | J40: 50332 | K40: 1.88 | L40: 15955.718 | M40: 56727 | N40: 0.23 | O40: 129.92999 | P40: 15 | Q40: AAPL|15
A41: AAPL | B41: FY2022Q4 | C41: 2022 | D41: 4 | E41: 44834 | F41: N | G41: actual | H41: street | I41: 90146 | J41: 38095 | K41: 1.29 | M41: 50672 | N41: 0.23 | O41: 138.2 | P41: 16 | Q41: AAPL|16
A42: AAPL | B42: FY2022Q3 | C42: 2022 | D42: 3 | E42: 44742 | F42: N | G42: actual | H42: street | I42: 82959 | J42: 35885 | K42: 1.2 | L42: 16262.203 | M42: 58107 | N42: 0.23 | O42: 136.72 | P42: 17 | Q42: AAPL|17
A43: AAPL | B43: FY2022Q2 | C43: 2022 | D43: 2 | E43: 44651 | F43: N | G43: actual | H43: street | I43: 97278 | J43: 42559 | K43: 1.52 | L43: 16403.316 | M43: 67399 | N43: 0.22 | O43: 174.61 | P43: 18 | Q43: AAPL|18
A44: AAPL | B44: FY2022Q1 | C44: 2022 | D44: 1 | E44: 44561 | F44: N | G44: actual | H44: street | I44: 123945 | J44: 54243 | K44: 2.1 | L44: 16519.291 | M44: 71932 | N44: 0.22 | O44: 177.57001 | P44: 19 | Q44: AAPL|19
A45: AAPL | B45: FY2021Q4 | C45: 2021 | D45: 4 | E45: 44469 | F45: N | G45: actual | H45: street | I45: 83360 | J45: 35174 | K45: 1.24 | M45: 63090 | N45: 0.22 | O45: 141.5 | P45: 20 | Q45: AAPL|20
A46: AAPL | B46: FY2021Q3 | C46: 2021 | D46: 3 | E46: 44377 | F46: N | G46: actual | H46: street | I46: 81434 | J46: 35255 | K46: 1.3 | L46: 16781.735 | M46: 64280 | N46: 0.22 | O46: 136.96001 | P46: 21 | Q46: AAPL|21
A47: AAPL | B47: FY2021Q2 | C47: 2021 | D47: 2 | E47: 44286 | F47: N | G47: actual | H47: street | I47: 89584 | J47: 38079 | K47: 1.4 | L47: 16929.157 | M47: 69178 | N47: 0.205 | O47: 122.15 | P47: 22 | Q47: AAPL|22
A48: AAPL | B48: FY2021Q1 | C48: 2021 | D48: 1 | E48: 44196 | F48: N | G48: actual | H48: street | I48: 111439 | J48: 44328 | K48: 1.68 | L48: 17113.688 | M48: 66224 | N48: 0.205 | O48: 132.69 | P48: 23 | Q48: AAPL|23
A49: AAPL | B49: FY2020Q4 | C49: 2020 | D49: 4 | E49: 44104 | F49: N | G49: actual | H49: street | I49: 64698 | J49: 24689 | K49: 0.73 | M49: 65339 | O49: 115.81 | P49: 24 | Q49: AAPL|24
A50: AMZN | B50: FY2026Q2 | C50: 2026 | D50: 2 | E50: 46203 | F50: N | G50: actual | H50: street | I50: 775680 | J50: 393810 | K50: 5.75 | L50: 10903 | M50: 551620 | O50: 238.34 | P50: 1 | Q50: AMZN|1
A51: AMZN | B51: FY2026Q1 | C51: 2026 | D51: 1 | E51: 46112 | F51: N | G51: actual | H51: street | I51: 181519 | J51: 94056 | K51: 2.78 | L51: 10874 | M51: 441914 | O51: 208.27 | P51: 2 | Q51: AMZN|2
A52: AMZN | B52: FY2025Q4 | C52: 2025 | D52: 4 | E52: 46022 | F52: N | G52: actual | H52: street | I52: 213386 | J52: 103427 | K52: 1.95 | L52: 10863 | M52: 411065 | O52: 230.82001 | P52: 3 | Q52: AMZN|3
A53: AMZN | B53: FY2025Q3 | C53: 2025 | D53: 3 | E53: 45930 | F53: N | G53: actual | H53: street | I53: 180169 | J53: 91499 | K53: 1.95 | L53: 10845 | M53: 369631 | O53: 219.57001 | P53: 4 | Q53: AMZN|4
A54: AMZN | B54: FY2025Q2 | C54: 2025 | D54: 2 | E54: 45838 | F54: N | G54: actual | H54: street | I54: 167702 | J54: 86893 | K54: 1.68 | L54: 10806 | M54: 333775 | O54: 219.39 | P54: 5 | Q54: AMZN|5
A55: AMZN | B55: FY2025Q1 | C55: 2025 | D55: 1 | E55: 45747 | F55: N | G55: actual | H55: street | I55: 155667 | J55: 78691 | K55: 1.59 | L55: 10751.75 | M55: 305867 | O55: 190.25999 | P55: 6 | Q55: AMZN|6
A56: AMZN | B56: FY2024Q4 | C56: 2024 | D56: 4 | E56: 45657 | F56: N | G56: actual | H56: street | I56: 187792 | J56: 88899 | K56: 1.86 | L56: 10721 | M56: 285970 | O56: 219.39 | P56: 7 | Q56: AMZN|7
A57: AMZN | B57: FY2024Q3 | C57: 2024 | D57: 3 | E57: 45565 | F57: N | G57: actual | H57: street | I57: 158877 | J57: 77900 | K57: 1.43 | L57: 10681.75 | M57: 259151 | O57: 186.33 | P57: 8 | Q57: AMZN|8
A58: AMZN | B58: FY2024Q2 | C58: 2024 | D58: 2 | E58: 45473 | F58: N | G58: actual | H58: street | I58: 147977 | J58: 74192 | K58: 1.26 | L58: 10637.5 | M58: 236447 | O58: 193.25 | P58: 9 | Q58: AMZN|9
A59: AMZN | B59: FY2024Q1 | C59: 2024 | D59: 1 | E59: 45382 | F59: N | G59: actual | H59: street | I59: 143313 | J59: 70680 | K59: 0.98 | L59: 10572.75 | M59: 216661 | O59: 180.38 | P59: 10 | Q59: AMZN|10
A60: AMZN | B60: FY2023Q4 | C60: 2023 | D60: 4 | E60: 45291 | F60: N | G60: actual | H60: street | I60: 169961 | J60: 77408 | K60: 1 | L60: 10492 | M60: 201875 | O60: 151.94 | P60: 11 | Q60: AMZN|11
A61: AMZN | B61: FY2023Q3 | C61: 2023 | D61: 3 | E61: 45199 | F61: N | G61: actual | H61: street | I61: 143083 | J61: 68061 | K61: 0.94 | L61: 10394.5 | M61: 182973 | O61: 127.12 | P61: 12 | Q61: AMZN|12
... A63: AMZN | B63: FY2023Q1 | C63: 2023 | D63: 1 | E63: 45016 | F63: N | G63: actual | H63: street | I63: 127358 | J63: 59567 | K63: 0.31 | L63: 10347 | M63: 154526 | O63: 103.29 | P63: 14 | Q63: AMZN|14
A64: AMZN | B64: FY2022Q4 | C64: 2022 | D64: 4 | E64: 44926 | F64: N | G64: actual | H64: street | I64: 149204 | J64: 63564 | K64: 0.03 | M64: 146043 | O64: 84 | P64: 15 | Q64: AMZN|15
A65: AMZN | B65: FY2022Q3 | C65: 2022 | D65: 3 | E65: 44834 | F65: N | G65: actual | H65: street | I65: 127101 | J65: 56833 | K65: 0.28 | L65: 10331 | M65: 137489 | O65: 113 | P65: 16 | Q65: AMZN|16
A66: AMZN | B66: FY2022Q2 | C66: 2022 | D66: 2 | E66: 44742 | F66: N | G66: actual | H66: street | I66: 121234 | J66: 54810 | K66: -0.2 | L66: 10175 | M66: 131402 | O66: 106.21 | P66: 17 | Q66: AMZN|17
A67: AMZN | B67: FY2022Q1 | C67: 2022 | D67: 1 | E67: 44651 | F67: N | G67: actual | H67: street | I67: 116444 | J67: 49945 | K67: -0.38 | L67: 10171 | M67: 134001 | O67: 162.9975 | P67: 18 | Q67: AMZN|18
A68: AMZN | B68: FY2021Q4 | C68: 2021 | D68: 4 | E68: 44561 | F68: N | G68: actual | H68: street | I68: 137412 | J68: 54577 | K68: 1.39 | M68: 138245 | O68: 166.717 | P68: 19 | Q68: AMZN|19
A69: AMZN | B69: FY2021Q3 | C69: 2021 | D69: 3 | E69: 44469 | F69: N | G69: actual | H69: street | I69: 110812 | J69: 47882 | K69: 0.31 | L69: 10309 | M69: 120564 | O69: 164.252 | P69: 20 | Q69: AMZN|20
A70: AMZN | B70: FY2021Q2 | C70: 2021 | D70: 2 | E70: 44377 | F70: N | G70: actual | H70: street | I70: 113080 | J70: 48904 | K70: 0.76 | L70: 10286 | M70: 114803 | O70: 172.008 | P70: 21 | Q70: AMZN|21
A71: AMZN | B71: FY2021Q1 | C71: 2021 | D71: 1 | E71: 44286 | F71: N | G71: actual | H71: street | I71: 108518 | J71: 46115 | K71: 0.79 | L71: 513 | M71: 103320 | O71: 154.70399 | P71: 22 | Q71: AMZN|22
A72: AMZN | B72: FY2020Q4 | C72: 2020 | D72: 4 | E72: 44196 | F72: N | G72: actual | H72: street | I72: 125555 | J72: 46271 | K72: 0.7 | L72: 513 | M72: 93404 | O72: 162.8465 | P72: 23 | Q72: AMZN|23
A73: AMZN | B73: FY2020Q3 | C73: 2020 | D73: 3 | E73: 44104 | F73: N | G73: actual | H73: street | I73: 96145 | J73: 39039 | K73: 0.62 | L73: 512 | M73: 82775 | O73: 157.43649 | P73: 24 | Q73: AMZN|24
A74: AVGO | B74: FY2026Q3 | C74: 2026 | D74: 3 | E74: 46234 | F74: N | G74: actual | H74: street | I74: 29591 | J74: 20456 | L74: 4887 | M74: 99690 | N74: 0.65 | O74: 389.28 | P74: 1 | Q74: AVGO|1
A75: AVGO | B75: FY2026Q2 | C75: 2026 | D75: 2 | E75: 46142 | F75: N | G75: actual | H75: street | I75: 22187 | J75: 15415 | K75: 2.44 | L75: 4876 | M75: 87691 | N75: 0.65 | O75: 417.42999 | P75: 2 | Q75: AVGO|2
A76: AVGO | B76: FY2026Q1 | C76: 2026 | D76: 1 | E76: 46053 | F76: N | G76: actual | H76: street | I76: 19311 | J76: 13157 | K76: 2.05 | L76: 4888 | M76: 79872 | N76: 0.65 | O76: 331.29999 | P76: 3 | Q76: AVGO|3
A77: AVGO | B77: FY2025Q4 | C77: 2025 | D77: 4 | E77: 45961 | F77: N | G77: actual | H77: street | I77: 18015 | J77: 12249 | K77: 1.95 | L77: 4889 | M77: 81292 | N77: 0.59 | O77: 369.63 | P77: 4 | Q77: AVGO|4
A78: AVGO | B78: FY2025Q3 | C78: 2025 | D78: 3 | E78: 45869 | F78: N | G78: actual | H78: street | I78: 15952 | J78: 10703 | K78: 1.69 | L78: 4860 | M78: 73277 | N78: 0.59 | O78: 293.70001 | P78: 5 | Q78: AVGO|5
A79: AVGO | B79: FY2025Q2 | C79: 2025 | D79: 2 | E79: 45777 | F79: N | G79: actual | H79: street | I79: 15004 | J79: 10197 | K79: 1.58 | L79: 4828.5 | M79: 69586 | N79: 0.59 | O79: 192.47 | P79: 6 | Q79: AVGO|6
A80: AVGO | B80: FY2025Q1 | C80: 2025 | D80: 1 | E80: 45688 | F80: N | G80: actual | H80: street | I80: 14916 | J80: 10145 | K80: 1.6 | L80: 4820.5 | M80: 69789 | N80: 0.59 | O80: 221.27 | P80: 7 | Q80: AVGO|7
A81: AVGO | B81: FY2024Q4 | C81: 2024 | D81: 4 | E81: 45596 | F81: N | G81: actual | H81: street | I81: 14054 | J81: 9002 | K81: 1.42 | M81: 67678 | N81: 0.53 | O81: 169.77 | P81: 8 | Q81: AVGO|8
A82: AVGO | B82: FY2024Q3 | C82: 2024 | D82: 3 | E82: 45504 | F82: N | G82: actual | H82: street | I82: 13072 | J82: 8356 | K82: 1.24 | L82: 4636 | M82: 65651 | N82: 0.525 | O82: 160.67999 | P82: 9 | Q82: AVGO|9
A83: AVGO | B83: FY2024Q2 | C83: 2024 | D83: 2 | E83: 45412 | F83: N | G83: actual | H83: street | I83: 12487 | J83: 7776 | K83: 1.1 | L83: 4495 | M83: 69961 | N83: 0.525 | O83: 130.02699 | P83: 10 | Q83: AVGO|10
A84: AVGO | B84: FY2024Q1 | C84: 2024 | D84: 1 | E84: 45322 | F84: N | G84: actual | H84: street | I84: 11961 | J84: 7375 | K84: 1.1 | L84: 436.5 | M84: 70284 | N84: 0.525 | O84: 118 | P84: 11 | Q84: AVGO|11
A85: AVGO | B85: FY2023Q4 | C85: 2023 | D85: 4 | E85: 45230 | F85: N | G85: actual | H85: street | I85: 9295 | J85: 6407 | K85: 1.11 | L85: 427 | M85: 23988 | N85: 0.46 | O85: 84.137001 | P85: 12 | Q85: AVGO|12
A86: AVGO | B86: FY2023Q3 | C86: 2023 | D86: 3 | E86: 45138 | F86: N | G86: actual | H86: street | I86: 8876 | J86: 6164 | K86: 1.05 | L86: 4269 | M86: 22079 | N86: 0.46 | O86: 89.864998 | P86: 13 | Q86: AVGO|13
A87: AVGO | B87: FY2023Q2 | C87: 2023 | D87: 2 | E87: 45046 | F87: N | G87: actual | H87: street | I87: 8733 | J87: 6115 | K87: 1.03 | L87: 427 | M87: 22007 | N87: 0.46 | O87: 62.650002 | P87: 14 | Q87: AVGO|14
A88: AVGO | B88: FY2023Q1 | C88: 2023 | D88: 1 | E88: 44957 | F88: N | G88: actual | H88: street | I88: 8915 | J88: 6004 | K88: 1.03 | L88: 429 | M88: 23310 | N88: 0.46 | O88: 58.500999 | P88: 15 | Q88: AVGO|15
A89: AVGO | B89: FY2022Q4 | C89: 2022 | D89: 4 | E89: 44865 | F89: N | G89: actual | H89: street | I89: 8930 | J89: 5926 | K89: 1.05 | M89: 22709 | N89: 0.41 | O89: 47.012001 | P89: 16 | Q89: AVGO|16
A90: AVGO | B90: FY2022Q3 | C90: 2022 | D90: 3 | E90: 44773 | F90: N | G90: actual | H90: street | I90: 8464 | J90: 5681 | K90: 0.97 | L90: 430 | M90: 20903 | N90: 0.41 | O90: 53.548 | P90: 17 | Q90: AVGO|17
A91: AVGO | B91: FY2022Q2 | C91: 2022 | D91: 2 | E91: 44681 | F91: N | G91: actual | H91: street | I91: 8103 | J91: 5439 | K91: 0.91 | L91: 424 | M91: 20990 | N91: 0.41 | O91: 55.438999 | P91: 18 | Q91: AVGO|18
A92: AVGO | B92: FY2022Q1 | C92: 2022 | D92: 1 | E92: 44592 | F92: N | G92: actual | H92: street | I92: 7706 | J92: 5049 | K92: 0.84 | L92: 429 | M92: 22994 | N92: 0.41 | O92: 58.588001 | P92: 19 | Q92: AVGO|19
A93: AVGO | B93: FY2021Q4 | C93: 2021 | D93: 4 | E93: 44500 | F93: N | G93: actual | H93: street | I93: 7407 | J93: 4638 | K93: 0.78 | M93: 24989 | N93: 0.36 | O93: 53.167 | P93: 20 | Q93: AVGO|20
A94: AVGO | B94: FY2021Q3 | C94: 2021 | D94: 3 | E94: 44408 | F94: N | G94: actual | H94: street | I94: 6778 | J94: 4197 | K94: 0.7 | L94: 429 | M94: 24367 | N94: 0.36 | O94: 48.540001 | P94: 21 | Q94: AVGO|21
A95: AVGO | B95: FY2021Q2 | C95: 2021 | D95: 2 | E95: 44316 | F95: N | G95: actual | H95: street | I95: 6610 | J95: 4057 | K95: 0.66 | L95: 429 | M95: 23966 | N95: 0.36 | O95: 45.619999 | P95: 22 | Q95: AVGO|22
A96: AVGO | B96: FY2021Q1 | C96: 2021 | D96: 1 | E96: 44227 | F96: N | G96: actual | H96: street | I96: 6655 | J96: 3952 | K96: 0.66 | L96: 428 | M96: 23999 | N96: 0.36 | O96: 45.049999 | P96: 23 | Q96: AVGO|23
A97: AVGO | B97: FY2020Q4 | C97: 2020 | D97: 4 | E97: 44135 | F97: N | G97: actual | H97: street | I97: 6467 | J97: 3747 | K97: 0.64 | M97: 23901 | O97: 34.963001 | P97: 24 | Q97: AVGO|24
A98: CEG | B98: FY2026Q2 | C98: 2026 | D98: 2 | E98: 46203 | F98: N | G98: actual | H98: street | I98: 7504 | J98: 1228 | K98: 2.55 | L98: 360 | M98: 31977 | N98: 0.427 | O98: 248.37 | P98: 1 | Q98: CEG|1
A99: CEG | B99: FY2026Q1 | C99: 2026 | D99: 1 | E99: 46112 | F99: N | G99: actual | H99: street | I99: 11122 | J99: 2990 | K99: 2.74 | L99: 354 | M99: 33483 | N99: 0.427 | O99: 279.25 | P99: 2 | Q99: CEG|2
A100: CEG | B100: FY2025Q4 | C100: 2025 | D100: 4 | E100: 46022 | F100: N | G100: actual | H100: street | I100: 6074 | J100: 990 | K100: 2.3 | L100: 313 | M100: 14517 | N100: 0.388 | O100: 353.26999 | P100: 3 | Q100: CEG|3
A101: CEG | B101: FY2025Q3 | C101: 2025 | D101: 3 | E101: 45930 | F101: N | G101: actual | H101: street | I101: 6570 | J101: 1492 | K101: 3.04 | L101: 313 | M101: 14350 | N101: 0.388 | O101: 329.07001 | P101: 4 | Q101: CEG|4
A102: CEG | B102: FY2025Q2 | C102: 2025 | D102: 2 | E102: 45838 | F102: N | G102: actual | H102: street | I102: 6101 | J102: 1352 | K102: 1.91 | L102: 314 | M102: 13446 | N102: 0.388 | O102: 322.76001 | P102: 5 | Q102: CEG|5
A103: CEG | B103: FY2025Q1 | C103: 2025 | D103: 1 | E103: 45747 | F103: N | G103: actual | H103: street | I103: 6788 | J103: 859 | K103: 2.14 | L103: 314 | M103: 12956 | N103: 0.388 | O103: 201.63 | P103: 6 | Q103: CEG|6
A104: CEG | B104: FY2024Q4 | C104: 2024 | D104: 4 | E104: 45657 | F104: N | G104: actual | H104: street | I104: 5382 | J104: 1286 | K104: 2.44 | L104: 315 | M104: 13166 | N104: 0.353 | O104: 223.71001 | P104: 7 | Q104: CEG|7
...

Sheet Raw_Est
A1: ticker | B1: eps_f1 | C1: eps_f2 | D1: fy1_end | E1: n_analysts | F1: as_of
A2: AAOI | B2: 0.68 | C2: 4.602 | D2: 46387 | E2: 6 | F2: 46280
A3: AAPL | B3: 8.81483 | C3: 9.57579 | D3: 46295 | E3: 27 | F3: 46280
A4: AMZN | B4: 12.89405 | C4: 10.49168 | D4: 46387 | E4: 44 | F4: 46280
A5: AVGO | B5: 11.65766 | C5: 19.38391 | D5: 46326 | E5: 39 | F5: 46280
A6: CEG | B6: 12.11777 | C6: 13.34165 | D6: 46387 | E6: 10 | F6: 46280
A7: CRWD | B7: 1.25609 | C7: 1.60591 | D7: 46418 | E7: 45 | F7: 46280
A8: DELL | B8: 25.88376 | C8: 24.66365 | D8: 46418 | E8: 23 | F8: 46280
A9: DIOD | B9: 3.225 | C9: 5.85 | D9: 46387 | E9: 2 | F9: 46280
A10: FTNT | B10: 3.45008 | C10: 3.77777 | D10: 46387 | E10: 38 | F10: 46280
A11: GOOG | B11: 20.60438 | C11: 14.85683 | D11: 46387 | E11: 39 | F11: 46280
A12: MRVL | B12: 4.21276 | C12: 6.7608 | D12: 46418 | E12: 33 | F12: 46280
A13: MSFT | B13: 19.75972 | C13: 23.59268 | D13: 46568 | E13: 25 | F13: 46280
... A21: TER | B21: 9.09129 | C21: 11.65247 | D21: 46387 | E21: 15 | F21: 46280
A23: eps_f1＝本財年共識、eps_f2＝下一財年共識，皆為 Adjusted 口徑（與 EPS_TTM 同口徑）。

Sheet Raw_Price
A1: ticker | B1: price | C1: price_date | D1: next_earnings | E1: as_of
A2: AAOI | B2: 96.349998 | C2: 46280 | D2: 46331 | E2: 46280
A3: AAPL | B3: 329.35999 | C3: 46280 | D3: 46324 | E3: 46280
A4: AMZN | B4: 248.92999 | C4: 46280 | D4: 46324 | E4: 46280
A5: AVGO | B5: 341.70001 | C5: 46280 | D5: 46365 | E5: 46280
A6: CEG | B6: 261.25 | C6: 46280 | D6: 46335 | E6: 46280
A7: CRWD | B7: 238.23 | C7: 46280 | D7: 46357 | E7: 46280
A8: DELL | B8: 555.69012 | C8: 46280 | D8: 46353 | E8: 46280
A9: DIOD | B9: 87.529999 | C9: 46280 | D9: 46331 | E9: 46280
A10: FTNT | B10: 170.17999 | C10: 46280 | D10: 46330 | E10: 46280
A11: GOOG | B11: 340.73999 | C11: 46280 | D11: 46323 | E11: 46280
A12: MRVL | B12: 224.32001 | C12: 46280 | D12: 46357 | E12: 46280
A13: MSFT | B13: 500.84 | C13: 46280 | D13: 46323 | E13: 46280
... A21: TER | B21: 328.125 | C21: 46280 | D21: 46316 | E21: 46280

Sheet Calc
A1: ticker | B1: 公司 | C1: 等級 | D1: 股價 | E1: Rev_TTM($M) | F1: EPS_TTM(Adj) | G1: EPS_TTM_fwd | H1: EPS_NTM | I1: EPS_TTM_YoY | J1: PE_TTM | K1: PE_TTM_fwd | L1: PE_NTM | M1: EPS成長_F | N1: PEG_T | O1: PEG_F | P1: DPS_TTM | Q1: 殖利率 | R1: 配息YoY | S1: 營收YoY_最新季 | T1: 營收QoQ_最新季 | U1: 營收QoQ_上一季 | V1: 營收加速度(pp) | W1: 動能判讀 | X1: 同期加速度(pp) | Y1: EPS_YoY_最新季 | Z1: 毛利率_TTM | AA1: 毛利率_5年平均 | AB1: GM vs 5年平均(bps) | AC1: ΔGM_YoY(bps) | AD1: 每股淨值 | AE1: 淨利_TTM($M) | AF1: ROE_TTM | AG1: ROE_5年平均 | AH1: ROE_Forward | AI1: 當季EPS預估 | AJ1: 預估期別 | AK1: 預估來源 | AL1: 分析師家數 | AM1: 下次財報日 | AN1: 資料日期 | AO1: ROE錨點_seq1 | AP1: ROE錨點_seq5 | AQ1: ROE錨點_seq9 | AR1: ROE錨點_seq13 | AS1: ROE錨點_seq17
A2: =IF(Tickers!A2="","",Tickers!A2) -> AAPL | B2: =IF($A2="","",IFERROR(INDEX(Tickers!$B$2:$B$100,MATCH($A2,Tickers!$A$2:$A$100,0)),"")) -> Apple Inc. | C2: =IF($A2="","",IFERROR(INDEX(Tickers!$D$2:$D$100,MATCH($A2,Tickers!$A$2:$A$100,0)),"")) -> 0 | D2: =IF($A2="","",IFERROR(INDEX(Raw_Price!$B$2:$B$100,MATCH($A2,Raw_Price!$A$2:$A$100,0)),"")) -> 329.35999 | E2: =IF($A2="","",IFERROR(SUMIFS(Raw_Q!$I$2:$I$600,Raw_Q!$A$2:$A$600,$A2,Raw_Q!$P$2:$P$600,">=1",Raw_Q!$P$2:$P$600,"<=4"),"")) -> 466823 | F2: =IF($A2="","",IFERROR(SUMIFS(Raw_Q!$K$2:$K$600,Raw_Q!$A$2:$A$600,$A2,Raw_Q!$P$2:$P$600,">=1",Raw_Q!$P$2:$P$600,"<=4"),"")) -> 8.72 | G2: =IF($A2="","",IFERROR(SUMIFS(Raw_Q!$K$2:$K$600,Raw_Q!$A$2:$A$600,$A2,Raw_Q!$P$2:$P$600,">=0",Raw_Q!$P$2:$P$600,"<=3"),"")) -> 8.84656 | H2: =IF($A2="","",IFERROR(INDEX(Raw_Est!$B$2:$B$100,MATCH($A2,Raw_Est!$A$2:$A$100,0))*MIN(1,MAX(0,(INDEX(Raw_Est!$D$2:$D$100,MATCH($A2,Raw_Est!$A$2:$A$100,0))-TODAY())/Config!$B$8))+INDEX(Raw_Est!$C$2:$C$100,MATCH($A2,Raw_Est!$A$2:$A$100,0))*(1-MIN(1,MAX(0,(INDEX(Raw_Est!$D$2:$D$100,MATCH($A2,Raw_Est!$A$2:$A$100,0))-TODAY())/Config!$B$8))),"")) -> 9.5445177 | I2: =IF($A2="","",IFERROR(SUMIFS(Raw_Q!$K$2:$K$600,Raw_Q!$A$2:$A$600,$A2,Raw_Q!$P$2:$P$600,">=1",Raw_Q!$P$2:$P$600,"<=4")/SUMIFS(Raw_Q!$K$2:$K$600,Raw_Q!$A$2:$A$600,$A2,Raw_Q!$P$2:$P$600,">=5",Raw_Q!$P$2:$P$600,"<=8")-1,"")) -> 0.323217 | J2: =IF($A2="","",IFERROR(IF(F2<=0,"N/M",D2/F2),"N/M")) -> 37.770641 | K2: =IF($A2="","",IFERROR(IF(G2<=0,"N/M",D2/G2),"N/M")) -> 37.230289 | L2: =IF($A2="","",IFERROR(IF(H2<=0,"N/M",D2/H2),"N/M")) -> 34.507766 | M2: =IF($A2="","",IFERROR(INDEX(Raw_Est!$C$2:$C$100,MATCH($A2,Raw_Est!$A$2:$A$100,0))/INDEX(Raw_Est!$B$2:$B$100,MATCH($A2,Raw_Est!$A$2:$A$100,0))-1,"")) -> 0.086327246 | N2: =IF($A2="","",IFERROR(IF(OR(NOT(ISNUMBER(J2)),I2<Config!$B$6),"N/M",J2/(I2*100)),"N/M")) -> 1.1685846 | O2: =IF($A2="","",IFERROR(IF(OR(NOT(ISNUMBER(L2)),M2<Config!$B$6),"N/M",L2/(M2*100)),"N/M")) -> 3.9973204 | P2: =IF($A2="","",IFERROR(SUMIFS(Raw_Q!$N$2:$N$600,Raw_Q!$A$2:$A$600,$A2,Raw_Q!$P$2:$P$600,">=1",Raw_Q!$P$2:$P$600,"<=4"),"")) -> 1.05 | Q2: =IF($A2="","",IFERROR(IF(P2=0,"不配息",P2/D2),"")) -> 0.0031880011 | R2: =IF($A2="","",IFERROR(IF(SUMIFS(Raw_Q!$N$2:$N$600,Raw_Q!$A$2:$A$600,$A2,Raw_Q!$P$2:$P$600,">=5",Raw_Q!$P$2:$P$600,"<=8")=0,"",SUMIFS(Raw_Q!$N$2:$N$600,Raw_Q!$A$2:$A$600,$A2,Raw_Q!$P$2:$P$600,">=1",Raw_Q!$P$2:$P$600,"<=4")/SUMIFS(Raw_Q!$N$2:$N$600,Raw_Q!$A$2:$A$600,$A2,Raw_Q!$P$2:$P$600,">=5",Raw_Q!$P$2:$P$600,"<=8")-1),"")) -> 0.03960396 | S2: =IF($A2="","",IFERROR(SUMIFS(Raw_Q!$I$2:$I$600,Raw_Q!$A$2:$A$600,$A2,Raw_Q!$P$2:$P$600,1)/SUMIFS(Raw_Q!$I$2:$I$600,Raw_Q!$A$2:$A$600,$A2,Raw_Q!$P$2:$P$600,5)-1,"")) -> 0.16356502 | T2: =IF($A2="","",IFERROR(SUMIFS(Raw_Q!$I$2:$I$600,Raw_Q!$A$2:$A$600,$A2,Raw_Q!$P$2:$P$600,1)/SUMIFS(Raw_Q!$I$2:$I$600,Raw_Q!$A$2:$A$600,$A2,Raw_Q!$P$2:$P$600,2)-1,"")) -> -0.015892574 | U2: =IF($A2="","",IFERROR(SUMIFS(Raw_Q!$I$2:$I$600,Raw_Q!$A$2:$A$600,$A2,Raw_Q!$P$2:$P$600,2)/SUMIFS(Raw_Q!$I$2:$I$600,Raw_Q!$A$2:$A$600,$A2,Raw_Q!$P$2:$P$600,3)-1,"")) -> -0.22657837 | V2: =IF($A2="","",IFERROR((T2-U2)*100,"")) -> 21.068579 | W2: =IF($A2="","",IFERROR(IF(NOT(ISNUMBER(T2)),"",IF(T2>0,IF(V2>0,"成長且加速","成長但減速"),IF(V2>0,"衰退但收斂","衰退且惡化"))),"")) -> 衰退但收斂 | X2: =IF($A2="","",IFERROR((T2-(SUMIFS(Raw_Q!$I$2:$I$600,Raw_Q!$A$2:$A$600,$A2,Raw_Q!$P$2:$P$600,5)/SUMIFS(Raw_Q!$I$2:$I$600,Raw_Q!$A$2:$A$600,$A2,Raw_Q!$P$2:$P$600,6)-1))*100,"")) -> -0.20186874 | Y2: =IF($A2="","",IFERROR(SUMIFS(Raw_Q!$K$2:$K$600,Raw_Q!$A$2:$A$600,$A2,Raw_Q!$P$2:$P$600,1)/SUMIFS(Raw_Q!$K$2:$K$600,Raw_Q!$A$2:$A$600,$A2,Raw_Q!$P$2:$P$600,5)-1,"")) -> 0.2866242 | Z2: =IF($A2="","",IFERROR(SUMIFS(Raw_Q!$J$2:$J$600,Raw_Q!$A$2:$A$600,$A2,Raw_Q!$P$2:$P$600,">=1",Raw_Q!$P$2:$P$600,"<=4")/E2,"")) -> 0.48652916 | AA2: =IF($A2="","",IFERROR(SUMIFS(Raw_Q!$J$2:$J$600,Raw_Q!$A$2:$A$600,$A2,Raw_Q!$P$2:$P$600,">=1",Raw_Q!$P$2:$P$600,"<="&Config!$B$5)/SUMIFS(Raw_Q!$I$2:$I$600,Raw_Q!$A$2:$A$600,$A2,Raw_Q!$P$2:$P$600,">=1",Raw_Q!$P$2:$P$600,"<="&Config!$B$5),"")) -> 0.45744556 | AB2: =IF($A2="","",IFERROR((Z2-AA2)*10000,"")) -> 290.83593 | AC2: =IF($A2="","",IFERROR((SUMIFS(Raw_Q!$J$2:$J$600,Raw_Q!$A$2:$A$600,$A2,Raw_Q!$P$2:$P$600,1)/SUMIFS(Raw_Q!$I$2:$I$600,Raw_Q!$A$2:$A$600,$A2,Raw_Q!$P$2:$P$600,1)-SUMIFS(Raw_Q!$J$2:$J$600,Raw_Q!$A$2:$A$600,$A2,Raw_Q!$P$2:$P$600,5)/SUMIFS(Raw_Q!$I$2:$I$600,Raw_Q!$A$2:$A$600,$A2,Raw_Q!$P$2:$P$600,5))*10000,"")) -> 356.55013 | AD2: =IF($A2="","",IFERROR(SUMIFS(Raw_Q!$M$2:$M$600,Raw_Q!$A$2:$A$600,$A2,Raw_Q!$P$2:$P$600,1)/SUMIFS(Raw_Q!$L$2:$L$600,Raw_Q!$A$2:$A$600,$A2,Raw_Q!$P$2:$P$600,1),"")) -> 7.3069907 | AE2: =IF($A2="","",IFERROR(SUMPRODUCT((Raw_Q!$A$2:$A$600=$A2)*(Raw_Q!$P$2:$P$600>=1)*(Raw_Q!$P$2:$P$600<=4)*Raw_Q!$K$2:$K$600*Raw_Q!$L$2:$L$600),"")) -> 128881.74 | AF2: =IF($A2="","",IFERROR(IF(MIN(SUMIFS(Raw_Q!$M$2:$M$600,Raw_Q!$A$2:$A$600,$A2,Raw_Q!$P$2:$P$600,1),SUMIFS(Raw_Q!$M$2:$M$600,Raw_Q!$A$2:$A$600,$A2,Raw_Q!$P$2:$P$600,5))<=0,"N/M",AE2/((SUMIFS(Raw_Q!$M$2:$M$600,Raw_Q!$A$2:$A$600,$A2,Raw_Q!$P$2:$P$600,1)+SUMIFS(Raw_Q!$M$2:$M$600,Raw_Q!$A$2:$A$600,$A2,Raw_Q!$P$2:$P$600,5))/2)),"N/M")) -> 1.486954 | AG2: =IF($A2="","",IFERROR(AVERAGE(AO2:AS2),"")) -> 1.4327803 | AH2: =IF($A2="","",IFERROR(IF(AD2<=0,"N/M",INDEX(Raw_Est!$B$2:$B$100,MATCH($A2,Raw_Est!$A$2:$A$100,0))/AD2),"N/M")) -> 1.2063557 | AI2: =IF($A2="","",IFERROR(SUMIFS(Raw_Q!$K$2:$K$600,Raw_Q!$A$2:$A$600,$A2,Raw_Q!$P$2:$P$600,0),"")) -> 1.97656 | AJ2: =IF($A2="","",IFERROR(INDEX(Raw_Q!$B$2:$B$600,MATCH($A2&"|"&0,Raw_Q!$Q$2:$Q$600,0)),"")) -> FY2026Q4E | AK2: =IF($A2="","",IFERROR(INDEX(Raw_Q!$G$2:$G$600,MATCH($A2&"|"&0,Raw_Q!$Q$2:$Q$600,0)),"")) -> consensus | AL2: =IF($A2="","",IFERROR(INDEX(Raw_Est!$E$2:$E$100,MATCH($A2,Raw_Est!$A$2:$A$100,0)),"")) -> 27 | AM2: =IF($A2="","",IFERROR(INDEX(Raw_Price!$D$2:$D$100,MATCH($A2,Raw_Price!$A$2:$A$100,0)),"")) -> 46324 | AN2: =IF($A2="","",IFERROR(INDEX(Raw_Price!$E$2:$E$100,MATCH($A2,Raw_Price!$A$2:$A$100,0)),"")) -> 46280 | AO2: =IF($A2="","",IFERROR(IF(MIN(SUMIFS(Raw_Q!$M$2:$M$600,Raw_Q!$A$2:$A$600,$A2,Raw_Q!$P$2:$P$600,1),SUMIFS(Raw_Q!$M$2:$M$600,Raw_Q!$A$2:$A$600,$A2,Raw_Q!$P$2:$P$600,5))<=0,"",SUMPRODUCT((Raw_Q!$A$2:$A$600=$A2)*(Raw_Q!$P$2:$P$600>=1)*(Raw_Q!$P$2:$P$600<=4)*Raw_Q!$K$2:$K$600*Raw_Q!$L$2:$L$600)/((SUMIFS(Raw_Q!$M$2:$M$600,Raw_Q!$A$2:$A$600,$A2,Raw_Q!$P$2:$P$600,1)+SUMIFS(Raw_Q!$M$2:$M$600,Raw_Q!$A$2:$A$600,$A2,Raw_Q!$P$2:$P$600,5))/2)),"")) -> 1.486954 | AP2: =IF($A2="","",IFERROR(IF(MIN(SUMIFS(Raw_Q!$M$2:$M$600,Raw_Q!$A$2:$A$600,$A2,Raw_Q!$P$2:$P$600,5),SUMIFS(Raw_Q!$M$2:$M$600,Raw_Q!$A$2:$A$600,$A2,Raw_Q!$P$2:$P$600,9))<=0,"",SUMPRODUCT((Raw_Q!$A$2:$A$600=$A2)*(Raw_Q!$P$2:$P$600>=5)*(Raw_Q!$P$2:$P$600<=8)*Raw_Q!$K$2:$K$600*Raw_Q!$L$2:$L$600)/((SUMIFS(Raw_Q!$M$2:$M$600,Raw_Q!$A$2:$A$600,$A2,Raw_Q!$P$2:$P$600,5)+SUMIFS(Raw_Q!$M$2:$M$600,Raw_Q!$A$2:$A$600,$A2,Raw_Q!$P$2:$P$600,9))/2)),"")) -> 1.5122854 | AQ2: =IF($A2="","",IFERROR(IF(MIN(SUMIFS(Raw_Q!$M$2:$M$600,Raw_Q!$A$2:$A$600,$A2,Raw_Q!$P$2:$P$600,9),SUMIFS(Raw_Q!$M$2:$M$600,Raw_Q!$A$2:$A$600,$A2,Raw_Q!$P$2:$P$600,13))<=0,"",SUMPRODUCT((Raw_Q!$A$2:$A$600=$A2)*(Raw_Q!$P$2:$P$600>=9)*(Raw_Q!$P$2:$P$600<=12)*Raw_Q!$K$2:$K$600*Raw_Q!$L$2:$L$600)/((SUMIFS(Raw_Q!$M$2:$M$600,Raw_Q!$A$2:$A$600,$A2,Raw_Q!$P$2:$P$600,9)+SUMIFS(Raw_Q!$M$2:$M$600,Raw_Q!$A$2:$A$600,$A2,Raw_Q!$P$2:$P$600,13))/2)),"")) -> 1.6218787 | AR2: =IF($A2="","",IFERROR(IF(MIN(SUMIFS(Raw_Q!$M$2:$M$600,Raw_Q!$A$2:$A$600,$A2,Raw_Q!$P$2:$P$600,13),SUMIFS(Raw_Q!$M$2:$M$600,Raw_Q!$A$2:$A$600,$A2,Raw_Q!$P$2:$P$600,17))<=0,"",SUMPRODUCT((Raw_Q!$A$2:$A$600=$A2)*(Raw_Q!$P$2:$P$600>=13)*(Raw_Q!$P$2:$P$600<=16)*Raw_Q!$K$2:$K$600*Raw_Q!$L$2:$L$600)/((SUMIFS(Raw_Q!$M$2:$M$600,Raw_Q!$A$2:$A$600,$A2,Raw_Q!$P$2:$P$600,13)+SUMIFS(Raw_Q!$M$2:$M$600,Raw_Q!$A$2:$A$600,$A2,Raw_Q!$P$2:$P$600,17))/2)),"")) -> 1.2495382 | AS2: =IF($A2="","",IFERROR(IF(MIN(SUMIFS(Raw_Q!$M$2:$M$600,Raw_Q!$A$2:$A$600,$A2,Raw_Q!$P$2:$P$600,17),SUMIFS(Raw_Q!$M$2:$M$600,Raw_Q!$A$2:$A$600,$A2,Raw_Q!$P$2:$P$600,21))<=0,"",SUMPRODUCT((Raw_Q!$A$2:$A$600=$A2)*(Raw_Q!$P$2:$P$600>=17)*(Raw_Q!$P$2:$P$600<=20)*Raw_Q!$K$2:$K$600*Raw_Q!$L$2:$L$600)/((SUMIFS(Raw_Q!$M$2:$M$600,Raw_Q!$A$2:$A$600,$A2,Raw_Q!$P$2:$P$600,17)+SUMIFS(Raw_Q!$M$2:$M$600,Raw_Q!$A$2:$A$600,$A2,Raw_Q!$P$2:$P$600,21))/2)),"")) -> 1.2932451
A3: =IF(Tickers!A3="","",Tickers!A3) -> MSFT | B3: =IF($A3="","",IFERROR(INDEX(Tickers!$B$2:$B$100,MATCH($A3,Tickers!$A$2:$A$100,0)),"")) -> Microsoft Corporation | C3: =IF($A3="","",IFERROR(INDEX(Tickers!$D$2:$D$100,MATCH($A3,Tickers!$A$2:$A$100,0)),"")) -> 0 | D3: =IF($A3="","",IFERROR(INDEX(Raw_Price!$B$2:$B$100,MATCH($A3,Raw_Price!$A$2:$A$100,0)),"")) -> 500.84 | E3: =IF($A3="","",IFERROR(SUMIFS(Raw_Q!$I$2:$I$600,Raw_Q!$A$2:$A$600,$A3,Raw_Q!$P$2:$P$600,">=1",Raw_Q!$P$2:$P$600,"<=4"),"")) -> 331839 | F3: =IF($A3="","",IFERROR(SUMIFS(Raw_Q!$K$2:$K$600,Raw_Q!$A$2:$A$600,$A3,Raw_Q!$P$2:$P$600,">=1",Raw_Q!$P$2:$P$600,"<=4"),"")) -> 17.28 | G3: =IF($A3="","",IFERROR(SUMIFS(Raw_Q!$K$2:$K$600,Raw_Q!$A$2:$A$600,$A3,Raw_Q!$P$2:$P$600,">=0",Raw_Q!$P$2:$P$600,"<=3"),"")) -> 17.87092 | H3: =IF($A3="","",IFERROR(INDEX(Raw_Est!$B$2:$B$100,MATCH($A3,Raw_Est!$A$2:$A$100,0))*MIN(1,MAX(0,(INDEX(Raw_Est!$D$2:$D$100,MATCH($A3,Raw_Est!$A$2:$A$100,0))-TODAY())/Config!$B$8))+INDEX(Raw_Est!$C$2:$C$100,MATCH($A3,Raw_Est!$A$2:$A$100,0))*(1-MIN(1,MAX(0,(INDEX(Raw_Est!$D$2:$D$100,MATCH($A3,Raw_Est!$A$2:$A$100,0))-TODAY())/Config!$B$8))),"")) -> 20.568317 | I3: =IF($A3="","",IFERROR(SUMIFS(Raw_Q!$K$2:$K$600,Raw_Q!$A$2:$A$600,$A3,Raw_Q!$P$2:$P$600,">=1",Raw_Q!$P$2:$P$600,"<=4")/SUMIFS(Raw_Q!$K$2:$K$600,Raw_Q!$A$2:$A$600,$A3,Raw_Q!$P$2:$P$600,">=5",Raw_Q!$P$2:$P$600,"<=8")-1,"")) -> 0.26686217 | J3: =IF($A3="","",IFERROR(IF(F3<=0,"N/M",D3/F3),"N/M")) -> 28.983796 | K3: =IF($A3="","",IFERROR(IF(G3<=0,"N/M",D3/G3),"N/M")) -> 28.025418 | L3: =IF($A3="","",IFERROR(IF(H3<=0,"N/M",D3/H3),"N/M")) -> 24.350072 | M3: =IF($A3="","",IFERROR(INDEX(Raw_Est!$C$2:$C$100,MATCH($A3,Raw_Est!$A$2:$A$100,0))/INDEX(Raw_Est!$B$2:$B$100,MATCH($A3,Raw_Est!$A$2:$A$100,0))-1,"")) -> 0.19397846 | N3: =IF($A3="","",IFERROR(IF(OR(NOT(ISNUMBER(J3)),I3<Config!$B$6),"N/M",J3/(I3*100)),"N/M")) -> 1.0860961 | O3: =IF($A3="","",IFERROR(IF(OR(NOT(ISNUMBER(L3)),M3<Config!$B$6),"N/M",L3/(M3*100)),"N/M")) -> 1.2552977 | P3: =IF($A3="","",IFERROR(SUMIFS(Raw_Q!$N$2:$N$600,Raw_Q!$A$2:$A$600,$A3,Raw_Q!$P$2:$P$600,">=1",Raw_Q!$P$2:$P$600,"<=4"),"")) -> 3.56 | Q3: =IF($A3="","",IFERROR(IF(P3=0,"不配息",P3/D3),"")) -> 0.0071080585 | R3: =IF($A3="","",IFERROR(IF(SUMIFS(Raw_Q!$N$2:$N$600,Raw_Q!$A$2:$A$600,$A3,Raw_Q!$P$2:$P$600,">=5",Raw_Q!$P$2:$P$600,"<=8")=0,"",SUMIFS(Raw_Q!$N$2:$N$600,Raw_Q!$A$2:$A$600,$A3,Raw_Q!$P$2:$P$600,">=1",Raw_Q!$P$2:$P$600,"<=4")/SUMIFS(Raw_Q!$N$2:$N$600,Raw_Q!$A$2:$A$600,$A3,Raw_Q!$P$2:$P$600,">=5",Raw_Q!$P$2:$P$600,"<=8")-1),"")) -> 0.098765432 | S3: =IF($A3="","",IFERROR(SUMIFS(Raw_Q!$I$2:$I$600,Raw_Q!$A$2:$A$600,$A3,Raw_Q!$P$2:$P$600,1)/SUMIFS(Raw_Q!$I$2:$I$600,Raw_Q!$A$2:$A$600,$A3,Raw_Q!$P$2:$P$600,5)-1,"")) -> 0.17747021 | T3: =IF($A3="","",IFERROR(SUMIFS(Raw_Q!$I$2:$I$600,Raw_Q!$A$2:$A$600,$A3,Raw_Q!$P$2:$P$600,1)/SUMIFS(Raw_Q!$I$2:$I$600,Raw_Q!$A$2:$A$600,$A3,Raw_Q!$P$2:$P$600,2)-1,"")) -> 0.085913182 | U3: =IF($A3="","",IFERROR(SUMIFS(Raw_Q!$I$2:$I$600,Raw_Q!$A$2:$A$600,$A3,Raw_Q!$P$2:$P$600,2)/SUMIFS(Raw_Q!$I$2:$I$600,Raw_Q!$A$2:$A$600,$A3,Raw_Q!$P$2:$P$600,3)-1,"")) -> 0.01984669 | V3: =IF($A3="","",IFERROR((T3-U3)*100,"")) -> 6.6066492 | W3: =IF($A3="","",IFERROR(IF(NOT(ISNUMBER(T3)),"",IF(T3>0,IF(V3>0,"成長且加速","成長但減速"),IF(V3>0,"衰退但收斂","衰退且惡化"))),"")) -> 成長且加速 | X3: =IF($A3="","",IFERROR((T3-(SUMIFS(Raw_Q!$I$2:$I$600,Raw_Q!$A$2:$A$600,$A3,Raw_Q!$P$2:$P$600,5)/SUMIFS(Raw_Q!$I$2:$I$600,Raw_Q!$A$2:$A$600,$A3,Raw_Q!$P$2:$P$600,6)-1))*100,"")) -> -0.50724601 | Y3: =IF($A3="","",IFERROR(SUMIFS(Raw_Q!$K$2:$K$600,Raw_Q!$A$2:$A$600,$A3,Raw_Q!$P$2:$P$600,1)/SUMIFS(Raw_Q!$K$2:$K$600,Raw_Q!$A$2:$A$600,$A3,Raw_Q!$P$2:$P$600,5)-1,"")) -> 0.29863014 | Z3: =IF($A3="","",IFERROR(SUMIFS(Raw_Q!$J$2:$J$600,Raw_Q!$A$2:$A$600,$A3,Raw_Q!$P$2:$P$600,">=1",Raw_Q!$P$2:$P$600,"<=4")/E3,"")) -> 0.67944093 | AA3: =IF($A3="","",IFERROR(SUMIFS(Raw_Q!$J$2:$J$600,Raw_Q!$A$2:$A$600,$A3,Raw_Q!$P$2:$P$600,">=1",Raw_Q!$P$2:$P$600,"<="&Config!$B$5)/SUMIFS(Raw_Q!$I$2:$I$600,Raw_Q!$A$2:$A$600,$A3,Raw_Q!$P$2:$P$600,">=1",Raw_Q!$P$2:$P$600,"<="&Config!$B$5),"")) -> 0.68725559 | AB3: =IF($A3="","",IFERROR((Z3-AA3)*10000,"")) -> -78.146559 | AC3: =IF($A3="","",IFERROR((SUMIFS(Raw_Q!$J$2:$J$600,Raw_Q!$A$2:$A$600,$A3,Raw_Q!$P$2:$P$600,1)/SUMIFS(Raw_Q!$I$2:$I$600,Raw_Q!$A$2:$A$600,$A3,Raw_Q!$P$2:$P$600,1)-SUMIFS(Raw_Q!$J$2:$J$600,Raw_Q!$A$2:$A$600,$A3,Raw_Q!$P$2:$P$600,5)/SUMIFS(Raw_Q!$I$2:$I$600,Raw_Q!$A$2:$A$600,$A3,Raw_Q!$P$2:$P$600,5))*10000,"")) -> -138.79259 | AD3: =IF($A3="","",IFERROR(SUMIFS(Raw_Q!$M$2:$M$600,Raw_Q!$A$2:$A$600,$A3,Raw_Q!$P$2:$P$600,1)/SUMIFS(Raw_Q!$L$2:$L$600,Raw_Q!$A$2:$A$600,$A3,Raw_Q!$P$2:$P$600,1),"")) -> 59.436652 | AE3: =IF($A3="","",IFERROR(SUMPRODUCT((Raw_Q!$A$2:$A$600=$A3)*(Raw_Q!$P$2:$P$600>=1)*(Raw_Q!$P$2:$P$600<=4)*Raw_Q!$K$2:$K$600*Raw_Q!$L$2:$L$600),"")) -> 128788.95 | AF3: =IF($A3="","",IFERROR(IF(MIN(SUMIFS(Raw_Q!$M$2:$M$600,Raw_Q!$A$2:$A$600,$A3,Raw_Q!$P$2:$P$600,1),SUMIFS(Raw_Q!$M$2:$M$600,Raw_Q!$A$2:$A$600,$A3,Raw_Q!$P$2:$P$600,5))<=0,"N/M",AE3/((SUMIFS(Raw_Q!$M$2:$M$600,Raw_Q!$A$2:$A$600,$A3,Raw_Q!$P$2:$P$600,1)+SUMIFS(Raw_Q!$M$2:$M$600,Raw_Q!$A$2:$A$600,$A3,Raw_Q!$P$2:$P$600,5))/2)),"N/M")) -> 0.32776313 | AG3: =IF($A3="","",IFERROR(AVERAGE(AO3:AS3),"")) -> 0.31321768 | AH3: =IF($A3="","",IFERROR(IF(AD3<=0,"N/M",INDEX(Raw_Est!$B$2:$B$100,MATCH($A3,Raw_Est!$A$2:$A$100,0))/AD3),"N/M")) -> 0.33245009 | AI3: =IF($A3="","",IFERROR(SUMIFS(Raw_Q!$K$2:$K$600,Raw_Q!$A$2:$A$600,$A3,Raw_Q!$P$2:$P$600,0),"")) -> 4.72092 | AJ3: =IF($A3="","",IFERROR(INDEX(Raw_Q!$B$2:$B$600,MATCH($A3&"|"&0,Raw_Q!$Q$2:$Q$600,0)),"")) -> FY2027Q1E | AK3: =IF($A3="","",IFERROR(INDEX(Raw_Q!$G$2:$G$600,MATCH($A3&"|"&0,Raw_Q!$Q$2:$Q$600,0)),"")) -> consensus | AL3: =IF($A3="","",IFERROR(INDEX(Raw_Est!$E$2:$E$100,MATCH($A3,Raw_Est!$A$2:$A$100,0)),"")) -> 25 | AM3: =IF($A3="","",IFERROR(INDEX(Raw_Price!$D$2:$D$100,MATCH($A3,Raw_Price!$A$2:$A$100,0)),"")) -> 46323 | AN3: =IF($A3="","",IFERROR(INDEX(Raw_Price!$E$2:$E$100,MATCH($A3,Raw_Price!$A$2:$A$100,0)),"")) -> 46280 | AO3: =IF($A3="","",IFERROR(IF(MIN(SUMIFS(Raw_Q!$M$2:$M$600,Raw_Q!$A$2:$A$600,$A3,Raw_Q!$P$2:$P$600,1),SUMIFS(Raw_Q!$M$2:$M$600,Raw_Q!$A$2:$A$600,$A3,Raw_Q!$P$2:$P$600,5))<=0,"",SUMPRODUCT((Raw_Q!$A$2:$A$600=$A3)*(Raw_Q!$P$2:$P$600>=1)*(Raw_Q!$P$2:$P$600<=4)*Raw_Q!$K$2:$K$600*Raw_Q!$L$2:$L$600)/((SUMIFS(Raw_Q!$M$2:$M$600,Raw_Q!$A$2:$A$600,$A3,Raw_Q!$P$2:$P$600,1)+SUMIFS(Raw_Q!$M$2:$M$600,Raw_Q!$A$2:$A$600,$A3,Raw_Q!$P$2:$P$600,5))/2)),"")) -> 0.32776313 | AP3: =IF($A3="","",IFERROR(IF(MIN(SUMIFS(Raw_Q!$M$2:$M$600,Raw_Q!$A$2:$A$600,$A3,Raw_Q!$P$2:$P$600,5),SUMIFS(Raw_Q!$M$2:$M$600,Raw_Q!$A$2:$A$600,$A3,Raw_Q!$P$2:$P$600,9))<=0,"",SUMPRODUCT((Raw_Q!$A$2:$A$600=$A3)*(Raw_Q!$P$2:$P$600>=5)*(Raw_Q!$P$2:$P$600<=8)*Raw_Q!$K$2:$K$600*Raw_Q!$L$2:$L$600)/((SUMIFS(Raw_Q!$M$2:$M$600,Raw_Q!$A$2:$A$600,$A3,Raw_Q!$P$2:$P$600,5)+SUMIFS(Raw_Q!$M$2:$M$600,Raw_Q!$A$2:$A$600,$A3,Raw_Q!$P$2:$P$600,9))/2)),"")) -> 0.3328946 | AQ3: =IF($A3="","",IFERROR(IF(MIN(SUMIFS(Raw_Q!$M$2:$M$600,Raw_Q!$A$2:$A$600,$A3,Raw_Q!$P$2:$P$600,9),SUMIFS(Raw_Q!$M$2:$M$600,Raw_Q!$A$2:$A$600,$A3,Raw_Q!$P$2:$P$600,13))<=0,"",SUMPRODUCT((Raw_Q!$A$2:$A$600=$A3)*(Raw_Q!$P$2:$P$600>=9)*(Raw_Q!$P$2:$P$600<=12)*Raw_Q!$K$2:$K$600*Raw_Q!$L$2:$L$600)/((SUMIFS(Raw_Q!$M$2:$M$600,Raw_Q!$A$2:$A$600,$A3,Raw_Q!$P$2:$P$600,9)+SUMIFS(Raw_Q!$M$2:$M$600,Raw_Q!$A$2:$A$600,$A3,Raw_Q!$P$2:$P$600,13))/2)),"")) -> 0.27869721 | AR3: =IF($A3="","",IFERROR(IF(MIN(SUMIFS(Raw_Q!$M$2:$M$600,Raw_Q!$A$2:$A$600,$A3,Raw_Q!$P$2:$P$600,13),SUMIFS(Raw_Q!$M$2:$M$600,Raw_Q!$A$2:$A$600,$A3,Raw_Q!$P$2:$P$600,17))<=0,"",SUMPRODUCT((Raw_Q!$A$2:$A$600=$A3)*(Raw_Q!$P$2:$P$600>=13)*(Raw_Q!$P$2:$P$600<=16)*Raw_Q!$K$2:$K$600*Raw_Q!$L$2:$L$600)/((SUMIFS(Raw_Q!$M$2:$M$600,Raw_Q!$A$2:$A$600,$A3,Raw_Q!$P$2:$P$600,13)+SUMIFS(Raw_Q!$M$2:$M$600,Raw_Q!$A$2:$A$600,$A3,Raw_Q!$P$2:$P$600,17))/2)),"")) -> 0.28550915 | AS3: =IF($A3="","",IFERROR(IF(MIN(SUMIFS(Raw_Q!$M$2:$M$600,Raw_Q!$A$2:$A$600,$A3,Raw_Q!$P$2:$P$600,17),SUMIFS(Raw_Q!$M$2:$M$600,Raw_Q!$A$2:$A$600,$A3,Raw_Q!$P$2:$P$600,21))<=0,"",SUMPRODUCT((Raw_Q!$A$2:$A$600=$A3)*(Raw_Q!$P$2:$P$600>=17)*(Raw_Q!$P$2:$P$600<=20)*Raw_Q!$K$2:$K$600*Raw_Q!$L$2:$L$600)/((SUMIFS(Raw_Q!$M$2:$M$600,Raw_Q!$A$2:$A$600,$A3,Raw_Q!$P$2:$P$600,17)+SUMIFS(Raw_Q!$M$2:$M$600,Raw_Q!$A$2:$A$600,$A3,Raw_Q!$P$2:$P$600,21))/2)),"")) -> 0.34122432
A4: =IF(Tickers!A4="","",Tickers!A4) -> NVDA | B4: =IF($A4="","",IFERROR(INDEX(Tickers!$B$2:$B$100,MATCH($A4,Tickers!$A$2:$A$100,0)),"")) -> NVIDIA Corporation | C4: =IF($A4="","",IFERROR(INDEX(Tickers!$D$2:$D$100,MATCH($A4,Tickers!$A$2:$A$100,0)),"")) -> 0 | D4: =IF($A4="","",IFERROR(INDEX(Raw_Price!$B$2:$B$100,MATCH($A4,Raw_Price!$A$2:$A$100,0)),"")) -> 212.27 | E4: =IF($A4="","",IFERROR(SUMIFS(Raw_Q!$I$2:$I$600,Raw_Q!$A$2:$A$600,$A4,Raw_Q!$P$2:$P$600,">=1",Raw_Q!$P$2:$P$600,"<=4"),"")) -> 509718 | F4: =IF($A4="","",IFERROR(SUMIFS(Raw_Q!$K$2:$K$600,Raw_Q!$A$2:$A$600,$A4,Raw_Q!$P$2:$P$600,">=1",Raw_Q!$P$2:$P$600,"<=4"),"")) -> 7.01 | G4: =IF($A4="","",IFERROR(SUMIFS(Raw_Q!$K$2:$K$600,Raw_Q!$A$2:$A$600,$A4,Raw_Q!$P$2:$P$600,">=0",Raw_Q!$P$2:$P$600,"<=3"),"")) -> 8.05 | H4: =IF($A4="","",IFERROR(INDEX(Raw_Est!$B$2:$B$100,MATCH($A4,Raw_Est!$A$2:$A$100,0))*MIN(1,MAX(0,(INDEX(Raw_Est!$D$2:$D$100,MATCH($A4,Raw_Est!$A$2:$A$100,0))-TODAY())/Config!$B$8))+INDEX(Raw_Est!$C$2:$C$100,MATCH($A4,Raw_Est!$A$2:$A$100,0))*(1-MIN(1,MAX(0,(INDEX(Raw_Est!$D$2:$D$100,MATCH($A4,Raw_Est!$A$2:$A$100,0))-TODAY())/Config!$B$8))),"")) -> 13.22994 | I4: =IF($A4="","",IFERROR(SUMIFS(Raw_Q!$K$2:$K$600,Raw_Q!$A$2:$A$600,$A4,Raw_Q!$P$2:$P$600,">=1",Raw_Q!$P$2:$P$600,"<=4")/SUMIFS(Raw_Q!$K$2:$K$600,Raw_Q!$A$2:$A$600,$A4,Raw_Q!$P$2:$P$600,">=5",Raw_Q!$P$2:$P$600,"<=8")-1,"")) -> 0.96910112 | J4: =IF($A4="","",IFERROR(IF(F4<=0,"N/M",D4/F4),"N/M")) -> 30.281028 | K4: =IF($A4="","",IFERROR(IF(G4<=0,"N/M",D4/G4),"N/M")) -> 26.368945 | L4: =IF($A4="","",IFERROR(IF(H4<=0,"N/M",D4/H4),"N/M")) -> 16.044669 | M4: =IF($A4="","",IFERROR(INDEX(Raw_Est!$C$2:$C$100,MATCH($A4,Raw_Est!$A$2:$A$100,0))/INDEX(Raw_Est!$B$2:$B$100,MATCH($A4,Raw_Est!$A$2:$A$100,0))-1,"")) -> 0.67778104 | N4: =IF($A4="","",IFERROR(IF(OR(NOT(ISNUMBER(J4)),I4<Config!$B$6),"N/M",J4/(I4*100)),"N/M")) -> 0.3124651 | O4: =IF($A4="","",IFERROR(IF(OR(NOT(ISNUMBER(L4)),M4<Config!$B$6),"N/M",L4/(M4*100)),"N/M")) -> 0.23672348 | P4: =IF($A4="","",IFERROR(SUMIFS(Raw_Q!$N$2:$N$600,Raw_Q!$A$2:$A$600,$A4,Raw_Q!$P$2:$P$600,">=1",Raw_Q!$P$2:$P$600,"<=4"),"")) -> 0.28 | Q4: =IF($A4="","",IFERROR(IF(P4=0,"不配息",P4/D4),"")) -> 0.0013190747 | R4: =IF($A4="","",IFERROR(IF(SUMIFS(Raw_Q!$N$2:$N$600,Raw_Q!$A$2:$A$600,$A4,Raw_Q!$P$2:$P$600,">=5",Raw_Q!$P$2:$P$600,"<=8")=0,"",SUMIFS(Raw_Q!$N$2:$N$600,Raw_Q!$A$2:$A$600,$A4,Raw_Q!$P$2:$P$600,">=1",Raw_Q!$P$2:$P$600,"<=4")/SUMIFS(Raw_Q!$N$2:$N$600,Raw_Q!$A$2:$A$600,$A4,Raw_Q!$P$2:$P$600,">=5",Raw_Q!$P$2:$P$600,"<=8")-1),"")) -> 6 | S4: =IF($A4="","",IFERROR(SUMIFS(Raw_Q!$I$2:$I$600,Raw_Q!$A$2:$A$600,$A4,Raw_Q!$P$2:$P$600,1)/SUMIFS(Raw_Q!$I$2:$I$600,Raw_Q!$A$2:$A$600,$A4,Raw_Q!$P$2:$P$600,5)-1,"")) -> 5.4816122 | T4: =IF($A4="","",IFERROR(SUMIFS(Raw_Q!$I$2:$I$600,Raw_Q!$A$2:$A$600,$A4,Raw_Q!$P$2:$P$600,1)/SUMIFS(Raw_Q!$I$2:$I$600,Raw_Q!$A$2:$A$600,$A4,Raw_Q!$P$2:$P$600,2)-1,"")) -> 2.7121853 | U4: =IF($A4="","",IFERROR(SUMIFS(Raw_Q!$I$2:$I$600,Raw_Q!$A$2:$A$600,$A4,Raw_Q!$P$2:$P$600,2)/SUMIFS(Raw_Q!$I$2:$I$600,Raw_Q!$A$2:$A$600,$A4,Raw_Q!$P$2:$P$600,3)-1,"")) -> 0.19798318 | V4: =IF($A4="","",IFERROR((T4-U4)*100,"")) -> 251.42021 | W4: =IF($A4="","",IFERROR(IF(NOT(ISNUMBER(T4)),"",IF(T4>0,IF(V4>0,"成長且加速","成長但減速"),IF(V4>0,"衰退但收斂","衰退且惡化"))),"")) -> 成長且加速 | X4: =IF($A4="","",IFERROR((T4-(SUMIFS(Raw_Q!$I$2:$I$600,Raw_Q!$A$2:$A$600,$A4,Raw_Q!$P$2:$P$600,5)/SUMIFS(Raw_Q!$I$2:$I$600,Raw_Q!$A$2:$A$600,$A4,Raw_Q!$P$2:$P$600,6)-1))*100,"")) -> 265.13392 | Y4: =IF($A4="","",IFERROR(SUMIFS(Raw_Q!$K$2:$K$600,Raw_Q!$A$2:$A$600,$A4,Raw_Q!$P$2:$P$600,1)/SUMIFS(Raw_Q!$K$2:$K$600,Raw_Q!$A$2:$A$600,$A4,Raw_Q!$P$2:$P$600,5)-1,"")) -> 1.1142857 | Z4: =IF($A4="","",IFERROR(SUMIFS(Raw_Q!$J$2:$J$600,Raw_Q!$A$2:$A$600,$A4,Raw_Q!$P$2:$P$600,">=1",Raw_Q!$P$2:$P$600,"<=4")/E4,"")) -> 0.7461773 | AA4: =IF($A4="","",IFERROR(SUMIFS(Raw_Q!$J$2:$J$600,Raw_Q!$A$2:$A$600,$A4,Raw_Q!$P$2:$P$600,">=1",Raw_Q!$P$2:$P$600,"<="&Config!$B$5)/SUMIFS(Raw_Q!$I$2:$I$600,Raw_Q!$A$2:$A$600,$A4,Raw_Q!$P$2:$P$600,">=1",Raw_Q!$P$2:$P$600,"<="&Config!$B$5),"")) -> 0.72932076 | AB4: =IF($A4="","",IFERROR((Z4-AA4)*10000,"")) -> 168.56542 | AC4: =IF($A4="","",IFERROR((SUMIFS(Raw_Q!$J$2:$J$600,Raw_Q!$A$2:$A$600,$A4,Raw_Q!$P$2:$P$600,1)/SUMIFS(Raw_Q!$I$2:$I$600,Raw_Q!$A$2:$A$600,$A4,Raw_Q!$P$2:$P$600,1)-SUMIFS(Raw_Q!$J$2:$J$600,Raw_Q!$A$2:$A$600,$A4,Raw_Q!$P$2:$P$600,5)/SUMIFS(Raw_Q!$I$2:$I$600,Raw_Q!$A$2:$A$600,$A4,Raw_Q!$P$2:$P$600,5))*10000,"")) -> 225.07118 | AD4: =IF($A4="","",IFERROR(SUMIFS(Raw_Q!$M$2:$M$600,Raw_Q!$A$2:$A$600,$A4,Raw_Q!$P$2:$P$600,1)/SUMIFS(Raw_Q!$L$2:$L$600,Raw_Q!$A$2:$A$600,$A4,Raw_Q!$P$2:$P$600,1),"")) -> 9.3855518 | AE4: =IF($A4="","",IFERROR(SUMPRODUCT((Raw_Q!$A$2:$A$600=$A4)*(Raw_Q!$P$2:$P$600>=1)*(Raw_Q!$P$2:$P$600<=4)*Raw_Q!$K$2:$K$600*Raw_Q!$L$2:$L$600),"")) -> 171181.36 | AF4: =IF($A4="","",IFERROR(IF(MIN(SUMIFS(Raw_Q!$M$2:$M$600,Raw_Q!$A$2:$A$600,$A4,Raw_Q!$P$2:$P$600,1),SUMIFS(Raw_Q!$M$2:$M$600,Raw_Q!$A$2:$A$600,$A4,Raw_Q!$P$2:$P$600,5))<=0,"N/M",AE4/((SUMIFS(Raw_Q!$M$2:$M$600,Raw_Q!$A$2:$A$600,$A4,Raw_Q!$P$2:$P$600,1)+SUMIFS(Raw_Q!$M$2:$M$600,Raw_Q!$A$2:$A$600,$A4,Raw_Q!$P$2:$P$600,5))/2)),"N/M")) -> 1.0402526 | AG4: =IF($A4="","",IFERROR(AVERAGE(AO4:AS4),"")) -> 0.6367055 | AH4: =IF($A4="","",IFERROR(IF(AD4<=0,"N/M",INDEX(Raw_Est!$B$2:$B$100,MATCH($A4,Raw_Est!$A$2:$A$100,0))/AD4),"N/M")) -> 0.99161671 | AI4: =IF($A4="","",IFERROR(SUMIFS(Raw_Q!$K$2:$K$600,Raw_Q!$A$2:$A$600,$A4,Raw_Q!$P$2:$P$600,0),"")) -> 2.34 | AJ4: =IF($A4="","",IFERROR(INDEX(Raw_Q!$B$2:$B$600,MATCH($A4&"|"&0,Raw_Q!$Q$2:$Q$600,0)),"")) -> FY2027Q3E | AK4: =IF($A4="","",IFERROR(INDEX(Raw_Q!$G$2:$G$600,MATCH($A4&"|"&0,Raw_Q!$Q$2:$Q$600,0)),"")) -> consensus | AL4: =IF($A4="","",IFERROR(INDEX(Raw_Est!$E$2:$E$100,MATCH($A4,Raw_Est!$A$2:$A$100,0)),"")) -> 42 | AM4: =IF($A4="","",IFERROR(INDEX(Raw_Price!$D$2:$D$100,MATCH($A4,Raw_Price!$A$2:$A$100,0)),"")) -> 46343 | AN4: =IF($A4="","",IFERROR(INDEX(Raw_Price!$E$2:$E$100,MATCH($A4,Raw_Price!$A$2:$A$100,0)),"")) -> 46280 | AO4: =IF($A4="","",IFERROR(IF(MIN(SUMIFS(Raw_Q!$M$2:$M$600,Raw_Q!$A$2:$A$600,$A4,Raw_Q!$P$2:$P$600,1),SUMIFS(Raw_Q!$M$2:$M$600,Raw_Q!$A$2:$A$600,$A4,Raw_Q!$P$2:$P$600,5))<=0,"",SUMPRODUCT((Raw_Q!$A$2:$A$600=$A4)*(Raw_Q!$P$2:$P$600>=1)*(Raw_Q!$P$2:$P$600<=4)*Raw_Q!$K$2:$K$600*Raw_Q!$L$2:$L$600)/((SUMIFS(Raw_Q!$M$2:$M$600,Raw_Q!$A$2:$A$600,$A4,Raw_Q!$P$2:$P$600,1)+SUMIFS(Raw_Q!$M$2:$M$600,Raw_Q!$A$2:$A$600,$A4,Raw_Q!$P$2:$P$600,5))/2)),"")) -> 1.0402526 | AP4: =IF($A4="","",IFERROR(IF(MIN(SUMIFS(Raw_Q!$M$2:$M$600,Raw_Q!$A$2:$A$600,$A4,Raw_Q!$P$2:$P$600,5),SUMIFS(Raw_Q!$M$2:$M$600,Raw_Q!$A$2:$A$600,$A4,Raw_Q!$P$2:$P$600,9))<=0,"",SUMPRODUCT((Raw_Q!$A$2:$A$600=$A4)*(Raw_Q!$P$2:$P$600>=5)*(Raw_Q!$P$2:$P$600<=8)*Raw_Q!$K$2:$K$600*Raw_Q!$L$2:$L$600)/((SUMIFS(Raw_Q!$M$2:$M$600,Raw_Q!$A$2:$A$600,$A4,Raw_Q!$P$2:$P$600,5)+SUMIFS(Raw_Q!$M$2:$M$600,Raw_Q!$A$2:$A$600,$A4,Raw_Q!$P$2:$P$600,9))/2)),"")) -> 0.83089621 | AQ4: =IF($A4="","",IFERROR(IF(MIN(SUMIFS(Raw_Q!$M$2:$M$600,Raw_Q!$A$2:$A$600,$A4,Raw_Q!$P$2:$P$600,9),SUMIFS(Raw_Q!$M$2:$M$600,Raw_Q!$A$2:$A$600,$A4,Raw_Q!$P$2:$P$600,13))<=0,"",SUMPRODUCT((Raw_Q!$A$2:$A$600=$A4)*(Raw_Q!$P$2:$P$600>=9)*(Raw_Q!$P$2:$P$600<=12)*Raw_Q!$K$2:$K$600*Raw_Q!$L$2:$L$600)/((SUMIFS(Raw_Q!$M$2:$M$600,Raw_Q!$A$2:$A$600,$A4,Raw_Q!$P$2:$P$600,9)+SUMIFS(Raw_Q!$M$2:$M$600,Raw_Q!$A$2:$A$600,$A4,Raw_Q!$P$2:$P$600,13))/2)),"")) -> 0.53533354 | AR4: =IF($A4="","",IFERROR(IF(MIN(SUMIFS(Raw_Q!$M$2:$M$600,Raw_Q!$A$2:$A$600,$A4,Raw_Q!$P$2:$P$600,13),SUMIFS(Raw_Q!$M$2:$M$600,Raw_Q!$A$2:$A$600,$A4,Raw_Q!$P$2:$P$600,17))<=0,"",SUMPRODUCT((Raw_Q!$A$2:$A$600=$A4)*(Raw_Q!$P$2:$P$600>=13)*(Raw_Q!$P$2:$P$600<=16)*Raw_Q!$K$2:$K$600*Raw_Q!$L$2:$L$600)/((SUMIFS(Raw_Q!$M$2:$M$600,Raw_Q!$A$2:$A$600,$A4,Raw_Q!$P$2:$P$600,13)+SUMIFS(Raw_Q!$M$2:$M$600,Raw_Q!$A$2:$A$600,$A4,Raw_Q!$P$2:$P$600,17))/2)),"")) -> 0.42790076 | AS4: =IF($A4="","",IFERROR(IF(MIN(SUMIFS(Raw_Q!$M$2:$M$600,Raw_Q!$A$2:$A$600,$A4,Raw_Q!$P$2:$P$600,17),SUMIFS(Raw_Q!$M$2:$M$600,Raw_Q!$A$2:$A$600,$A4,Raw_Q!$P$2:$P$600,21))<=0,"",SUMPRODUCT((Raw_Q!$A$2:$A$600=$A4)*(Raw_Q!$P$2:$P$600>=17)*(Raw_Q!$P$2:$P$600<=20)*Raw_Q!$K$2:$K$600*Raw_Q!$L$2:$L$600)/((SUMIFS(Raw_Q!$M$2:$M$600,Raw_Q!$A$2:$A$600,$A4,Raw_Q!$P$2:$P$600,17)+SUMIFS(Raw_Q!$M$2:$M$600,Raw_Q!$A$2:$A$600,$A4,Raw_Q!$P$2:$P$600,21))/2)),"")) -> 0.34914441
A5: =IF(Tickers!A5="","",Tickers!A5) -> AAOI | B5: =IF($A5="","",IFERROR(INDEX(Tickers!$B$2:$B$100,MATCH($A5,Tickers!$A$2:$A$100,0)),"")) -> Applied Optoelectronics, Inc. | C5: =IF($A5="","",IFERROR(INDEX(Tickers!$D$2:$D$100,MATCH($A5,Tickers!$A$2:$A$100,0)),"")) -> 觀察 | D5: =IF($A5="","",IFERROR(INDEX(Raw_Price!$B$2:$B$100,MATCH($A5,Raw_Price!$A$2:$A$100,0)),"")) -> 96.349998 | E5: =IF($A5="","",IFERROR(SUMIFS(Raw_Q!$I$2:$I$600,Raw_Q!$A$2:$A$600,$A5,Raw_Q!$P$2:$P$600,">=1",Raw_Q!$P$2:$P$600,"<=4"),"")) -> 595.97 | F5: =IF($A5="","",IFERROR(SUMIFS(Raw_Q!$K$2:$K$600,Raw_Q!$A$2:$A$600,$A5,Raw_Q!$P$2:$P$600,">=1",Raw_Q!$P$2:$P$600,"<=4"),"")) -> -0.11 | G5: =IF($A5="","",IFERROR(SUMIFS(Raw_Q!$K$2:$K$600,Raw_Q!$A$2:$A$600,$A5,Raw_Q!$P$2:$P$600,">=0",Raw_Q!$P$2:$P$600,"<=3"),"")) -> 0.12333 | H5: =IF($A5="","",IFERROR(INDEX(Raw_Est!$B$2:$B$100,MATCH($A5,Raw_Est!$A$2:$A$100,0))*MIN(1,MAX(0,(INDEX(Raw_Est!$D$2:$D$100,MATCH($A5,Raw_Est!$A$2:$A$100,0))-TODAY())/Config!$B$8))+INDEX(Raw_Est!$C$2:$C$100,MATCH($A5,Raw_Est!$A$2:$A$100,0))*(1-MIN(1,MAX(0,(INDEX(Raw_Est!$D$2:$D$100,MATCH($A5,Raw_Est!$A$2:$A$100,0))-TODAY())/Config!$B$8))),"")) -> 3.452263 | I5: =IF($A5="","",IFERROR(SUMIFS(Raw_Q!$K$2:$K$600,Raw_Q!$A$2:$A$600,$A5,Raw_Q!$P$2:$P$600,">=1",Raw_Q!$P$2:$P$600,"<=4")/SUMIFS(Raw_Q!$K$2:$K$600,Raw_Q!$A$2:$A$600,$A5,Raw_Q!$P$2:$P$600,">=5",Raw_Q!$P$2:$P$600,"<=8")-1,"")) -> -0.73170732 | J5: =IF($A5="","",IFERROR(IF(F5<=0,"N/M",D5/F5),"N/M")) -> N/M | K5: =IF($A5="","",IFERROR(IF(G5<=0,"N/M",D5/G5),"N/M")) -> 781.23732 | L5: =IF($A5="","",IFERROR(IF(H5<=0,"N/M",D5/H5),"N/M")) -> 27.909229 | M5: =IF($A5="","",IFERROR(INDEX(Raw_Est!$C$2:$C$100,MATCH($A5,Raw_Est!$A$2:$A$100,0))/INDEX(Raw_Est!$B$2:$B$100,MATCH($A5,Raw_Est!$A$2:$A$100,0))-1,"")) -> 5.7676471 | N5: =IF($A5="","",IFERROR(IF(OR(NOT(ISNUMBER(J5)),I5<Config!$B$6),"N/M",J5/(I5*100)),"N/M")) -> N/M | O5: =IF($A5="","",IFERROR(IF(OR(NOT(ISNUMBER(L5)),M5<Config!$B$6),"N/M",L5/(M5*100)),"N/M")) -> 0.04838928 | P5: =IF($A5="","",IFERROR(SUMIFS(Raw_Q!$N$2:$N$600,Raw_Q!$A$2:$A$600,$A5,Raw_Q!$P$2:$P$600,">=1",Raw_Q!$P$2:$P$600,"<=4"),"")) -> 0 | Q5: =IF($A5="","",IFERROR(IF(P5=0,"不配息",P5/D5),"")) -> 不配息 | R5: =IF($A5="","",IFERROR(IF(SUMIFS(Raw_Q!$N$2:$N$600,Raw_Q!$A$2:$A$600,$A5,Raw_Q!$P$2:$P$600,">=5",Raw_Q!$P$2:$P$600,"<=8")=0,"",SUMIFS(Raw_Q!$N$2:$N$600,Raw_Q!$A$2:$A$600,$A5,Raw_Q!$P$2:$P$600,">=1",Raw_Q!$P$2:$P$600,"<=4")/SUMIFS(Raw_Q!$N$2:$N$600,Raw_Q!$A$2:$A$600,$A5,Raw_Q!$P$2:$P$600,">=5",Raw_Q!$P$2:$P$600,"<=8")-1),"")) | S5: =IF($A5="","",IFERROR(SUMIFS(Raw_Q!$I$2:$I$600,Raw_Q!$A$2:$A$600,$A5,Raw_Q!$P$2:$P$600,1)/SUMIFS(Raw_Q!$I$2:$I$600,Raw_Q!$A$2:$A$600,$A5,Raw_Q!$P$2:$P$600,5)-1,"")) -> 0.86418914 | T5: =IF($A5="","",IFERROR(SUMIFS(Raw_Q!$I$2:$I$600,Raw_Q!$A$2:$A$600,$A5,Raw_Q!$P$2:$P$600,1)/SUMIFS(Raw_Q!$I$2:$I$600,Raw_Q!$A$2:$A$600,$A5,Raw_Q!$P$2:$P$600,2)-1,"")) -> 0.26979569 | U5: =IF($A5="","",IFERROR(SUMIFS(Raw_Q!$I$2:$I$600,Raw_Q!$A$2:$A$600,$A5,Raw_Q!$P$2:$P$600,2)/SUMIFS(Raw_Q!$I$2:$I$600,Raw_Q!$A$2:$A$600,$A5,Raw_Q!$P$2:$P$600,3)-1,"")) -> 0.12563862 | V5: =IF($A5="","",IFERROR((T5-U5)*100,"")) -> 14.415707 | W5: =IF($A5="","",IFERROR(IF(NOT(ISNUMBER(T5)),"",IF(T5>0,IF(V5>0,"成長且加速","成長但減速"),IF(V5>0,"衰退但收斂","衰退且惡化"))),"")) -> 成長且加速 | X5: =IF($A5="","",IFERROR((T5-(SUMIFS(Raw_Q!$I$2:$I$600,Raw_Q!$A$2:$A$600,$A5,Raw_Q!$P$2:$P$600,5)/SUMIFS(Raw_Q!$I$2:$I$600,Raw_Q!$A$2:$A$600,$A5,Raw_Q!$P$2:$P$600,6)-1))*100,"")) -> 23.882202 | Y5: =IF($A5="","",IFERROR(SUMIFS(Raw_Q!$K$2:$K$600,Raw_Q!$A$2:$A$600,$A5,Raw_Q!$P$2:$P$600,1)/SUMIFS(Raw_Q!$K$2:$K$600,Raw_Q!$A$2:$A$600,$A5,Raw_Q!$P$2:$P$600,5)-1,"")) -> -1.375 | Z5: =IF($A5="","",IFERROR(SUMIFS(Raw_Q!$J$2:$J$600,Raw_Q!$A$2:$A$600,$A5,Raw_Q!$P$2:$P$600,">=1",Raw_Q!$P$2:$P$600,"<=4")/E5,"")) -> 0.28915885 | AA5: =IF($A5="","",IFERROR(SUMIFS(Raw_Q!$J$2:$J$600,Raw_Q!$A$2:$A$600,$A5,Raw_Q!$P$2:$P$600,">=1",Raw_Q!$P$2:$P$600,"<="&Config!$B$5)/SUMIFS(Raw_Q!$I$2:$I$600,Raw_Q!$A$2:$A$600,$A5,Raw_Q!$P$2:$P$600,">=1",Raw_Q!$P$2:$P$600,"<="&Config!$B$5),"")) -> 0.25346476 | AB5: =IF($A5="","",IFERROR((Z5-AA5)*10000,"")) -> 356.94087 | AC5: =IF($A5="","",IFERROR((SUMIFS(Raw_Q!$J$2:$J$600,Raw_Q!$A$2:$A$600,$A5,Raw_Q!$P$2:$P$600,1)/SUMIFS(Raw_Q!$I$2:$I$600,Raw_Q!$A$2:$A$600,$A5,Raw_Q!$P$2:$P$600,1)-SUMIFS(Raw_Q!$J$2:$J$600,Raw_Q!$A$2:$A$600,$A5,Raw_Q!$P$2:$P$600,5)/SUMIFS(Raw_Q!$I$2:$I$600,Raw_Q!$A$2:$A$600,$A5,Raw_Q!$P$2:$P$600,5))*10000,"")) -> -254.52329 | AD5: =IF($A5="","",IFERROR(SUMIFS(Raw_Q!$M$2:$M$600,Raw_Q!$A$2:$A$600,$A5,Raw_Q!$P$2:$P$600,1)/SUMIFS(Raw_Q!$L$2:$L$600,Raw_Q!$A$2:$A$600,$A5,Raw_Q!$P$2:$P$600,1),"")) -> 20.449502 | AE5: =IF($A5="","",IFERROR(SUMPRODUCT((Raw_Q!$A$2:$A$600=$A5)*(Raw_Q!$P$2:$P$600>=1)*(Raw_Q!$P$2:$P$600<=4)*Raw_Q!$K$2:$K$600*Raw_Q!$L$2:$L$600),"")) -> -6.82749 | AF5: =IF($A5="","",IFERROR(IF(MIN(SUMIFS(Raw_Q!$M$2:$M$600,Raw_Q!$A$2:$A$600,$A5,Raw_Q!$P$2:$P$600,1),SUMIFS(Raw_Q!$M$2:$M$600,Raw_Q!$A$2:$A$600,$A5,Raw_Q!$P$2:$P$600,5))<=0,"N/M",AE5/((SUMIFS(Raw_Q!$M$2:$M$600,Raw_Q!$A$2:$A$600,$A5,Raw_Q!$P$2:$P$600,1)+SUMIFS(Raw_Q!$M$2:$M$600,Raw_Q!$A$2:$A$600,$A5,Raw_Q!$P$2:$P$600,5))/2)),"N/M")) -> -0.0065240998 | AG5: =IF($A5="","",IFERROR(AVERAGE(AO5:AS5),"")) -> -0.12618364 | AH5: =IF($A5="","",IFERROR(IF(AD5<=0,"N/M",INDEX(Raw_Est!$B$2:$B$100,MATCH($A5,Raw_Est!$A$2:$A$100,0))/AD5),"N/M")) -> 0.033252643 | AI5: =IF($A5="","",IFERROR(SUMIFS(Raw_Q!$K$2:$K$600,Raw_Q!$A$2:$A$600,$A5,Raw_Q!$P$2:$P$600,0),"")) -> 0.14333 | AJ5: =IF($A5="","",IFERROR(INDEX(Raw_Q!$B$2:$B$600,MATCH($A5&"|"&0,Raw_Q!$Q$2:$Q$600,0)),"")) -> FY2026Q3E | AK5: =IF($A5="","",IFERROR(INDEX(Raw_Q!$G$2:$G$600,MATCH($A5&"|"&0,Raw_Q!$Q$2:$Q$600,0)),"")) -> consensus | AL5: =IF($A5="","",IFERROR(INDEX(Raw_Est!$E$2:$E$100,MATCH($A5,Raw_Est!$A$2:$A$100,0)),"")) -> 6 | AM5: =IF($A5="","",IFERROR(INDEX(Raw_Price!$D$2:$D$100,MATCH($A5,Raw_Price!$A$2:$A$100,0)),"")) -> 46331 | AN5: =IF($A5="","",IFERROR(INDEX(Raw_Price!$E$2:$E$100,MATCH($A5,Raw_Price!$A$2:$A$100,0)),"")) -> 46280 | AO5: =IF($A5="","",IFERROR(IF(MIN(SUMIFS(Raw_Q!$M$2:$M$600,Raw_Q!$A$2:$A$600,$A5,Raw_Q!$P$2:$P$600,1),SUMIFS(Raw_Q!$M$2:$M$600,Raw_Q!$A$2:$A$600,$A5,Raw_Q!$P$2:$P$600,5))<=0,"",SUMPRODUCT((Raw_Q!$A$2:$A$600=$A5)*(Raw_Q!$P$2:$P$600>=1)*(Raw_Q!$P$2:$P$600<=4)*Raw_Q!$K$2:$K$600*Raw_Q!$L$2:$L$600)/((SUMIFS(Raw_Q!$M$2:$M$600,Raw_Q!$A$2:$A$600,$A5,Raw_Q!$P$2:$P$600,1)+SUMIFS(Raw_Q!$M$2:$M$600,Raw_Q!$A$2:$A$600,$A5,Raw_Q!$P$2:$P$600,5))/2)),"")) -> -0.0065240998 | AP5: =IF($A5="","",IFERROR(IF(MIN(SUMIFS(Raw_Q!$M$2:$M$600,Raw_Q!$A$2:$A$600,$A5,Raw_Q!$P$2:$P$600,5),SUMIFS(Raw_Q!$M$2:$M$600,Raw_Q!$A$2:$A$600,$A5,Raw_Q!$P$2:$P$600,9))<=0,"",SUMPRODUCT((Raw_Q!$A$2:$A$600=$A5)*(Raw_Q!$P$2:$P$600>=5)*(Raw_Q!$P$2:$P$600<=8)*Raw_Q!$K$2:$K$600*Raw_Q!$L$2:$L$600)/((SUMIFS(Raw_Q!$M$2:$M$600,Raw_Q!$A$2:$A$600,$A5,Raw_Q!$P$2:$P$600,5)+SUMIFS(Raw_Q!$M$2:$M$600,Raw_Q!$A$2:$A$600,$A5,Raw_Q!$P$2:$P$600,9))/2)),"")) -> -0.064954612 | AQ5: =IF($A5="","",IFERROR(IF(MIN(SUMIFS(Raw_Q!$M$2:$M$600,Raw_Q!$A$2:$A$600,$A5,Raw_Q!$P$2:$P$600,9),SUMIFS(Raw_Q!$M$2:$M$600,Raw_Q!$A$2:$A$600,$A5,Raw_Q!$P$2:$P$600,13))<=0,"",SUMPRODUCT((Raw_Q!$A$2:$A$600=$A5)*(Raw_Q!$P$2:$P$600>=9)*(Raw_Q!$P$2:$P$600<=12)*Raw_Q!$K$2:$K$600*Raw_Q!$L$2:$L$600)/((SUMIFS(Raw_Q!$M$2:$M$600,Raw_Q!$A$2:$A$600,$A5,Raw_Q!$P$2:$P$600,9)+SUMIFS(Raw_Q!$M$2:$M$600,Raw_Q!$A$2:$A$600,$A5,Raw_Q!$P$2:$P$600,13))/2)),"")) -> -0.12097587 | AR5: =IF($A5="","",IFERROR(IF(MIN(SUMIFS(Raw_Q!$M$2:$M$600,Raw_Q!$A$2:$A$600,$A5,Raw_Q!$P$2:$P$600,13),SUMIFS(Raw_Q!$M$2:$M$600,Raw_Q!$A$2:$A$600,$A5,Raw_Q!$P$2:$P$600,17))<=0,"",SUMPRODUCT((Raw_Q!$A$2:$A$600=$A5)*(Raw_Q!$P$2:$P$600>=13)*(Raw_Q!$P$2:$P$600<=16)*Raw_Q!$K$2:$K$600*Raw_Q!$L$2:$L$600)/((SUMIFS(Raw_Q!$M$2:$M$600,Raw_Q!$A$2:$A$600,$A5,Raw_Q!$P$2:$P$600,13)+SUMIFS(Raw_Q!$M$2:$M$600,Raw_Q!$A$2:$A$600,$A5,Raw_Q!$P$2:$P$600,17))/2)),"")) -> -0.1834917 | AS5: =IF($A5="","",IFERROR(IF(MIN(SUMIFS(Raw_Q!$M$2:$M$600,Raw_Q!$A$2:$A$600,$A5,Raw_Q!$P$2:$P$600,17),SUMIFS(Raw_Q!$M$2:$M$600,Raw_Q!$A$2:$A$600,$A5,Raw_Q!$P$2:$P$600,21))<=0,"",SUMPRODUCT((Raw_Q!$A$2:$A$600=$A5)*(Raw_Q!$P$2:$P$600>=17)*(Raw_Q!$P$2:$P$600<=20)*Raw_Q!$K$2:$K$600*Raw_Q!$L$2:$L$600)/((SUMIFS(Raw_Q!$M$2:$M$600,Raw_Q!$A$2:$A$600,$A5,Raw_Q!$P$2:$P$600,17)+SUMIFS(Raw_Q!$M$2:$M$600,Raw_Q!$A$2:$A$600,$A5,Raw_Q!$P$2:$P$600,21))/2)),"")) -> -0.2549719
